Workbook
Name lista: _xludf.REPLACE(_xludf.GET.WORKBOOK(1),1,_xludf.FIND("]",_xludf.GET.WORKBOOK(1)),"")
Name lista: _xludf.REPLACE(_xludf.GET.WORKBOOK(1),1,_xludf.FIND("]",_xludf.GET.WORKBOOK(1)),"")
Name lista: _xludf.REPLACE(_xludf.GET.WORKBOOK(1),1,_xludf.FIND("]",_xludf.GET.WORKBOOK(1)),"")
Name lista: _xludf.REPLACE(_xludf.GET.WORKBOOK(1),1,_xludf.FIND("]",_xludf.GET.WORKBOOK(1)),"")
Name lista: _xludf.REPLACE(_xludf.GET.WORKBOOK(1),1,_xludf.FIND("]",_xludf.GET.WORKBOOK(1)),"")
Name lista: _xludf.REPLACE(_xludf.GET.WORKBOOK(1),1,_xludf.FIND("]",_xludf.GET.WORKBOOK(1)),"")
Name lista: _xludf.REPLACE(_xludf.GET.WORKBOOK(1),1,_xludf.FIND("]",_xludf.GET.WORKBOOK(1)),"")
Name lista: _xludf.REPLACE(_xludf.GET.WORKBOOK(1),1,_xludf.FIND("]",_xludf.GET.WORKBOOK(1)),"")
Name lista: _xludf.REPLACE(_xludf.GET.WORKBOOK(1),1,_xludf.FIND("]",_xludf.GET.WORKBOOK(1)),"")
Name lista: _xludf.REPLACE(_xludf.GET.WORKBOOK(1),1,_xludf.FIND("]",_xludf.GET.WORKBOOK(1)),"")
Name lista: _xludf.REPLACE(_xludf.GET.WORKBOOK(1),1,_xludf.FIND("]",_xludf.GET.WORKBOOK(1)),"")
Name lista: _xludf.REPLACE(_xludf.GET.WORKBOOK(1),1,_xludf.FIND("]",_xludf.GET.WORKBOOK(1)),"")
Name lista: _xludf.REPLACE(_xludf.GET.WORKBOOK(1),1,_xludf.FIND("]",_xludf.GET.WORKBOOK(1)),"")
Name lista: _xludf.REPLACE(_xludf.GET.WORKBOOK(1),1,_xludf.FIND("]",_xludf.GET.WORKBOOK(1)),"")
Name lista: _xludf.REPLACE(_xludf.GET.WORKBOOK(1),1,_xludf.FIND("]",_xludf.GET.WORKBOOK(1)),"")
Name lista: _xludf.REPLACE(_xludf.GET.WORKBOOK(1),1,_xludf.FIND("]",_xludf.GET.WORKBOOK(1)),"")
Name lista: _xludf.REPLACE(_xludf.GET.WORKBOOK(1),1,_xludf.FIND("]",_xludf.GET.WORKBOOK(1)),"")

Sheet Brownie 14 cm
B1: Ingrediente | C1: Gramos | D1: Precio | E1: Total Recetas | F1: Cantidad de Recetas: | G1: 1
B2: Manteca | C2: 60 | D2: =C2*'Valores y Totales'!C2 -> 660 | E2: =G$1*C2 -> 60
B3: Harina 0000 | C3: 0 | D3: =C3*'Valores y Totales'!C3 -> 0 | E3: =G$1*C3 -> 0
B4: Azucar Impalpable | C4: 0 | D4: =C4*'Valores y Totales'!C4 -> 0 | E4: =G$1*C4 -> 0
B5: Cacao | C5: 0 | D5: =C5*'Valores y Totales'!C5 -> 0 | E5: =G$1*C5 -> 0
B6: Huevo (unidad) | C6: 0 | D6: =C6*'Valores y Totales'!B6 -> 0 | E6: =G$1*C6 -> 0
B7: Azucar Común | C7: 0 | D7: =C7*'Valores y Totales'!C7 -> 0 | E7: =G$1*C7 -> 0
B8: Maizena | C8: 0 | D8: =C8*'Valores y Totales'!C8 -> 0 | E8: =G$1*C8 -> 0
B9: Chocolate Taza | C9: 150 | D9: =C9*'Valores y Totales'!C9 -> 3900 | E9: =G$1*C9 -> 150
B10: Nueces | C10: 0 | D10: =C10*'Valores y Totales'!C10 -> 0 | E10: =G$1*C10 -> 0
B11: Dulce de Leche | C11: 400 | D11: =C11*'Valores y Totales'!C11 -> 2000 | E11: =G$1*C11 -> 400
B12: Crema | C12: 120 | D12: =C12*'Valores y Totales'!C12 -> 1200 | E12: =G$1*C12 -> 120
B13: Harina Leudante | C13: 0 | D13: =C13*'Valores y Totales'!C13 -> 0 | E13: =G$1*C13 -> 0
B14: Limon | C14: 0 | D14: =C14*'Valores y Totales'!C14 -> 0 | E14: =G$1*C14 -> 0
B15: Bicarbonato | C15: 0 | D15: =C15*'Valores y Totales'!C15 -> 0 | E15: =G$1*C15 -> 0
B16: Polveo Hornear | C16: 0 | D16: =C16*'Valores y Totales'!C16 -> 0 | E16: =G$1*C16 -> 0
B17: Leche | C17: 0 | D17: =C17*'Valores y Totales'!C17 -> 0 | E17: =G$1*C17 -> 0
B18: Conac | C18: 30 | D18: =C18*'Valores y Totales'!C18 -> 400 | E18: =G$1*C18 -> 30
... B26: Chocochips | C26: 0 | D26: =C26*'Valores y Totales'!C26 -> 0 | E26: =G$1*C26 -> 0
C28: Una Receta | D28: Por Cantidad de Recetas
B29: Cantidad de Masitas | C29: 1 | D29: =C29*G$1 -> 1
B30: Costo Receta | C30: =SUM(D2:D26) -> 8160 | D30: =C30*G$1 -> 8160
B31: Costo Docena | C31: =C30/C29*12 -> 97920 | D31: =C31 -> 97920
B32: Costo Individual | C32: =C30/C29 -> 8160 | D32: =C32 -> 8160

Sheet Tarta de Coco placa 20x30
B1: Ingrediente | C1: Gramos | D1: Precio | E1: Total Recetas | F1: Cantidad de Recetas: | G1: 1
B2: Manteca | C2: 155 | D2: =C2*'Valores y Totales'!C2 -> 1705 | E2: =G$1*C2 -> 155
B3: Harina 0000 | C3: 250 | D3: =C3*'Valores y Totales'!C3 -> 275 | E3: =G$1*C3 -> 250
B4: Azucar Impalpable | C4: 150 | D4: =C4*'Valores y Totales'!C4 -> 225 | E4: =G$1*C4 -> 150
B5: Cacao | C5: 0 | D5: =C5*'Valores y Totales'!C5 -> 0 | E5: =G$1*C5 -> 0
B6: Huevo (unidad) | C6: 3 | D6: =C6*'Valores y Totales'!B6 -> 630 | E6: =G$1*C6 -> 3
B7: Azucar Común | C7: 75 | D7: =C7*'Valores y Totales'!C7 -> 105 | E7: =G$1*C7 -> 75
B8: Maizena | C8: 0 | D8: =C8*'Valores y Totales'!C8 -> 0 | E8: =G$1*C8 -> 0
B9: Chocolate Taza | C9: 0 | D9: =C9*'Valores y Totales'!C9 -> 0 | E9: =G$1*C9 -> 0
B10: Nueces | C10: 0 | D10: =C10*'Valores y Totales'!C10 -> 0 | E10: =G$1*C10 -> 0
B11: Dulce de Leche | C11: 700 | D11: =C11*'Valores y Totales'!C11 -> 3500 | E11: =G$1*C11 -> 700
B12: Crema | C12: 0 | D12: =C12*'Valores y Totales'!C12 -> 0 | E12: =G$1*C12 -> 0
B13: Harina Leudante | C13: 0 | D13: =C13*'Valores y Totales'!C13 -> 0 | E13: =G$1*C13 -> 0
B14: Limon | C14: 1 | D14: =C14*'Valores y Totales'!C14 -> 500 | E14: =G$1*C14 -> 1
B15: Bicarbonato | C15: 0 | D15: =C15*'Valores y Totales'!C15 -> 0 | E15: =G$1*C15 -> 0
B16: Polveo Hornear | C16: 7 | D16: =C16*'Valores y Totales'!C16 -> 28 | E16: =G$1*C16 -> 7
B17: Leche | C17: 0 | D17: =C17*'Valores y Totales'!C17 -> 0 | E17: =G$1*C17 -> 0
B18: Conac | C18: 0 | D18: =C18*'Valores y Totales'!C18 -> 0 | E18: =G$1*C18 -> 0
... B24: Pasas | C24: 0 | D24: =C24*'Valores y Totales'!C24 -> 0 | E24: =G$1*C24 -> 0
B25: Coco | C25: 150 | D25: =C25*'Valores y Totales'!C44 -> 1800 | E25: =G$1*C25 -> 150
B26: Dulce de Membrillo | C26: 0 | D26: =C26*'Valores y Totales'!C45 -> 0 | E26: =G$1*C26 -> 0
B27: Chocochips | C27: 0 | D27: =C27*'Valores y Totales'!C26 -> 0 | E27: =G$1*C27 -> 0
C29: Una Receta | D29: Por Cantidad de Recetas
B30: Cantidad de Masitas | C30: 30 | D30: 70
B31: Costo Receta | C31: =SUM(D2:D27) -> 8768 | D31: =C31*G$1 -> 8768
B32: Costo por unidad | C32: =C31/C30 -> 292.26667 | D32: =C32 -> 292.26667
B33: Costo Individual | C33: =C31/C30 -> 292.26667 | D33: =C33 -> 292.26667

Sheet Minifrola-DDL-Coco
B1: Ingrediente | C1: Gramos | D1: Precio | E1: Total Recetas | F1: Cantidad de Recetas: | G1: 1
B2: Manteca | C2: 310 | D2: =C2*'Valores y Totales'!C2 -> 3410 | E2: =G$1*C2 -> 310
B3: Harina 0000 | C3: 500 | D3: =C3*'Valores y Totales'!C3 -> 550 | E3: =G$1*C3 -> 500
B4: Azucar Impalpable | C4: 150 | D4: =C4*'Valores y Totales'!C4 -> 225 | E4: =G$1*C4 -> 150
B5: Cacao | C5: 0 | D5: =C5*'Valores y Totales'!C5 -> 0 | E5: =G$1*C5 -> 0
B6: Huevo (unidad) | C6: 6 | D6: =C6*'Valores y Totales'!B6 -> 1260 | E6: =G$1*C6 -> 6
B7: Azucar Común | C7: 150 | D7: =C7*'Valores y Totales'!C7 -> 210 | E7: =G$1*C7 -> 150
B8: Maizena | C8: 0 | D8: =C8*'Valores y Totales'!C8 -> 0 | E8: =G$1*C8 -> 0
B9: Chocolate Taza | C9: 0 | D9: =C9*'Valores y Totales'!C9 -> 0 | E9: =G$1*C9 -> 0
B10: Nueces | C10: 0 | D10: =C10*'Valores y Totales'!C10 -> 0 | E10: =G$1*C10 -> 0
B11: Dulce de Leche | C11: 1200 | D11: =C11*'Valores y Totales'!C11 -> 6000 | E11: =G$1*C11 -> 1200
B12: Crema | C12: 0 | D12: =C12*'Valores y Totales'!C12 -> 0 | E12: =G$1*C12 -> 0
B13: Harina Leudante | C13: 0 | D13: =C13*'Valores y Totales'!C13 -> 0 | E13: =G$1*C13 -> 0
B14: Limon | C14: 1 | D14: =C14*'Valores y Totales'!C14 -> 500 | E14: =G$1*C14 -> 1
B15: Bicarbonato | C15: 0 | D15: =C15*'Valores y Totales'!C15 -> 0 | E15: =G$1*C15 -> 0
B16: Polveo Hornear | C16: 15 | D16: =C16*'Valores y Totales'!C16 -> 60 | E16: =G$1*C16 -> 15
B17: Leche | C17: 0 | D17: =C17*'Valores y Totales'!C17 -> 0 | E17: =G$1*C17 -> 0
B18: Conac | C18: 0 | D18: =C18*'Valores y Totales'!C18 -> 0 | E18: =G$1*C18 -> 0
... B24: Pasas | C24: 0 | D24: =C24*'Valores y Totales'!C24 -> 0 | E24: =G$1*C24 -> 0
B25: Coco | C25: 300 | D25: =C25*'Valores y Totales'!C44 -> 3600 | E25: =G$1*C25 -> 300
B26: Dulce de Membrillo | C26: 0 | D26: =C26*'Valores y Totales'!C45 -> 0 | E26: =G$1*C26 -> 0
B27: Chocochips | C27: 0 | D27: =C27*'Valores y Totales'!C26 -> 0 | E27: =G$1*C27 -> 0
C29: Una Receta | D29: Por Cantidad de Recetas
B30: Cantidad de Masitas | C30: 15 | D30: =C30*G$1 -> 15 | E30: de 8 cm
B31: Costo Receta | C31: =SUM(D2:D27) -> 15815 | D31: =C31*G$1 -> 15815
B32: Costo por unidad | C32: =C31/C30 -> 1054.3333 | D32: =C32 -> 1054.3333
B33: Costo Individual | C33: =C31/C30 -> 1054.3333 | D33: =C33 -> 1054.3333

Sheet Minifrola-Manzana
B1: Ingrediente | C1: Gramos | D1: Precio | E1: Total Recetas | F1: Cantidad de Recetas: | G1: 1
B2: Manteca | C2: 350 | D2: =C2*'Valores y Totales'!C2 -> 3850 | E2: =G$1*C2 -> 350
B3: Harina 0000 | C3: 500 | D3: =C3*'Valores y Totales'!C3 -> 550 | E3: =G$1*C3 -> 500
B4: Azucar Impalpable | C4: 150 | D4: =C4*'Valores y Totales'!C4 -> 225 | E4: =G$1*C4 -> 150
B5: Cacao | C5: 0 | D5: =C5*'Valores y Totales'!C5 -> 0 | E5: =G$1*C5 -> 0
B6: Huevo (unidad) | C6: 2 | D6: =C6*'Valores y Totales'!B6 -> 420 | E6: =G$1*C6 -> 2
B7: Azucar Común | C7: 160 | D7: =C7*'Valores y Totales'!C7 -> 224 | E7: =G$1*C7 -> 160
B8: Maizena | C8: 0 | D8: =C8*'Valores y Totales'!C8 -> 0 | E8: =G$1*C8 -> 0
B9: Chocolate Taza | C9: 0 | D9: =C9*'Valores y Totales'!C9 -> 0 | E9: =G$1*C9 -> 0
B10: Nueces | C10: 0 | D10: =C10*'Valores y Totales'!C10 -> 0 | E10: =G$1*C10 -> 0
B11: Dulce de Leche | C11: 0 | D11: =C11*'Valores y Totales'!C11 -> 0 | E11: =G$1*C11 -> 0
B12: Crema | C12: 0 | D12: =C12*'Valores y Totales'!C12 -> 0 | E12: =G$1*C12 -> 0
B13: Harina Leudante | C13: 0 | D13: =C13*'Valores y Totales'!C13 -> 0 | E13: =G$1*C13 -> 0
B14: Limon | C14: 1 | D14: =C14*'Valores y Totales'!C14 -> 500 | E14: =G$1*C14 -> 1
B15: Bicarbonato | C15: 0 | D15: =C15*'Valores y Totales'!C15 -> 0 | E15: =G$1*C15 -> 0
B16: Polveo Hornear | C16: 15 | D16: =C16*'Valores y Totales'!C16 -> 60 | E16: =G$1*C16 -> 15
B17: Leche | C17: 0 | D17: =C17*'Valores y Totales'!C17 -> 0 | E17: =G$1*C17 -> 0
B18: Conac | C18: 0 | D18: =C18*'Valores y Totales'!C18 -> 0 | E18: =G$1*C18 -> 0
... B25: Yogur | C25: 0 | D25: =C25*'Valores y Totales'!C25 -> 0 | E25: =G$1*C25 -> 0
B26: Manzana | C26: 10 | D26: =C26*'Valores y Totales'!C49 -> 6000 | E26: =G$1*C26 -> 10
B27: Chocochips | C27: 0 | D27: =C27*'Valores y Totales'!C26 -> 0 | E27: =G$1*C27 -> 0
C29: Una Receta | D29: Por Cantidad de Recetas
B30: Cantidad de Masitas | C30: 15 | D30: =C30*G$1 -> 15 | E30: de 8 cm
B31: Costo Receta | C31: =SUM(D2:D27) -> 11829 | D31: =C31*G$1 -> 11829
B32: Costo por unidad | C32: =C31/C30 -> 788.6 | D32: =C32 -> 788.6
B33: Costo Individual | C33: =C31/C30 -> 788.6 | D33: =C33 -> 788.6

Sheet Minifrola-DDL
B1: Ingrediente | C1: Gramos | D1: Precio | E1: Total Recetas | F1: Cantidad de Recetas: | G1: 1
B2: Manteca | C2: 250 | D2: =C2*'Valores y Totales'!C2 -> 2750 | E2: =G$1*C2 -> 250
B3: Harina 0000 | C3: 500 | D3: =C3*'Valores y Totales'!C3 -> 550 | E3: =G$1*C3 -> 500
B4: Azucar Impalpable | C4: 150 | D4: =C4*'Valores y Totales'!C4 -> 225 | E4: =G$1*C4 -> 150
B5: Cacao | C5: 0 | D5: =C5*'Valores y Totales'!C5 -> 0 | E5: =G$1*C5 -> 0
B6: Huevo (unidad) | C6: 2 | D6: =C6*'Valores y Totales'!B6 -> 420 | E6: =G$1*C6 -> 2
B7: Azucar Común | C7: 0 | D7: =C7*'Valores y Totales'!C7 -> 0 | E7: =G$1*C7 -> 0
B8: Maizena | C8: 0 | D8: =C8*'Valores y Totales'!C8 -> 0 | E8: =G$1*C8 -> 0
B9: Chocolate Taza | C9: 0 | D9: =C9*'Valores y Totales'!C9 -> 0 | E9: =G$1*C9 -> 0
B10: Nueces | C10: 0 | D10: =C10*'Valores y Totales'!C10 -> 0 | E10: =G$1*C10 -> 0
B11: Dulce de Leche | C11: 1200 | D11: =C11*'Valores y Totales'!C11 -> 6000 | E11: =G$1*C11 -> 1200
B12: Crema | C12: 0 | D12: =C12*'Valores y Totales'!C12 -> 0 | E12: =G$1*C12 -> 0
B13: Harina Leudante | C13: 0 | D13: =C13*'Valores y Totales'!C13 -> 0 | E13: =G$1*C13 -> 0
B14: Limon | C14: 1 | D14: =C14*'Valores y Totales'!C14 -> 500 | E14: =G$1*C14 -> 1
B15: Bicarbonato | C15: 0 | D15: =C15*'Valores y Totales'!C15 -> 0 | E15: =G$1*C15 -> 0
B16: Polveo Hornear | C16: 15 | D16: =C16*'Valores y Totales'!C16 -> 60 | E16: =G$1*C16 -> 15
B17: Leche | C17: 0 | D17: =C17*'Valores y Totales'!C17 -> 0 | E17: =G$1*C17 -> 0
B18: Conac | C18: 0 | D18: =C18*'Valores y Totales'!C18 -> 0 | E18: =G$1*C18 -> 0
... B25: Yogur | C25: 0 | D25: =C25*'Valores y Totales'!C25 -> 0 | E25: =G$1*C25 -> 0
B26: Dulce de Membrillo | C26: 0 | D26: =C26*'Valores y Totales'!C45 -> 0 | E26: =G$1*C26 -> 0
B27: Chocochips | C27: 0 | D27: =C27*'Valores y Totales'!C26 -> 0 | E27: =G$1*C27 -> 0
C29: Una Receta | D29: Por Cantidad de Recetas
B30: Cantidad de Masitas | C30: 15 | D30: =C30*G$1 -> 15 | E30: de 8 cm
B31: Costo Receta | C31: =SUM(D2:D27) -> 10505 | D31: =C31*G$1 -> 10505
B32: Costo por unidad | C32: =C31/C30 -> 700.33333 | D32: =C32 -> 700.33333
B33: Costo Individual | C33: =C31/C30 -> 700.33333 | D33: =C33 -> 700.33333

Sheet Pastafrola Membrillo
B1: Ingrediente | C1: Gramos | D1: Precio | E1: Total Recetas | F1: Cantidad de Recetas: | G1: 1
B2: Manteca | C2: 250 | D2: =C2*'Valores y Totales'!C2 -> 2750 | E2: =G$1*C2 -> 250
B3: Harina 0000 | C3: 500 | D3: =C3*'Valores y Totales'!C3 -> 550 | E3: =G$1*C3 -> 500
B4: Azucar Impalpable | C4: 150 | D4: =C4*'Valores y Totales'!C4 -> 225 | E4: =G$1*C4 -> 150
B5: Cacao | C5: 0 | D5: =C5*'Valores y Totales'!C5 -> 0 | E5: =G$1*C5 -> 0
B6: Huevo (unidad) | C6: 2 | D6: =C6*'Valores y Totales'!B6 -> 420 | E6: =G$1*C6 -> 2
B7: Azucar Común | C7: 0 | D7: =C7*'Valores y Totales'!C7 -> 0 | E7: =G$1*C7 -> 0
B8: Maizena | C8: 0 | D8: =C8*'Valores y Totales'!C8 -> 0 | E8: =G$1*C8 -> 0
B9: Chocolate Taza | C9: 0 | D9: =C9*'Valores y Totales'!C9 -> 0 | E9: =G$1*C9 -> 0
B10: Nueces | C10: 0 | D10: =C10*'Valores y Totales'!C10 -> 0 | E10: =G$1*C10 -> 0
B11: Dulce de Leche | C11: 0 | D11: =C11*'Valores y Totales'!C11 -> 0 | E11: =G$1*C11 -> 0
B12: Crema | C12: 0 | D12: =C12*'Valores y Totales'!C12 -> 0 | E12: =G$1*C12 -> 0
B13: Harina Leudante | C13: 0 | D13: =C13*'Valores y Totales'!C13 -> 0 | E13: =G$1*C13 -> 0
B14: Limon | C14: 1 | D14: =C14*'Valores y Totales'!C14 -> 500 | E14: =G$1*C14 -> 1
B15: Bicarbonato | C15: 0 | D15: =C15*'Valores y Totales'!C15 -> 0 | E15: =G$1*C15 -> 0
B16: Polveo Hornear | C16: 10 | D16: =C16*'Valores y Totales'!C16 -> 40 | E16: =G$1*C16 -> 10
B17: Leche | C17: 0 | D17: =C17*'Valores y Totales'!C17 -> 0 | E17: =G$1*C17 -> 0
B18: Conac | C18: 0 | D18: =C18*'Valores y Totales'!C18 -> 0 | E18: =G$1*C18 -> 0
... B25: Yogur | C25: 0 | D25: =C25*'Valores y Totales'!C25 -> 0 | E25: =G$1*C25 -> 0
B26: Dulce de Membrillo | C26: 1200 | D26: =C26*'Valores y Totales'!C45 -> 7200 | E26: =G$1*C26 -> 1200
B27: Chocochips | C27: 0 | D27: =C27*'Valores y Totales'!C26 -> 0 | E27: =G$1*C27 -> 0
C29: Una Receta | D29: Por Cantidad de Recetas
B30: Cantidad de Masitas | C30: 60 | D30: =C30*G$1 -> 60
B31: Costo Receta | C31: =SUM(D2:D27) -> 11685 | D31: =C31*G$1 -> 11685
B32: Costo por unidad | C32: =C31/C30 -> 194.75 | D32: =C32 -> 194.75
B33: Costo Individual | C33: =C31/C30 -> 194.75 | D33: =C33 -> 194.75

Sheet Minifrola-Membrillo
B1: Ingrediente | C1: Gramos | D1: Precio | E1: Total Recetas | F1: Cantidad de Recetas: | G1: 1
B2: Manteca | C2: 250 | D2: =C2*'Valores y Totales'!C2 -> 2750 | E2: =G$1*C2 -> 250
B3: Harina 0000 | C3: 500 | D3: =C3*'Valores y Totales'!C3 -> 550 | E3: =G$1*C3 -> 500
B4: Azucar Impalpable | C4: 150 | D4: =C4*'Valores y Totales'!C4 -> 225 | E4: =G$1*C4 -> 150
B5: Cacao | C5: 0 | D5: =C5*'Valores y Totales'!C5 -> 0 | E5: =G$1*C5 -> 0
B6: Huevo (unidad) | C6: 2 | D6: =C6*'Valores y Totales'!B6 -> 420 | E6: =G$1*C6 -> 2
B7: Azucar Común | C7: 0 | D7: =C7*'Valores y Totales'!C7 -> 0 | E7: =G$1*C7 -> 0
B8: Maizena | C8: 0 | D8: =C8*'Valores y Totales'!C8 -> 0 | E8: =G$1*C8 -> 0
B9: Chocolate Taza | C9: 0 | D9: =C9*'Valores y Totales'!C9 -> 0 | E9: =G$1*C9 -> 0
B10: Nueces | C10: 0 | D10: =C10*'Valores y Totales'!C10 -> 0 | E10: =G$1*C10 -> 0
B11: Dulce de Leche | C11: 0 | D11: =C11*'Valores y Totales'!C11 -> 0 | E11: =G$1*C11 -> 0
B12: Crema | C12: 0 | D12: =C12*'Valores y Totales'!C12 -> 0 | E12: =G$1*C12 -> 0
B13: Harina Leudante | C13: 0 | D13: =C13*'Valores y Totales'!C13 -> 0 | E13: =G$1*C13 -> 0
B14: Limon | C14: 1 | D14: =C14*'Valores y Totales'!C14 -> 500 | E14: =G$1*C14 -> 1
B15: Bicarbonato | C15: 0 | D15: =C15*'Valores y Totales'!C15 -> 0 | E15: =G$1*C15 -> 0
B16: Polveo Hornear | C16: 10 | D16: =C16*'Valores y Totales'!C16 -> 40 | E16: =G$1*C16 -> 10
B17: Leche | C17: 0 | D17: =C17*'Valores y Totales'!C17 -> 0 | E17: =G$1*C17 -> 0
B18: Conac | C18: 0 | D18: =C18*'Valores y Totales'!C18 -> 0 | E18: =G$1*C18 -> 0
... B25: Yogur | C25: 0 | D25: =C25*'Valores y Totales'!C25 -> 0 | E25: =G$1*C25 -> 0
B26: Dulce de Membrillo | C26: 1200 | D26: =C26*'Valores y Totales'!C45 -> 7200 | E26: =G$1*C26 -> 1200
B27: Chocochips | C27: 0 | D27: =C27*'Valores y Totales'!C26 -> 0 | E27: =G$1*C27 -> 0
C29: Una Receta | D29: Por Cantidad de Recetas
B30: Cantidad de Masitas | C30: 15 | D30: =C30*G$1 -> 15 | E30: de 8 cm
B31: Costo Receta | C31: =SUM(D2:D27) -> 11685 | D31: =C31*G$1 -> 11685
B32: Costo por unidad | C32: =C31/C30 -> 779 | D32: =C32 -> 779
B33: Costo Individual | C33: =C31/C30 -> 779 | D33: =C33 -> 779

Sheet Pepas
B1: Ingrediente | C1: Gramos | D1: Precio | E1: Total Recetas | F1: Cantidad de Recetas: | G1: 1
B2: Manteca | C2: 125 | D2: =C2*'Valores y Totales'!C2 -> 1375 | E2: =G$1*C2 -> 125
B3: Harina 0000 | C3: 300 | D3: =C3*'Valores y Totales'!C3 -> 330 | E3: =G$1*C3 -> 300
B4: Azucar Impalpable | C4: 0 | D4: =C4*'Valores y Totales'!C4 -> 0 | E4: =G$1*C4 -> 0
B5: Cacao | C5: 0 | D5: =C5*'Valores y Totales'!C5 -> 0 | E5: =G$1*C5 -> 0
B6: Huevo (unidad) | C6: 2 | D6: =C6*'Valores y Totales'!B6 -> 420 | E6: =G$1*C6 -> 2
B7: Azucar Común | C7: 125 | D7: =C7*'Valores y Totales'!C7 -> 175 | E7: =G$1*C7 -> 125
B8: Maizena | C8: 0 | D8: =C8*'Valores y Totales'!C8 -> 0 | E8: =G$1*C8 -> 0
B9: Chocolate Taza | C9: 0 | D9: =C9*'Valores y Totales'!C9 -> 0 | E9: =G$1*C9 -> 0
B10: Nueces | C10: 0 | D10: =C10*'Valores y Totales'!C10 -> 0 | E10: =G$1*C10 -> 0
B11: Dulce de Leche | C11: 0 | D11: =C11*'Valores y Totales'!C11 -> 0 | E11: =G$1*C11 -> 0
B12: Crema | C12: 0 | D12: =C12*'Valores y Totales'!C12 -> 0 | E12: =G$1*C12 -> 0
B13: Harina Leudante | C13: 0 | D13: =C13*'Valores y Totales'!C13 -> 0 | E13: =G$1*C13 -> 0
B14: Limon | C14: 1 | D14: =C14*'Valores y Totales'!C14 -> 500 | E14: =G$1*C14 -> 1
B15: Bicarbonato | C15: 0 | D15: =C15*'Valores y Totales'!C15 -> 0 | E15: =G$1*C15 -> 0
B16: Polveo Hornear | C16: 8 | D16: =C16*'Valores y Totales'!C16 -> 32 | E16: =G$1*C16 -> 8
B17: Leche | C17: 0 | D17: =C17*'Valores y Totales'!C17 -> 0 | E17: =G$1*C17 -> 0
B18: Conac | C18: 0 | D18: =C18*'Valores y Totales'!C18 -> 0 | E18: =G$1*C18 -> 0
... B25: Yogur | C25: 0 | D25: =C25*'Valores y Totales'!C25 -> 0 | E25: =G$1*C25 -> 0
B26: Dulce de Membrillo | C26: 300 | D26: =C26*'Valores y Totales'!C45 -> 1800 | E26: =G$1*C26 -> 300
B27: Chocochips | C27: 0 | D27: =C27*'Valores y Totales'!C26 -> 0 | E27: =G$1*C27 -> 0
C29: Una Receta | D29: Por Cantidad de Recetas
B30: Cantidad de Masitas | C30: 48 | D30: =C30*G$1 -> 48
B31: Costo Receta | C31: =SUM(D2:D27) -> 4632 | D31: =C31*G$1 -> 4632
B32: Costo Docena | C32: =C31/C30*12 -> 1158 | D32: =C32 -> 1158
B33: Costo Individual | C33: =C31/C30 -> 96.5 | D33: =C33 -> 96.5

Sheet Crema Bariloche
B1: Ingrediente | C1: Gramos | D1: Precio | E1: Total Recetas | F1: Cantidad de Recetas: | G1: 1
B2: Manteca | C2: 60 | D2: =C2*'Valores y Totales'!C2 -> 660 | E2: =G$1*C2 -> 60
B3: Harina 0000 | C3: 0 | D3: =C3*'Valores y Totales'!C3 -> 0 | E3: =G$1*C3 -> 0
B4: Azucar Impalpable | C4: 0 | D4: =C4*'Valores y Totales'!C4 -> 0 | E4: =G$1*C4 -> 0
B5: Cacao | C5: 0 | D5: =C5*'Valores y Totales'!C5 -> 0 | E5: =G$1*C5 -> 0
B6: Huevo (unidad) | C6: 0 | D6: =C6*'Valores y Totales'!B6 -> 0 | E6: =G$1*C6 -> 0
B7: Azucar Común | C7: 0 | D7: =C7*'Valores y Totales'!C7 -> 0 | E7: =G$1*C7 -> 0
B8: Maizena | C8: 0 | D8: =C8*'Valores y Totales'!C8 -> 0 | E8: =G$1*C8 -> 0
B9: Chocolate Taza | C9: 150 | D9: =C9*'Valores y Totales'!C9 -> 3900 | E9: =G$1*C9 -> 150
B10: Nueces | C10: 0 | D10: =C10*'Valores y Totales'!C10 -> 0 | E10: =G$1*C10 -> 0
B11: Dulce de Leche | C11: 400 | D11: =C11*'Valores y Totales'!C11 -> 2000 | E11: =G$1*C11 -> 400
B12: Crema | C12: 120 | D12: =C12*'Valores y Totales'!C12 -> 1200 | E12: =G$1*C12 -> 120
B13: Harina Leudante | C13: 0 | D13: =C13*'Valores y Totales'!C13 -> 0 | E13: =G$1*C13 -> 0
B14: Limon | C14: 0 | D14: =C14*'Valores y Totales'!C14 -> 0 | E14: =G$1*C14 -> 0
B15: Bicarbonato | C15: 0 | D15: =C15*'Valores y Totales'!C15 -> 0 | E15: =G$1*C15 -> 0
B16: Polveo Hornear | C16: 0 | D16: =C16*'Valores y Totales'!C16 -> 0 | E16: =G$1*C16 -> 0
B17: Leche | C17: 0 | D17: =C17*'Valores y Totales'!C17 -> 0 | E17: =G$1*C17 -> 0
B18: Conac | C18: 30 | D18: =C18*'Valores y Totales'!C18 -> 400 | E18: =G$1*C18 -> 30
... B26: Chocochips | C26: 0 | D26: =C26*'Valores y Totales'!C26 -> 0 | E26: =G$1*C26 -> 0
C28: Una Receta | D28: Por Cantidad de Recetas
B29: Cantidad de Masitas | C29: 1 | D29: =C29*G$1 -> 1
B30: Costo Receta | C30: =SUM(D2:D26) -> 8160 | D30: =C30*G$1 -> 8160
B31: Costo Docena | C31: =C30/C29*12 -> 97920 | D31: =C31 -> 97920
B32: Costo Individual | C32: =C30/C29 -> 8160 | D32: =C32 -> 8160

Sheet Receta Torta Espumita
B1: Ingrediente | C1: Gramos | D1: Precio | E1: Total Recetas | F1: Cantidad de Recetas: | G1: 1
B2: Manteca | C2: 150 | D2: =C2*'Valores y Totales'!C2 -> 1650 | E2: =G$1*C2 -> 150
B3: Harina 0000 | C3: 150 | D3: =C3*'Valores y Totales'!C3 -> 165 | E3: =G$1*C3 -> 150
B4: Azucar Impalpable | C4: 0 | D4: =C4*'Valores y Totales'!C4 -> 0 | E4: =G$1*C4 -> 0
B5: Cacao | C5: 0 | D5: =C5*'Valores y Totales'!C5 -> 0 | E5: =G$1*C5 -> 0
B6: Huevo (unidad) | C6: 3 | D6: =C6*'Valores y Totales'!B6 -> 630 | E6: =G$1*C6 -> 3
B7: Azucar Común | C7: 250 | D7: =C7*'Valores y Totales'!C7 -> 350 | E7: =G$1*C7 -> 250
B8: Maizena | C8: 100 | D8: =C8*'Valores y Totales'!C8 -> 210 | E8: =G$1*C8 -> 100
B9: Chocolate Taza | C9: 0 | D9: =C9*'Valores y Totales'!C9 -> 0 | E9: =G$1*C9 -> 0
B10: Nueces | C10: 0 | D10: =C10*'Valores y Totales'!C10 -> 0 | E10: =G$1*C10 -> 0
B11: Dulce de Leche | C11: 0 | D11: =C11*'Valores y Totales'!C11 -> 0 | E11: =G$1*C11 -> 0
B12: Crema | C12: 0 | D12: =C12*'Valores y Totales'!C12 -> 0 | E12: =G$1*C12 -> 0
B13: Harina Leudante | C13: 0 | D13: =C13*'Valores y Totales'!C13 -> 0 | E13: =G$1*C13 -> 0
B14: Limon | C14: 0 | D14: =C14*'Valores y Totales'!C14 -> 0 | E14: =G$1*C14 -> 0
B15: Bicarbonato | C15: 0 | D15: =C15*'Valores y Totales'!C15 -> 0 | E15: =G$1*C15 -> 0
B16: Polveo Hornear | C16: 20 | D16: =C16*'Valores y Totales'!C16 -> 80 | E16: =G$1*C16 -> 20
B17: Leche | C17: 100 | D17: =C17*'Valores y Totales'!C17 -> 250 | E17: =G$1*C17 -> 100
B18: Conac | C18: 0 | D18: =C18*'Valores y Totales'!C18 -> 0 | E18: =G$1*C18 -> 0
... B26: Chocochips | C26: 0 | D26: =C26*'Valores y Totales'!C26 -> 0 | E26: =G$1*C26 -> 0
C28: Una Receta | D28: Por Cantidad de Recetas
B29: Cantidad de Masitas | C29: 25 | D29: =C29*G$1 -> 25
B30: Costo Receta | C30: =SUM(D2:D20) -> 3335 | D30: =C30*G$1 -> 3335
B31: Costo Docena | C31: =C30/C29*12 -> 1600.8 | D31: =C31 -> 1600.8
B32: Costo Individual | C32: =C30/C29 -> 133.4 | D32: =C32 -> 133.4

Sheet Cupcakes Chocolate
B1: Ingrediente | C1: Gramos | D1: Precio | E1: Total Recetas | F1: Cantidad de Recetas: | G1: 1
B2: Manteca | C2: 110 | D2: =C2*'Valores y Totales'!C2 -> 1210 | E2: =G$1*C2 -> 110
B3: Harina 0000 | C3: 0 | D3: =C3*'Valores y Totales'!C3 -> 0 | E3: =G$1*C3 -> 0
B4: Azucar Impalpable | C4: 0 | D4: =C4*'Valores y Totales'!C4 -> 0 | E4: =G$1*C4 -> 0
B5: Cacao | C5: 50 | D5: =C5*'Valores y Totales'!C5 -> 1250 | E5: =G$1*C5 -> 50
B6: Huevo (unidad) | C6: 2 | D6: =C6*'Valores y Totales'!B6 -> 420 | E6: =G$1*C6 -> 2
B7: Azucar Común | C7: 0 | D7: =C7*'Valores y Totales'!C7 -> 0 | E7: =G$1*C7 -> 0
B8: Maizena | C8: 0 | D8: =C8*'Valores y Totales'!C8 -> 0 | E8: =G$1*C8 -> 0
B9: Chocolate Taza | C9: 0 | D9: =C9*'Valores y Totales'!C9 -> 0 | E9: =G$1*C9 -> 0
B10: Nueces | C10: 0 | D10: =C10*'Valores y Totales'!C10 -> 0 | E10: =G$1*C10 -> 0
B11: Dulce de Leche | C11: 0 | D11: =C11*'Valores y Totales'!C11 -> 0 | E11: =G$1*C11 -> 0
B12: Crema | C12: 0 | D12: =C12*'Valores y Totales'!C12 -> 0 | E12: =G$1*C12 -> 0
B13: Harina Leudante | C13: 250 | D13: =C13*'Valores y Totales'!C13 -> 525 | E13: =G$1*C13 -> 250
B14: Limon | C14: 0 | D14: =C14*'Valores y Totales'!C14 -> 0 | E14: =G$1*C14 -> 0
B15: Bicarbonato | C15: 0 | D15: =C15*'Valores y Totales'!C15 -> 0 | E15: =G$1*C15 -> 0
B16: Polveo Hornear | C16: 0 | D16: =C16*'Valores y Totales'!C16 -> 0 | E16: =G$1*C16 -> 0
B17: Leche | C17: 160 | D17: =C17*'Valores y Totales'!C17 -> 400 | E17: =G$1*C17 -> 160
B18: Conac | C18: 0 | D18: =C18*'Valores y Totales'!C18 -> 0 | E18: =G$1*C18 -> 0
... B31: Pasta de Forrar | C31: 0 | D31: =C31*'Valores y Totales'!C31 -> 0 | E31: =G$1*C31 -> 0
B32: PIROTINES | C32: 12 | D32: 30
C36: Una Receta | D36: Por Cantidad de Recetas
B37: Cantidad de Porciones | C37: 12 | D37: =C37*G$1 -> 12
B38: Costo Receta | C38: =SUM(D2:D32) -> 4203 | D38: =C38*G$1 -> 4203

Sheet Ganache Isabel Vermal
B1: Ingrediente | C1: Gramos | D1: Precio | E1: Total Recetas | F1: Cantidad de Recetas: | G1: 1
B2: Manteca | D2: =C2*'Valores y Totales'!C2 -> 0 | E2: =G$1*C2 -> 0
B3: Harina 0000 | D3: =C3*'Valores y Totales'!C3 -> 0 | E3: =G$1*C3 -> 0
B4: Azucar Impalpable | D4: =C4*'Valores y Totales'!C4 -> 0 | E4: =G$1*C4 -> 0
B5: Cacao | D5: =C5*'Valores y Totales'!C5 -> 0 | E5: =G$1*C5 -> 0
B6: Huevo (unidad) | D6: =C6*'Valores y Totales'!B6 -> 0 | E6: =G$1*C6 -> 0
B7: Azucar Común | D7: =C7*'Valores y Totales'!C7 -> 0 | E7: =G$1*C7 -> 0
B8: Maizena | D8: =C8*'Valores y Totales'!C8 -> 0 | E8: =G$1*C8 -> 0
B9: Chocolate Taza | C9: 270 | D9: =C9*'Valores y Totales'!C9 -> 7020 | E9: =G$1*C9 -> 270
B10: Nueces | D10: =C10*'Valores y Totales'!C10 -> 0 | E10: =G$1*C10 -> 0
B11: Dulce de Leche | C11: 250 | D11: =C11*'Valores y Totales'!C11 -> 1250 | E11: =G$1*C11 -> 250
B12: Crema | C12: 300 | D12: =C12*'Valores y Totales'!C12 -> 3000 | E12: =G$1*C12 -> 300
B13: Harina Leudante | D13: =C13*'Valores y Totales'!C13 -> 0 | E13: =G$1*C13 -> 0
B14: Limon | D14: =C14*'Valores y Totales'!C14 -> 0 | E14: =G$1*C14 -> 0
B15: Bicarbonato | D15: =C15*'Valores y Totales'!C15 -> 0 | E15: =G$1*C15 -> 0
B16: Polveo Hornear | D16: =C16*'Valores y Totales'!C16 -> 0 | E16: =G$1*C16 -> 0
B17: Leche | D17: =C17*'Valores y Totales'!C17 -> 0 | E17: =G$1*C17 -> 0
B18: Conac | D18: =C18*'Valores y Totales'!C18 -> 0 | E18: =G$1*C18 -> 0
B19: Naranja | D19: =C19*'Valores y Totales'!C19 -> 0 | E19: =G$1*C19 -> 0
B20: Azucar Negro | D20: =C20*'Valores y Totales'!C20 -> 0 | E20: =G$1*C20 -> 0
B21: Chocolate Baño | C21: 0 | D21: =C21*'Valores y Totales'!C21 -> 0 | E21: =G$1*C21 -> 0
B22: Biscochuelo | D22: =C22*'Valores y Totales'!C22 -> 0 | E22: =G$1*C22 -> 0
B23: Ciruelas | C23: 0 | D23: =C23*'Valores y Totales'!C23 -> 0 | E23: =G$1*C23 -> 0
B24: Pasas | C24: 0 | D24: 0 | E24: =G$1*C24 -> 0
B25: Yogur | C25: 0 | D25: 0 | E25: =G$1*C25 -> 0
B26: Chocochips | C26: 0 | D26: 0 | E26: =G$1*C26 -> 0
C28: Una Receta | D28: Por Cantidad de Recetas
B29: Cantidad de Porciones | C29: 1 | D29: 1
B30: Costo Receta | C30: =SUM(D2:D22) -> 11270 | D30: =C30*G$1 -> 11270
B31: Costo Docena | C31: 0 | D31: =C31 -> 0
B32: Costo Individual | C32: =C30/C29 -> 11270 | D32: =C32 -> 11270

Sheet Torta Choc Isabel Vermal
B1: Ingrediente | C1: Gramos | D1: Precio | E1: Total Recetas | F1: Cantidad de Recetas: | G1: 1
B2: Manteca | C2: 150 | D2: =C2*'Valores y Totales'!C2 -> 1650 | E2: =G$1*C2 -> 150
B3: Harina 0000 | C3: 300 | D3: =C3*'Valores y Totales'!C3 -> 330 | E3: =G$1*C3 -> 300
B4: Azucar Impalpable | C4: 0 | D4: =C4*'Valores y Totales'!C4 -> 0 | E4: =G$1*C4 -> 0
B5: Cacao | C5: 100 | D5: =C5*'Valores y Totales'!C5 -> 2500 | E5: =G$1*C5 -> 100
B6: Huevo (unidad) | C6: 3 | D6: =C6*'Valores y Totales'!B6 -> 630 | E6: =G$1*C6 -> 3
B7: Azucar Común | C7: 250 | D7: =C7*'Valores y Totales'!C7 -> 350 | E7: =G$1*C7 -> 250
B8: Maizena | C8: 0 | D8: =C8*'Valores y Totales'!C8 -> 0 | E8: =G$1*C8 -> 0
B9: Chocolate Taza | C9: 0 | D9: =C9*'Valores y Totales'!C9 -> 0 | E9: =G$1*C9 -> 0
B10: Nueces | C10: 0 | D10: =C10*'Valores y Totales'!C10 -> 0 | E10: =G$1*C10 -> 0
B11: Dulce de Leche | C11: 0 | D11: =C11*'Valores y Totales'!C11 -> 0 | E11: =G$1*C11 -> 0
B12: Crema | C12: 0 | D12: =C12*'Valores y Totales'!C12 -> 0 | E12: =G$1*C12 -> 0
B13: Harina Leudante | C13: 0 | D13: =C13*'Valores y Totales'!C13 -> 0 | E13: =G$1*C13 -> 0
B14: Limon | C14: 1 | D14: =C14*'Valores y Totales'!C14 -> 500 | E14: =G$1*C14 -> 1
B15: Bicarbonato | C15: 0 | D15: =C15*'Valores y Totales'!C15 -> 0 | E15: =G$1*C15 -> 0
B16: Polveo Hornear | C16: 0 | D16: =C16*'Valores y Totales'!C16 -> 0 | E16: =G$1*C16 -> 0
B17: Leche | C17: 270 | D17: =C17*'Valores y Totales'!C17 -> 675 | E17: =G$1*C17 -> 270
B18: Conac | C18: 0 | D18: =C18*'Valores y Totales'!C18 -> 0 | E18: =G$1*C18 -> 0
... B26: Chocochips | C26: 0 | D26: =C26*'Valores y Totales'!C26 -> 0 | E26: =G$1*C26 -> 0
C28: Una Receta | D28: Por Cantidad de Recetas
B29: Cantidad de Porciones | C29: 1 | D29: =C29*G$1 -> 1
B30: Costo Receta | C30: =SUM(D2:D20) -> 7210 | D30: 1
B31: Costo Individual | C31: =C30/C29 -> 7210 | D31: =C31 -> 7210

Sheet Biscuit Chocolate
B1: Ingrediente | C1: Gramos | D1: Precio | E1: Total Recetas | F1: Cantidad de Recetas: | G1: 1
B2: Manteca | C2: 75 | D2: =C2*'Valores y Totales'!C2 -> 825 | E2: =G$1*C2 -> 75
B3: Harina 0000 | C3: 270 | D3: =C3*'Valores y Totales'!C3 -> 297 | E3: =G$1*C3 -> 270
B4: Azucar Impalpable | C4: 0 | D4: =C4*'Valores y Totales'!C4 -> 0 | E4: =G$1*C4 -> 0
B5: Cacao | C5: 0 | D5: =C5*'Valores y Totales'!C5 -> 0 | E5: =G$1*C5 -> 0
B6: Huevo (unidad) | C6: 2 | D6: =C6*'Valores y Totales'!B6 -> 420 | E6: =G$1*C6 -> 2
B7: Azucar Común | C7: 165 | D7: =C7*'Valores y Totales'!C7 -> 231 | E7: =G$1*C7 -> 165
B8: Maizena | C8: 0 | D8: =C8*'Valores y Totales'!C8 -> 0 | E8: =G$1*C8 -> 0
B9: Chocolate Taza | C9: 170 | D9: =C9*'Valores y Totales'!C9 -> 4420 | E9: =G$1*C9 -> 170
B10: Nueces | C10: 0 | D10: =C10*'Valores y Totales'!C10 -> 0 | E10: =G$1*C10 -> 0
B11: Dulce de Leche | C11: 0 | D11: =C11*'Valores y Totales'!C11 -> 0 | E11: =G$1*C11 -> 0
B12: Crema | C12: 225 | D12: =C12*'Valores y Totales'!C12 -> 2250 | E12: =G$1*C12 -> 225
B13: Harina Leudante | C13: 0 | D13: =C13*'Valores y Totales'!C13 -> 0 | E13: =G$1*C13 -> 0
B14: Limon | C14: 0 | D14: =C14*'Valores y Totales'!C14 -> 0 | E14: =G$1*C14 -> 0
B15: Bicarbonato | C15: 0 | D15: =C15*'Valores y Totales'!C15 -> 0 | E15: =G$1*C15 -> 0
B16: Polveo Hornear | C16: 0 | D16: =C16*'Valores y Totales'!C16 -> 0 | E16: =G$1*C16 -> 0
B17: Leche | C17: 120 | D17: =C17*'Valores y Totales'!C17 -> 300 | E17: =G$1*C17 -> 120
B18: Conac | C18: 0 | D18: =C18*'Valores y Totales'!C18 -> 0 | E18: =G$1*C18 -> 0
... B26: Chocochips | C26: 0 | D26: =C26*'Valores y Totales'!C26 -> 0 | E26: =G$1*C26 -> 0
C28: Una Receta | D28: Por Cantidad de Recetas
B29: Cantidad de Porciones | C29: 1 | D29: =C29*G$1 -> 1
B30: Costo Receta | C30: =SUM(D2:D26) -> 8846.5 | D30: =C30*G$1 -> 8846.5
B32: Costo Individual | C32: =C30/C29 -> 8846.5 | D32: =C32 -> 8846.5

Sheet Butter Cream Chocolate
B1: Ingrediente | C1: Gramos | D1: Precio | E1: Total Recetas | F1: Cantidad de Recetas: | G1: 1
B2: Manteca | C2: 250 | D2: =C2*'Valores y Totales'!C2 -> 2750 | E2: =G$1*C2 -> 250
B3: Harina 0000 | C3: 0 | D3: =C3*'Valores y Totales'!C3 -> 0 | E3: =G$1*C3 -> 0
B4: Azucar Impalpable | C4: 300 | D4: =C4*'Valores y Totales'!C4 -> 450 | E4: =G$1*C4 -> 300
B5: Cacao | C5: 45 | D5: =C5*'Valores y Totales'!C5 -> 1125 | E5: =G$1*C5 -> 45
B6: Huevo (unidad) | C6: 0 | D6: =C6*'Valores y Totales'!B6 -> 0 | E6: =G$1*C6 -> 0
B7: Azucar Común | C7: 0 | D7: =C7*'Valores y Totales'!C7 -> 0 | E7: =G$1*C7 -> 0
B8: Maizena | C8: 0 | D8: =C8*'Valores y Totales'!C8 -> 0 | E8: =G$1*C8 -> 0
B9: Chocolate Taza | C9: 0 | D9: =C9*'Valores y Totales'!C9 -> 0 | E9: =G$1*C9 -> 0
B10: Nueces | C10: 0 | D10: =C10*'Valores y Totales'!C10 -> 0 | E10: =G$1*C10 -> 0
B11: Dulce de Leche | C11: 0 | D11: =C11*'Valores y Totales'!C11 -> 0 | E11: =G$1*C11 -> 0
B12: Crema | C12: 0 | D12: =C12*'Valores y Totales'!C12 -> 0 | E12: =G$1*C12 -> 0
B13: Harina Leudante | C13: 0 | D13: =C13*'Valores y Totales'!C13 -> 0 | E13: =G$1*C13 -> 0
B14: Limon | C14: 0 | D14: =C14*'Valores y Totales'!C14 -> 0 | E14: =G$1*C14 -> 0
B15: Bicarbonato | C15: 0 | D15: =C15*'Valores y Totales'!C15 -> 0 | E15: =G$1*C15 -> 0
B16: Polveo Hornear | C16: 0 | D16: =C16*'Valores y Totales'!C16 -> 0 | E16: =G$1*C16 -> 0
B17: Leche | C17: 30 | D17: =C17*'Valores y Totales'!C17 -> 75 | E17: =G$1*C17 -> 30
B18: Conac | C18: 0 | D18: =C18*'Valores y Totales'!C18 -> 0 | E18: =G$1*C18 -> 0
... B26: Chocochips | C26: 0 | D26: =C26*'Valores y Totales'!C26 -> 0 | E26: =G$1*C26 -> 0
C28: Una Receta | D28: Por Cantidad de Recetas
B29: Cantidad de Porciones | C29: 1 | D29: =C29*G$1 -> 1
B30: Costo Receta | C30: =SUM(D2:D26) -> 4400 | D30: =C30*G$1 -> 4400
B32: Costo Individual | C32: =C30/C29 -> 4400 | D32: =C32 -> 4400

Sheet Brownie Eri
B1: Ingrediente | C1: Gramos | D1: Precio | E1: Total Recetas | F1: Cantidad de Recetas: | G1: 1
B2: Manteca | C2: 200 | D2: =C2*'Valores y Totales'!C2 -> 2200 | E2: =G$1*C2 -> 200
B3: Harina 0000 | C3: 250 | D3: =C3*'Valores y Totales'!C3 -> 275 | E3: =G$1*C3 -> 250
B4: Azucar Impalpable | C4: 0 | D4: =C4*'Valores y Totales'!C4 -> 0 | E4: =G$1*C4 -> 0
B5: Cacao | C5: 30 | D5: =C5*'Valores y Totales'!C5 -> 750 | E5: =G$1*C5 -> 30
B6: Huevo (unidad) | C6: 6 | D6: =C6*'Valores y Totales'!B6 -> 1260 | E6: =G$1*C6 -> 6
B7: Azucar Común | C7: 0 | D7: =C7*'Valores y Totales'!C7 -> 0 | E7: =G$1*C7 -> 0
B8: Maizena | C8: 0 | D8: =C8*'Valores y Totales'!C8 -> 0 | E8: =G$1*C8 -> 0
B9: Chocolate Taza | C9: 100 | D9: =C9*'Valores y Totales'!C9 -> 2600 | E9: =G$1*C9 -> 100
B10: Nueces | C10: 100 | D10: =C10*'Valores y Totales'!C10 -> 2200 | E10: =G$1*C10 -> 100
B11: Dulce de Leche | C11: 0 | D11: =C11*'Valores y Totales'!C11 -> 0 | E11: =G$1*C11 -> 0
B12: Crema | C12: 0 | D12: =C12*'Valores y Totales'!C12 -> 0 | E12: =G$1*C12 -> 0
B13: Harina Leudante | C13: 0 | D13: =C13*'Valores y Totales'!C13 -> 0 | E13: =G$1*C13 -> 0
B14: Limon | C14: 0 | D14: =C14*'Valores y Totales'!C14 -> 0 | E14: =G$1*C14 -> 0
B15: Bicarbonato | C15: 0 | D15: =C15*'Valores y Totales'!C15 -> 0 | E15: =G$1*C15 -> 0
B16: Polveo Hornear | C16: 8 | D16: =C16*'Valores y Totales'!C16 -> 32 | E16: =G$1*C16 -> 8
B17: Leche | C17: 0 | D17: =C17*'Valores y Totales'!C17 -> 0 | E17: =G$1*C17 -> 0
B18: Conac | C18: 0 | D18: =C18*'Valores y Totales'!C18 -> 0 | E18: =G$1*C18 -> 0
... B26: Chocochips | C26: 0 | D26: =C26*'Valores y Totales'!C26 -> 0 | E26: =G$1*C26 -> 0
C28: Una Receta | D28: Por Cantidad de Recetas
B29: Cantidad de Alfajores | C29: 1 | D29: =C29*G$1 -> 1
B30: Costo Receta | C30: =SUM(D2:D26) -> 11490 | D30: =C30*G$1 -> 11490
B31: Costo Docena | D31: =C31 -> 0
B32: Costo Individual | C32: =C30/C29 -> 11490 | D32: =C32 -> 11490

Sheet Alfajores de Chocolate 4 cm NUT
B1: Ingrediente | C1: Gramos | D1: Precio | E1: Total Recetas | F1: Cantidad de Recetas: | G1: 1
B2: Manteca | C2: 150 | D2: =C2*'Valores y Totales'!C2 -> 1650 | E2: =G$1*C2 -> 150
B3: Harina 0000 | C3: 200 | D3: =C3*'Valores y Totales'!C3 -> 220 | E3: =G$1*C3 -> 200
B4: Azucar Impalpable | C4: 0 | D4: =C4*'Valores y Totales'!C4 -> 0 | E4: =G$1*C4 -> 0
B5: Cacao | C5: 50 | D5: =C5*'Valores y Totales'!C5 -> 1250 | E5: =G$1*C5 -> 50
B6: Huevo (unidad) | C6: 3 | D6: =C6*'Valores y Totales'!B6 -> 630 | E6: =G$1*C6 -> 3
B7: Azucar Común | C7: 0 | D7: =C7*'Valores y Totales'!C7 -> 0 | E7: =G$1*C7 -> 0
B8: Maizena | C8: 50 | D8: =C8*'Valores y Totales'!C8 -> 105 | E8: =G$1*C8 -> 50
B9: Chocolate Taza | C9: 0 | D9: =C9*'Valores y Totales'!C9 -> 0 | E9: =G$1*C9 -> 0
B10: Nueces | C10: 0 | D10: =C10*'Valores y Totales'!C10 -> 0 | E10: =G$1*C10 -> 0
B11: Dulce de Leche | C11: 0 | D11: =C11*'Valores y Totales'!C11 -> 0 | E11: =G$1*C11 -> 0
B12: Crema | C12: 0 | D12: =C12*'Valores y Totales'!C12 -> 0 | E12: =G$1*C12 -> 0
B13: Harina Leudante | C13: 0 | D13: =C13*'Valores y Totales'!C13 -> 0 | E13: =G$1*C13 -> 0
B14: Limon | C14: 0 | D14: =C14*'Valores y Totales'!C14 -> 0 | E14: =G$1*C14 -> 0
B15: Bicarbonato | C15: 0 | D15: =C15*'Valores y Totales'!C15 -> 0 | E15: =G$1*C15 -> 0
B16: Polveo Hornear | C16: 0 | D16: =C16*'Valores y Totales'!C16 -> 0 | E16: =G$1*C16 -> 0
B17: Leche | C17: 0 | D17: =C17*'Valores y Totales'!C17 -> 0 | E17: =G$1*C17 -> 0
B18: Conac | C18: 0 | D18: =C18*'Valores y Totales'!C18 -> 0 | E18: =G$1*C18 -> 0
... B24: Pasas | C24: 0 | D24: =C24*'Valores y Totales'!C24 -> 0 | E24: =G$1*C24 -> 0
B25: Nutella | C25: =11*C29 -> 440 | D25: =C25*'Valores y Totales'!C47 -> 378.4 | E25: =G$1*C25 -> 440
B26: Chocochips | C26: 0 | D26: =C26*'Valores y Totales'!C26 -> 0 | E26: =G$1*C26 -> 0
C28: Una Receta | D28: Por Cantidad de Recetas
B29: Cantidad de Alfajores | C29: 40 | D29: =C29*G$1 -> 40
B30: Costo Receta | C30: =SUM(D2:D26) -> 8463.4 | D30: =C30*G$1 -> 8463.4
B31: Costo Docena
B32: Costo Individual | C32: =C30/C29 -> 211.585 | D32: =C32 -> 211.585

Sheet Alfajores de Nuez 4 cm
B1: Ingrediente | C1: Gramos | D1: Precio | E1: Total Recetas | F1: Cantidad de Recetas: | G1: 1
B2: Manteca | C2: 200 | D2: =C2*'Valores y Totales'!C2 -> 2200 | E2: =G$1*C2 -> 200
B3: Harina 0000 | C3: 250 | D3: =C3*'Valores y Totales'!C3 -> 275 | E3: =G$1*C3 -> 250
B4: Azucar Impalpable | C4: 0 | D4: =C4*'Valores y Totales'!C4 -> 0 | E4: =G$1*C4 -> 0
B5: Cacao | C5: 0 | D5: =C5*'Valores y Totales'!C5 -> 0 | E5: =G$1*C5 -> 0
B6: Huevo (unidad) | C6: 1 | D6: =C6*'Valores y Totales'!C6 -> 210 | E6: =G$1*C6 -> 1
B7: Azucar Común | C7: 0 | D7: =C7*'Valores y Totales'!C7 -> 0 | E7: =G$1*C7 -> 0
B8: Maizena | C8: 0 | D8: =C8*'Valores y Totales'!C8 -> 0 | E8: =G$1*C8 -> 0
B9: Chocolate Taza | C9: 0 | D9: =C9*'Valores y Totales'!C9 -> 0 | E9: =G$1*C9 -> 0
B10: Nueces | C10: 300 | D10: =C10*'Valores y Totales'!C10 -> 6600 | E10: =G$1*C10 -> 300
B11: Dulce de Leche | C11: 1200 | D11: =C11*'Valores y Totales'!C11 -> 6000 | E11: =G$1*C11 -> 1200
B12: Crema | C12: 0 | D12: =C12*'Valores y Totales'!C12 -> 0 | E12: =G$1*C12 -> 0
B13: Harina Leudante | C13: 0 | D13: =C13*'Valores y Totales'!C13 -> 0 | E13: =G$1*C13 -> 0
... B26: Chocochips | C26: 0 | D26: =C26*'Valores y Totales'!C26 -> 0 | E26: =G$1*C26 -> 0
C28: Una Receta | D28: Por Cantidad de Recetas
B29: Cantidad de Masitas | C29: 65 | D29: =C29*G$1 -> 65
B30: Costo Receta | C30: =SUM(D2:D26) -> 15745 | D30: =C30*G$1 -> 15745
B31: Costo Docena | D31: =C31 -> 0
B32: Costo Individual | C32: =C30/C29 -> 242.23077 | D32: =C32 -> 242.23077

Sheet Alfajores de Chocolate 4 cm
B1: Ingrediente | C1: Gramos | D1: Precio | E1: Total Recetas | F1: Cantidad de Recetas: | G1: 1
B2: Manteca | C2: 150 | D2: =C2*'Valores y Totales'!C2 -> 1650 | E2: =G$1*C2 -> 150
B3: Harina 0000 | C3: 200 | D3: =C3*'Valores y Totales'!C3 -> 220 | E3: =G$1*C3 -> 200
B4: Azucar Impalpable | C4: 0 | D4: =C4*'Valores y Totales'!C4 -> 0 | E4: =G$1*C4 -> 0
B5: Cacao | C5: 50 | D5: =C5*'Valores y Totales'!C5 -> 1250 | E5: =G$1*C5 -> 50
B6: Huevo (unidad) | C6: 3 | D6: =C6*'Valores y Totales'!B6 -> 630 | E6: =G$1*C6 -> 3
B7: Azucar Común | C7: 0 | D7: =C7*'Valores y Totales'!C7 -> 0 | E7: =G$1*C7 -> 0
B8: Maizena | C8: 50 | D8: =C8*'Valores y Totales'!C8 -> 105 | E8: =G$1*C8 -> 50
B9: Chocolate Taza | C9: 0 | D9: =C9*'Valores y Totales'!C9 -> 0 | E9: =G$1*C9 -> 0
B10: Nueces | C10: 0 | D10: =C10*'Valores y Totales'!C10 -> 0 | E10: =G$1*C10 -> 0
B11: Dulce de Leche | C11: =20*C29 -> 800 | D11: =C11*'Valores y Totales'!C11 -> 4000 | E11: =G$1*C11 -> 800
B12: Crema | C12: 0 | D12: =C12*'Valores y Totales'!C12 -> 0 | E12: =G$1*C12 -> 0
B13: Harina Leudante | C13: 0 | D13: =C13*'Valores y Totales'!C13 -> 0 | E13: =G$1*C13 -> 0
B14: Limon | C14: 0 | D14: =C14*'Valores y Totales'!C14 -> 0 | E14: =G$1*C14 -> 0
B15: Bicarbonato | C15: 0 | D15: =C15*'Valores y Totales'!C15 -> 0 | E15: =G$1*C15 -> 0
B16: Polveo Hornear | C16: 0 | D16: =C16*'Valores y Totales'!C16 -> 0 | E16: =G$1*C16 -> 0
B17: Leche | C17: 0 | D17: =C17*'Valores y Totales'!C17 -> 0 | E17: =G$1*C17 -> 0
B18: Conac | C18: 0 | D18: =C18*'Valores y Totales'!C18 -> 0 | E18: =G$1*C18 -> 0
B19: Naranja | C19: 0 | D19: =C19*'Valores y Totales'!C19 -> 0 | E19: =G$1*C19 -> 0
B20: Azucar Negro | C20: 100 | D20: =C20*'Valores y Totales'!C20 -> 230 | E20: =G$1*C20 -> 100
B21: Chocolate Banio | C21: 400 | D21: =C21*'Valores y Totales'!C21 -> 4000 | E21: =G$1*C21 -> 400
B22: Biscochuelo | C22: 0 | D22: =C22*'Valores y Totales'!C22 -> 0 | E22: =G$1*C22 -> 0
B23: Ciruelas | C23: 0 | D23: =C23*'Valores y Totales'!C23 -> 0 | E23: =G$1*C23 -> 0
... B26: Chocochips | C26: 0 | D26: =C26*'Valores y Totales'!C26 -> 0 | E26: =G$1*C26 -> 0
C28: Una Receta | D28: Por Cantidad de Recetas
B29: Cantidad de Alfajores | C29: 40 | D29: =C29*G$1 -> 40
B30: Costo Receta | C30: =SUM(D2:D26) -> 12085 | D30: =C30*G$1 -> 12085
B31: Costo Docena
B32: Costo Individual | C32: =C30/C29 -> 302.125 | D32: =C32 -> 302.125

Sheet Alfajores de Maicena 4 cm
B1: Ingrediente | C1: Gramos | D1: Precio | E1: Total Recetas | F1: Cantidad de Recetas: | G1: 1
B2: Manteca | C2: 200 | D2: =C2*'Valores y Totales'!C2 -> 2200 | E2: =G$1*C2 -> 200
B3: Coco | C3: 125 | D3: =C3*'Valores y Totales'!C44 -> 1500
B4: Harina 0000 | C4: 200 | D4: =C4*'Valores y Totales'!C3 -> 220 | E4: =G$1*C4 -> 200
B5: Azucar Impalpable | C5: 0 | D5: =C5*'Valores y Totales'!C4 -> 0 | E5: =G$1*C5 -> 0
B6: Cacao | C6: 0 | D6: =C6*'Valores y Totales'!C5 -> 0 | E6: =G$1*C6 -> 0
B7: Huevo (unidad) | C7: 2 | D7: =C7*'Valores y Totales'!B6 -> 420 | E7: =G$1*C7 -> 2
B8: Azucar Común | C8: 150 | D8: =C8*'Valores y Totales'!C7 -> 210 | E8: =G$1*C8 -> 150
B9: Maizena | C9: 300 | D9: =C9*'Valores y Totales'!C8 -> 630 | E9: =G$1*C9 -> 300
B10: Chocolate Taza | C10: 0 | D10: =C10*'Valores y Totales'!C9 -> 0 | E10: =G$1*C10 -> 0
B11: Nueces | C11: 0 | D11: =C11*'Valores y Totales'!C10 -> 0 | E11: =G$1*C11 -> 0
B12: Dulce de Leche | C12: 1300 | D12: =C12*'Valores y Totales'!C11 -> 6500 | E12: =G$1*C12 -> 1300
B13: Crema | C13: 0 | D13: =C13*'Valores y Totales'!C12 -> 0 | E13: =G$1*C13 -> 0
B14: Harina Leudante | C14: 0 | D14: =C14*'Valores y Totales'!C13 -> 0 | E14: =G$1*C14 -> 0
B15: Limon | C15: 1 | D15: =C15*'Valores y Totales'!C14 -> 500 | E15: =G$1*C15 -> 1
B16: Bicarbonato | C16: 0 | D16: =C16*'Valores y Totales'!C15 -> 0 | E16: =G$1*C16 -> 0
B17: Polveo Hornear | C17: 10 | D17: =C17*'Valores y Totales'!C16 -> 40 | E17: =G$1*C17 -> 10
B18: Leche | C18: 0 | D18: =C18*'Valores y Totales'!C17 -> 0 | E18: =G$1*C18 -> 0
B19: Conac | C19: 20 | D19: =C19*'Valores y Totales'!C18 -> 266.66667 | E19: =G$1*C19 -> 20
... B27: Chocochips | C27: 0 | D27: =C27*'Valores y Totales'!C26 -> 0 | E27: =G$1*C27 -> 0
C29: Una Receta | D29: Por Cantidad de Recetas
B30: Cantidad de Masitas | C30: 70 | D30: =C30*G$1 -> 70
B31: Costo Receta | C31: =SUM(D2:D27) -> 12486.667 | D31: =C31*G$1 -> 12486.667
B32: Costo Docena | D32: =C32 -> 0
B33: Costo Individual | C33: =C31/C30 -> 178.38095 | D33: =C33 -> 178.38095

Sheet Alfajores de Maicena 7 cm
B1: Ingrediente | C1: Gramos | D1: Precio | E1: Total Recetas | F1: Cantidad de Recetas: | G1: 1
B2: Manteca | C2: 200 | D2: =C2*'Valores y Totales'!C2 -> 2200 | E2: =G$1*C2 -> 200
B3: Coco | C3: 125 | D3: =C3*'Valores y Totales'!C44 -> 1500
B4: Harina 0000 | C4: 200 | D4: =C4*'Valores y Totales'!C3 -> 220 | E4: =G$1*C4 -> 200
B5: Azucar Impalpable | C5: 0 | D5: =C5*'Valores y Totales'!C4 -> 0 | E5: =G$1*C5 -> 0
B6: Cacao | C6: 0 | D6: =C6*'Valores y Totales'!C5 -> 0 | E6: =G$1*C6 -> 0
B7: Huevo (unidad) | C7: 2 | D7: =C7*'Valores y Totales'!B6 -> 420 | E7: =G$1*C7 -> 2
B8: Azucar Común | C8: 150 | D8: =C8*'Valores y Totales'!C7 -> 210 | E8: =G$1*C8 -> 150
B9: Maizena | C9: 300 | D9: =C9*'Valores y Totales'!C8 -> 630 | E9: =G$1*C9 -> 300
B10: Chocolate Taza | C10: 0 | D10: =C10*'Valores y Totales'!C9 -> 0 | E10: =G$1*C10 -> 0
B11: Nueces | C11: 0 | D11: =C11*'Valores y Totales'!C10 -> 0 | E11: =G$1*C11 -> 0
B12: Dulce de Leche | C12: 1250 | D12: =C12*'Valores y Totales'!C11 -> 6250 | E12: =G$1*C12 -> 1250
B13: Crema | C13: 0 | D13: =C13*'Valores y Totales'!C12 -> 0 | E13: =G$1*C13 -> 0
B14: Harina Leudante | C14: 0 | D14: =C14*'Valores y Totales'!C13 -> 0 | E14: =G$1*C14 -> 0
B15: Limon | C15: 1 | D15: =C15*'Valores y Totales'!C14 -> 500 | E15: =G$1*C15 -> 1
B16: Bicarbonato | C16: 0 | D16: =C16*'Valores y Totales'!C15 -> 0 | E16: =G$1*C16 -> 0
B17: Polveo Hornear | C17: 10 | D17: =C17*'Valores y Totales'!C16 -> 40 | E17: =G$1*C17 -> 10
B18: Leche | C18: 0 | D18: =C18*'Valores y Totales'!C17 -> 0 | E18: =G$1*C18 -> 0
B19: Conac | C19: 20 | D19: =C19*'Valores y Totales'!C18 -> 266.66667 | E19: =G$1*C19 -> 20
... B27: Chocochips | C27: 0 | D27: =C27*'Valores y Totales'!C26 -> 0 | E27: =G$1*C27 -> 0
C29: Una Receta | D29: Por Cantidad de Recetas
B30: Cantidad de Masitas | C30: 25 | D30: =C30*G$1 -> 25
B31: Costo Receta | C31: =SUM(D2:D27) -> 12236.667 | D31: =C31*G$1 -> 12236.667
B32: Costo Docena | D32: =C32 -> 0
B33: Costo Individual | C33: =C31/C30 -> 489.46667 | D33: =C33 -> 489.46667

Sheet Alfajores de Chocolate 7 cm
B1: Ingrediente | C1: Gramos | D1: Precio | E1: Total Recetas | F1: Cantidad de Recetas: | G1: 1
B2: Manteca | C2: 150 | D2: =C2*'Valores y Totales'!C2 -> 1650 | E2: =G$1*C2 -> 150
B3: Harina 0000 | C3: 200 | D3: =C3*'Valores y Totales'!C3 -> 220 | E3: =G$1*C3 -> 200
B4: Azucar Impalpable | C4: 0 | D4: =C4*'Valores y Totales'!C4 -> 0 | E4: =G$1*C4 -> 0
B5: Cacao | C5: 50 | D5: =C5*'Valores y Totales'!C5 -> 1250 | E5: =G$1*C5 -> 50
B6: Huevo (unidad) | C6: 3 | D6: =C6*'Valores y Totales'!B6 -> 630 | E6: =G$1*C6 -> 3
B7: Azucar Común | C7: 0 | D7: =C7*'Valores y Totales'!C7 -> 0 | E7: =G$1*C7 -> 0
B8: Maizena | C8: 50 | D8: =C8*'Valores y Totales'!C8 -> 105 | E8: =G$1*C8 -> 50
B9: Chocolate Taza | C9: 0 | D9: =C9*'Valores y Totales'!C9 -> 0 | E9: =G$1*C9 -> 0
B10: Nueces | C10: 0 | D10: =C10*'Valores y Totales'!C10 -> 0 | E10: =G$1*C10 -> 0
B11: Dulce de Leche | C11: 750 | D11: =C11*'Valores y Totales'!C11 -> 3750 | E11: =G$1*C11 -> 750
B12: Crema | C12: 0 | D12: =C12*'Valores y Totales'!C12 -> 0 | E12: =G$1*C12 -> 0
B13: Harina Leudante | C13: 0 | D13: =C13*'Valores y Totales'!C13 -> 0 | E13: =G$1*C13 -> 0
B14: Limon | C14: 0 | D14: =C14*'Valores y Totales'!C14 -> 0 | E14: =G$1*C14 -> 0
B15: Bicarbonato | C15: 0 | D15: =C15*'Valores y Totales'!C15 -> 0 | E15: =G$1*C15 -> 0
B16: Polveo Hornear | C16: 0 | D16: =C16*'Valores y Totales'!C16 -> 0 | E16: =G$1*C16 -> 0
B17: Leche | C17: 0 | D17: =C17*'Valores y Totales'!C17 -> 0 | E17: =G$1*C17 -> 0
B18: Conac | C18: 0 | D18: =C18*'Valores y Totales'!C18 -> 0 | E18: =G$1*C18 -> 0
... B26: Chocochips | C26: 0 | D26: =C26*'Valores y Totales'!C26 -> 0 | E26: =G$1*C26 -> 0
C28: Una Receta | D28: Por Cantidad de Recetas
B29: Cantidad de Alfajores | C29: 15 | D29: =C29*G$1 -> 15
B30: Costo Receta | C30: =SUM(D2:D26) -> 11835 | D30: =C30*G$1 -> 11835
B31: Costo Docena
B32: Costo Individual | C32: =C30/C29 -> 789 | D32: =C32 -> 789 | F32: =C32*2 -> 1578

Sheet Masitas Mantecosas de Choco
B1: Ingrediente | C1: Gramos | D1: Precio | E1: Total Recetas | F1: Cantidad de Recetas: | G1: 1
B2: Manteca | C2: 250 | D2: 80 | E2: =G$1*C2 -> 250
B3: Harina 0000 | C3: 315 | D3: 17.325 | E3: =G$1*C3 -> 315
B4: Azucar Impalpable | C4: 60 | D4: 4.68 | E4: =G$1*C4 -> 60
B5: Cacao | C5: 20 | D5: 21.2 | E5: =G$1*C5 -> 20
B6: Huevo (unidad) | C6: 1 | D6: 8.5 | E6: =G$1*C6 -> 1
B7: Azucar Común | C7: 0 | D7: 0 | E7: =G$1*C7 -> 0
B8: Maizena | C8: 0 | D8: 0 | E8: =G$1*C8 -> 0
B9: Chocolate Taza | C9: 0 | D9: 0 | E9: =G$1*C9 -> 0
B10: Nueces | C10: 0 | D10: 0 | E10: =G$1*C10 -> 0
B11: Dulce de Leche | C11: 0 | D11: 0 | E11: =G$1*C11 -> 0
B12: Crema | C12: 0 | D12: 0 | E12: =G$1*C12 -> 0
B13: Harina Leudante | C13: 0 | D13: 0 | E13: =G$1*C13 -> 0
... B26: Chocochips | C26: 0 | D26: 0 | E26: =G$1*C26 -> 0
C28: Una Receta | D28: Por Cantidad de Recetas
B29: Cantidad de Masitas | C29: 40 | D29: =C29*G$1 -> 40
B30: Costo Receta | C30: =SUM(D2:D26) -> 140.595 | D30: =C30*G$1 -> 140.595
B31: Costo Docena | C31: =C30/C29*12 -> 42.1785 | D31: =C31 -> 42.1785
B32: Costo Individual | C32: =C30/C29 -> 3.514875 | D32: =C32 -> 3.514875

Sheet Galletas Naranja Manga
B1: Ingrediente | C1: Gramos | D1: Precio | E1: Total Recetas | F1: Cantidad de Recetas: | G1: 1
B2: Manteca | C2: 100 | D2: 32 | E2: =G$1*C2 -> 100
B3: Harina 0000 | C3: 150 | D3: 8.25 | E3: =G$1*C3 -> 150
B4: Azucar Impalpable | C4: 75 | D4: 5.85 | E4: =G$1*C4 -> 75
B5: Cacao | C5: 0 | D5: 0 | E5: =G$1*C5 -> 0
B6: Huevo (unidad) | C6: 2 | D6: 17 | E6: =G$1*C6 -> 2
B7: Azucar Común | C7: 0 | D7: 0 | E7: =G$1*C7 -> 0
B8: Maizena | C8: 0 | D8: 0 | E8: =G$1*C8 -> 0
B9: Chocolate Taza | C9: 0 | D9: 0 | E9: =G$1*C9 -> 0
B10: Nueces | C10: 0 | D10: 0 | E10: =G$1*C10 -> 0
B11: Dulce de Leche | C11: 0 | D11: 0 | E11: =G$1*C11 -> 0
B12: Crema | C12: 0 | D12: 0 | E12: =G$1*C12 -> 0
B13: Harina Leudante | C13: 0 | D13: 0 | E13: =G$1*C13 -> 0
... B26: Chocochips | C26: 0 | D26: 0 | E26: =G$1*C26 -> 0
C28: Una Receta | D28: Por Cantidad de Recetas
B29: Cantidad de Masitas | C29: 40 | D29: =C29*G$1 -> 40
B30: Costo Receta | C30: =SUM(D2:D26) -> 73.1 | D30: =C30*G$1 -> 73.1
B31: Costo Docena | C31: =C30/C29*12 -> 21.93 | D31: =C31 -> 21.93
B32: Costo Individual | C32: =C30/C29 -> 1.8275 | D32: =C32 -> 1.8275

Sheet Cookies Ginger Snaps
B1: Ingrediente | C1: Gramos | D1: Precio | E1: Total Recetas | F1: Cantidad de Recetas: | G1: 1
B2: Manteca | C2: 180 | D2: =C2*'Valores y Totales'!C2 -> 1980 | E2: =G$1*C2 -> 180
B3: Harina 0000 | C3: 500 | D3: =C3*'Valores y Totales'!C3 -> 550 | E3: =G$1*C3 -> 500
B4: Azucar Impalpable | C4: 0 | D4: =C4*'Valores y Totales'!C4 -> 0 | E4: =G$1*C4 -> 0
B5: Cacao | C5: 0 | D5: =C5*'Valores y Totales'!C5 -> 0 | E5: =G$1*C5 -> 0
B6: Huevo (unidad) | C6: 1 | D6: =C6*'Valores y Totales'!B6 -> 210 | E6: =G$1*C6 -> 1
B7: Azucar Común | C7: 300 | D7: =C7*'Valores y Totales'!C7 -> 420 | E7: =G$1*C7 -> 300
B8: Maizena | C8: 0 | D8: =C8*'Valores y Totales'!C8 -> 0 | E8: =G$1*C8 -> 0
B9: Chocolate Taza | C9: 0 | D9: =C9*'Valores y Totales'!C9 -> 0 | E9: =G$1*C9 -> 0
B10: Nueces | C10: 0 | D10: =C10*'Valores y Totales'!C10 -> 0 | E10: =G$1*C10 -> 0
B11: Dulce de Leche | C11: 0 | D11: =C11*'Valores y Totales'!C11 -> 0 | E11: =G$1*C11 -> 0
B12: Crema | C12: 0 | D12: =C12*'Valores y Totales'!C12 -> 0 | E12: =G$1*C12 -> 0
B13: Harina Leudante | C13: 0 | D13: =C13*'Valores y Totales'!C13 -> 0 | E13: =G$1*C13 -> 0
B14: Limon | C14: 0 | D14: =C14*'Valores y Totales'!C14 -> 0 | E14: =G$1*C14 -> 0
B15: Bicarbonato | C15: 2 | D15: =C15*'Valores y Totales'!C15 -> 1.8 | E15: =G$1*C15 -> 2
B16: Polveo Hornear | C16: 0 | D16: =C16*'Valores y Totales'!C16 -> 0 | E16: =G$1*C16 -> 0
B17: Leche | C17: 0 | D17: =C17*'Valores y Totales'!C17 -> 0 | E17: =G$1*C17 -> 0
B18: Conac | C18: 0 | D18: =C18*'Valores y Totales'!C18 -> 0 | E18: =G$1*C18 -> 0
... B26: Chocochips | C26: 0 | D26: =C26*'Valores y Totales'!C26 -> 0 | E26: =G$1*C26 -> 0
B27: Chips Cobertura | C27: 0 | D27: =C27*'Valores y Totales'!#REF! -> #REF! | E27: =G$1*C27 -> 0
B28: Miel | C28: 20 | D28: ='Valores y Totales'!C52*C28 -> 160 | E28: =G$1*C28 -> 20
C29: Una Receta | D29: Por Cantidad de Recetas
B30: Cantidad de Porciones | C30: 60 | D30: =C30*G$1 -> 60
B31: Costo Receta | C31: =SUM(D2:D28) -> #REF! | D31: =C31*G$1 -> #REF!
B32: Costo Docena | C32: =C31/C30*12 -> #REF! | D32: =C32 -> #REF!
B33: Costo Individual | C33: =C31/C30 -> #REF! | D33: =C33 -> #REF!
B34: Las masitas son de 5 cm de diámetro

Sheet Browkies - Cookies doble choco
B1: Ingrediente | C1: Gramos | D1: Precio | E1: Total Recetas | F1: Cantidad de Recetas: | G1: 1
B2: Manteca | C2: 110 | D2: =C2*'Valores y Totales'!C2 -> 1210 | E2: =G$1*C2 -> 110
B3: Harina 0000 | C3: 155 | D3: =C3*'Valores y Totales'!C3 -> 170.5 | E3: =G$1*C3 -> 155
B4: Azucar Impalpable | C4: 0 | D4: =C4*'Valores y Totales'!C4 -> 0 | E4: =G$1*C4 -> 0
B5: Cacao | C5: 50 | D5: =C5*'Valores y Totales'!C5 -> 1250 | E5: =G$1*C5 -> 50
B6: Huevo (unidad) | C6: 2 | D6: =C6*'Valores y Totales'!B6 -> 420 | E6: =G$1*C6 -> 2
B7: Azucar Común | C7: 0 | D7: =C7*'Valores y Totales'!C7 -> 0 | E7: =G$1*C7 -> 0
B8: Maizena | C8: 0 | D8: =C8*'Valores y Totales'!C8 -> 0 | E8: =G$1*C8 -> 0
B9: Chocolate Taza | C9: 225 | D9: =C9*'Valores y Totales'!C9 -> 5850 | E9: =G$1*C9 -> 225
B10: Nueces | C10: 0 | D10: =C10*'Valores y Totales'!C10 -> 0 | E10: =G$1*C10 -> 0
B11: Dulce de Leche | C11: 0 | D11: =C11*'Valores y Totales'!C11 -> 0 | E11: =G$1*C11 -> 0
B12: Crema | C12: 0 | D12: =C12*'Valores y Totales'!C12 -> 0 | E12: =G$1*C12 -> 0
B13: Harina Leudante | C13: 0 | D13: =C13*'Valores y Totales'!C13 -> 0 | E13: =G$1*C13 -> 0
B14: Limon | C14: 0 | D14: =C14*'Valores y Totales'!C14 -> 0 | E14: =G$1*C14 -> 0
B15: Bicarbonato | C15: 0 | D15: =C15*'Valores y Totales'!C15 -> 0 | E15: =G$1*C15 -> 0
B16: Polveo Hornear | C16: 10 | D16: =C16*'Valores y Totales'!C16 -> 40 | E16: =G$1*C16 -> 10
B17: Leche | C17: 0 | D17: =C17*'Valores y Totales'!C17 -> 0 | E17: =G$1*C17 -> 0
B18: Conac | C18: 0 | D18: =C18*'Valores y Totales'!C18 -> 0 | E18: =G$1*C18 -> 0
... B26: Chocochips | C26: 150 | D26: =C26*'Valores y Totales'!C26 -> 1200 | E26: =G$1*C26 -> 150
C27: Una Receta | D27: Por Cantidad de Recetas
B28: Cantidad de Porciones | C28: 34 | D28: =C28*G$1 -> 34
B29: Costo Receta | C29: =SUM(D2:D26) -> 10658 | D29: =C29*G$1 -> 10658
B30: Costo Docena | C30: =C29/C28*12 -> 3761.6471 | D30: =C30 -> 3761.6471
B31: Costo Individual | C31: =C29/C28 -> 313.47059 | D31: =C31 -> 313.47059
B32: Las masitas son de 5 cm de diámetro y 30 g

Sheet Cookies Chip Taller
B1: Ingrediente | C1: Gramos | D1: Precio | E1: Total Recetas | F1: Cantidad de Recetas: | G1: 1
B2: Manteca | C2: 115 | D2: =C2*'Valores y Totales'!C2 -> 1265 | E2: =G$1*C2 -> 115
B3: Harina 0000 | C3: 185 | D3: =C3*'Valores y Totales'!C3 -> 203.5 | E3: =G$1*C3 -> 185
B4: Azucar Impalpable | C4: 0 | D4: =C4*'Valores y Totales'!C4 -> 0 | E4: =G$1*C4 -> 0
B5: Cacao | C5: 0 | D5: =C5*'Valores y Totales'!C5 -> 0 | E5: =G$1*C5 -> 0
B6: Huevo (unidad) | C6: 1 | D6: =C6*'Valores y Totales'!B6 -> 210 | E6: =G$1*C6 -> 1
B7: Azucar Común | C7: 100 | D7: =C7*'Valores y Totales'!C7 -> 140 | E7: =G$1*C7 -> 100
B8: Maizena | C8: 30 | D8: =C8*'Valores y Totales'!C8 -> 63 | E8: =G$1*C8 -> 30
B9: Chocolate Taza | C9: 0 | D9: =C9*'Valores y Totales'!C9 -> 0 | E9: =G$1*C9 -> 0
B10: Nueces | C10: 0 | D10: =C10*'Valores y Totales'!C10 -> 0 | E10: =G$1*C10 -> 0
B11: Dulce de Leche | C11: 0 | D11: =C11*'Valores y Totales'!C11 -> 0 | E11: =G$1*C11 -> 0
B12: Crema | C12: 0 | D12: =C12*'Valores y Totales'!C12 -> 0 | E12: =G$1*C12 -> 0
B13: Harina Leudante | C13: 0 | D13: =C13*'Valores y Totales'!C13 -> 0 | E13: =G$1*C13 -> 0
B14: Limon | C14: 0 | D14: =C14*'Valores y Totales'!C14 -> 0 | E14: =G$1*C14 -> 0
B15: Bicarbonato | C15: 0 | D15: =C15*'Valores y Totales'!C15 -> 0 | E15: =G$1*C15 -> 0
B16: Polveo Hornear | C16: 0 | D16: =C16*'Valores y Totales'!C16 -> 0 | E16: =G$1*C16 -> 0
B17: Leche | C17: 0 | D17: =C17*'Valores y Totales'!C17 -> 0 | E17: =G$1*C17 -> 0
B18: Conac | C18: 0 | D18: =C18*'Valores y Totales'!C18 -> 0 | E18: =G$1*C18 -> 0
... B26: Chocochips | C26: 150 | D26: =C26*'Valores y Totales'!C26 -> 1200 | E26: =G$1*C26 -> 150
C28: Una Receta | D28: Por Cantidad de Recetas
B29: Cantidad de Porciones | C29: 24 | D29: =C29*G$1 -> 24
B30: Costo Receta | C30: =SUM(D2:D27) -> 3311.5 | D30: =C30*G$1 -> 3311.5
B31: Costo Docena | C31: =C30/C29*12 -> 1655.75 | D31: =C31 -> 1655.75
B32: Costo Individual | C32: =C30/C29 -> 137.97917 | D32: =C32 -> 137.97917
B33: Las masitas son de 5 cm de diámetro y 30 g

Sheet Cookies Vainilla con Chips
B1: Ingrediente | C1: Gramos | D1: Precio | E1: Total Recetas | F1: Cantidad de Recetas: | G1: 1
B2: Manteca | C2: 200 | D2: =C2*'Valores y Totales'!C2 -> 2200 | E2: =G$1*C2 -> 200
B3: Harina 0000 | C3: 450 | D3: =C3*'Valores y Totales'!C3 -> 495 | E3: =G$1*C3 -> 450
B4: Azucar Impalpable | C4: 0 | D4: =C4*'Valores y Totales'!C4 -> 0 | E4: =G$1*C4 -> 0
B5: Cacao | C5: 0 | D5: =C5*'Valores y Totales'!C5 -> 0 | E5: =G$1*C5 -> 0
B6: Huevo (unidad) | C6: 2 | D6: =C6*'Valores y Totales'!B6 -> 420 | E6: =G$1*C6 -> 2
B7: Azucar Común | C7: 400 | D7: =C7*'Valores y Totales'!C7 -> 560 | E7: =G$1*C7 -> 400
B8: Maizena | C8: 0 | D8: =C8*'Valores y Totales'!C8 -> 0 | E8: =G$1*C8 -> 0
B9: Chocolate Taza | C9: 0 | D9: =C9*'Valores y Totales'!C9 -> 0 | E9: =G$1*C9 -> 0
B10: Nueces | C10: 0 | D10: =C10*'Valores y Totales'!C10 -> 0 | E10: =G$1*C10 -> 0
B11: Dulce de Leche | C11: 0 | D11: =C11*'Valores y Totales'!C11 -> 0 | E11: =G$1*C11 -> 0
B12: Crema | C12: 0 | D12: =C12*'Valores y Totales'!C12 -> 0 | E12: =G$1*C12 -> 0
B13: Harina Leudante | C13: 0 | D13: =C13*'Valores y Totales'!C13 -> 0 | E13: =G$1*C13 -> 0
B14: Limon | C14: 0 | D14: =C14*'Valores y Totales'!C14 -> 0 | E14: =G$1*C14 -> 0
B15: Bicarbonato | C15: 0 | D15: =C15*'Valores y Totales'!C15 -> 0 | E15: =G$1*C15 -> 0
B16: Polveo Hornear | C16: 15 | D16: =C16*'Valores y Totales'!C16 -> 60 | E16: =G$1*C16 -> 15
B17: Leche | C17: 0 | D17: =C17*'Valores y Totales'!C17 -> 0 | E17: =G$1*C17 -> 0
B18: Conac | C18: 0 | D18: =C18*'Valores y Totales'!C18 -> 0 | E18: =G$1*C18 -> 0
... B26: Chocochips | C26: 150 | D26: =C26*'Valores y Totales'!C26 -> 1200 | E26: =G$1*C26 -> 150
B27: Chips Cobertura | C27: 0 | D27: =C27*'Valores y Totales'!#REF! -> #REF! | E27: =G$1*C27 -> 0
C28: Una Receta | D28: Por Cantidad de Recetas
B29: Cantidad de Porciones | C29: 66 | D29: =C29*G$1 -> 66
B30: Costo Receta | C30: =SUM(D2:D27) -> #REF! | D30: =C30*G$1 -> #REF!
B31: Costo Docena | C31: =C30/C29*12 -> #REF! | D31: =C31 -> #REF!
B32: Costo Individual | C32: =C30/C29 -> #REF! | D32: =C32 -> #REF!
B33: Las masitas son de 5 cm de diámetro

Sheet Budin de Vainilla
B1: Ingrediente | C1: Gramos | D1: Precio | E1: Total Recetas | F1: Cantidad de Recetas: | G1: 1
B2: Manteca | C2: 250 | D2: =C2*'Valores y Totales'!C2 -> 2750 | E2: =G$1*C2 -> 250
B3: Harina 0000 | C3: 0 | D3: =C3*'Valores y Totales'!C3 -> 0 | E3: =G$1*C3 -> 0 | H3: Una Receta | I3: Por Cantidad de Recetas
B4: Azucar Impalpable | C4: 0 | D4: =C4*'Valores y Totales'!C4 -> 0 | E4: =G$1*C4 -> 0 | G4: Cantidad de Porciones | H4: 1 | I4: =H4*G$1 -> 1
B5: Cacao | C5: 0 | D5: =C5*'Valores y Totales'!C5 -> 0 | E5: =G$1*C5 -> 0 | G5: Costo Receta | H5: =SUM(D2:D30) -> 12963 | I5: =H5*G$1 -> 12963
B6: Huevo (unidad) | C6: 4 | D6: =C6*'Valores y Totales'!B6 -> 840 | E6: =G$1*C6 -> 4 | G6: Costo Docena | I6: =H6 -> 0
B7: Azucar Común | C7: 250 | D7: =C7*'Valores y Totales'!C7 -> 350 | E7: =G$1*C7 -> 250 | G7: Costo Individual | H7: =H5/H4 -> 12963 | I7: =H7 -> 12963
B8: Maizena | C8: 0 | D8: =C8*'Valores y Totales'!C8 -> 0 | E8: =G$1*C8 -> 0
B9: Chocolate Taza | C9: 0 | D9: =C9*'Valores y Totales'!C9 -> 0 | E9: =G$1*C9 -> 0
B10: Nueces | C10: 0 | D10: =C10*'Valores y Totales'!C10 -> 0 | E10: =G$1*C10 -> 0 | K10: 130 | L10: 1500
B11: Dulce de Leche | C11: 0 | D11: =C11*'Valores y Totales'!C11 -> 0 | E11: =G$1*C11 -> 0 | K11: =L11*K10/L10 -> 8.6666667 | L11: 100
B12: Crema | C12: 0 | D12: =C12*'Valores y Totales'!C12 -> 0 | E12: =G$1*C12 -> 0
B13: Harina Leudante | C13: 500 | D13: =C13*'Valores y Totales'!C13 -> 1050 | E13: =G$1*C13 -> 500
B14: Limon | C14: 0 | D14: =C14*'Valores y Totales'!C14 -> 0 | E14: =G$1*C14 -> 0
B15: Bicarbonato | C15: 0 | D15: =C15*'Valores y Totales'!C15 -> 0 | E15: =G$1*C15 -> 0
B16: Polveo Hornear | C16: 0 | D16: =C16*'Valores y Totales'!C16 -> 0 | E16: =G$1*C16 -> 0
B17: Leche | C17: 160 | D17: =C17*'Valores y Totales'!C17 -> 400 | E17: =G$1*C17 -> 160
B18: Conac | C18: 0 | D18: =C18*'Valores y Totales'!C18 -> 0 | E18: =G$1*C18 -> 0
B19: Naranja | C19: 0 | D19: =C19*'Valores y Totales'!C19 -> 0 | E19: =G$1*C19 -> 0
B20: Azucar Negro | C20: 0 | D20: =C20*'Valores y Totales'!C20 -> 0 | E20: =G$1*C20 -> 0
B21: Chocolate Baño | C21: 100 | D21: =C21*'Valores y Totales'!C21 -> 1000 | E21: =G$1*C21 -> 100
B22: Biscochuelo | C22: 0 | D22: =C22*'Valores y Totales'!C22 -> 0 | E22: =G$1*C22 -> 0
B23: Ciruelas | C23: 0 | D23: =C23*'Valores y Totales'!C23 -> 0 | E23: =G$1*C23 -> 0
... B26: Chocochips | C26: 0 | D26: =C26*'Valores y Totales'!C26 -> 0 | E26: =G$1*C26 -> 0
B27: Mix Europeo | C27: 150 | D27: ='Valores y Totales'!C40*C27 -> 90 | E27: =G$1*C27 -> 150
C28: Una Receta | D28: Por Cantidad de Recetas
B29: Cantidad de Masitas | C29: 3 | D29: =C29*G$1 -> 3 | E29: 500 gm c/u o 18 muff
B30: Costo Receta | C30: =SUM(D2:D27) -> 6480 | D30: =C30*G$1 -> 6480
B32: Costo Individual | C32: =C30/C29 -> 2160 | D32: =C32 -> 2160

Sheet Budin de Naranja
B1: Ingrediente | C1: Gramos | D1: Precio | E1: Total Recetas | F1: Cantidad de Recetas: | G1: 1
B2: Aceite | C2: 100 | D2: =C2*'Valores y Totales'!C41 -> 120 | E2: =G$1*C2 -> 100
B3: Harina 0000 | C3: 0 | D3: =C3*'Valores y Totales'!C3 -> 0 | E3: =G$1*C3 -> 0 | H3: Una Receta | I3: Por Cantidad de Recetas
B4: Azucar Impalpable | C4: 300 | D4: =C4*'Valores y Totales'!C4 -> 450 | E4: =G$1*C4 -> 300 | G4: Cantidad de Porciones | H4: 1 | I4: =H4*G$1 -> 1
B5: Cacao | C5: 0 | D5: =C5*'Valores y Totales'!C5 -> 0 | E5: =G$1*C5 -> 0 | G5: Costo Receta | H5: =SUM(D2:D30) -> 7652 | I5: =H5*G$1 -> 7652
B6: Huevo (unidad) | C6: 2 | D6: =C6*'Valores y Totales'!B6 -> 420 | E6: =G$1*C6 -> 2 | G6: Costo Docena | I6: =H6 -> 0
B7: Azucar Común | C7: 200 | D7: =C7*'Valores y Totales'!C7 -> 280 | E7: =G$1*C7 -> 200 | G7: Costo Individual | H7: =H5/H4 -> 7652 | I7: =H7 -> 7652
B8: Maizena | C8: 0 | D8: =C8*'Valores y Totales'!C8 -> 0 | E8: =G$1*C8 -> 0
B9: Chocolate Taza | C9: 0 | D9: =C9*'Valores y Totales'!C9 -> 0 | E9: =G$1*C9 -> 0
B10: Nueces | C10: 0 | D10: =C10*'Valores y Totales'!C10 -> 0 | E10: =G$1*C10 -> 0 | K10: 130 | L10: 1500
B11: Dulce de Leche | D11: =C11*'Valores y Totales'!C11 -> 0 | E11: =G$1*C11 -> 0 | K11: =L11*K10/L10 -> 8.6666667 | L11: 100
B12: Crema | D12: =C12*'Valores y Totales'!C12 -> 0 | E12: =G$1*C12 -> 0
B13: Harina Leudante | C13: 300 | D13: =C13*'Valores y Totales'!C13 -> 630 | E13: =G$1*C13 -> 300
B14: Limon | C14: 0 | D14: =C14*'Valores y Totales'!C14 -> 0 | E14: =G$1*C14 -> 0
B15: Bicarbonato | C15: 0 | D15: =C15*'Valores y Totales'!C15 -> 0 | E15: =G$1*C15 -> 0
B16: Polveo Hornear | C16: 0 | D16: =C16*'Valores y Totales'!C16 -> 0 | E16: =G$1*C16 -> 0
B17: Leche | C17: 50 | D17: =C17*'Valores y Totales'!C17 -> 125 | E17: =G$1*C17 -> 50
B18: Conac | C18: 0 | D18: =C18*'Valores y Totales'!C18 -> 0 | E18: =G$1*C18 -> 0
B19: Naranja | C19: 2 | D19: =C19*'Valores y Totales'!C19 -> 1000 | E19: =G$1*C19 -> 2
B20: Azucar Negro | C20: 0 | D20: =C20*'Valores y Totales'!C20 -> 0 | E20: =G$1*C20 -> 0
B21: Chocolate Baño | C21: 0 | D21: =C21*'Valores y Totales'!C21 -> 0 | E21: =G$1*C21 -> 0
B22: Biscochuelo | C22: 0 | D22: =C22*'Valores y Totales'!C22 -> 0 | E22: =G$1*C22 -> 0
B23: Ciruelas | C23: 0 | D23: =C23*'Valores y Totales'!C23 -> 0 | E23: =G$1*C23 -> 0
B24: Pasas | C24: 0 | D24: =C24*'Valores y Totales'!C24 -> 0 | E24: =G$1*C24 -> 0
... B26: Chocochips | C26: 100 | D26: =C26*'Valores y Totales'!C26 -> 800 | E26: =G$1*C26 -> 100
C28: Una Receta | D28: Por Cantidad de Recetas
B29: Cantidad de Masitas | C29: 2 | D29: =C29*G$1 -> 2 | E29: 500 gm c/u o 18 muff
B30: Costo Receta | C30: =SUM(D2:D27) -> 3825 | D30: =C30*G$1 -> 3825
B32: Costo Individual | C32: =C30/C29 -> 1912.5 | D32: =C32 -> 1912.5

Sheet Cookies Choco Naranja
B1: Ingrediente | C1: Gramos | D1: Precio | E1: Total Recetas | F1: Cantidad de Recetas: | G1: 1
B2: Manteca | C2: 110 | D2: =C2*'Valores y Totales'!C2 -> 1210 | E2: =G$1*C2 -> 110
B3: Harina 0000 | C3: 155 | D3: =C3*'Valores y Totales'!C3 -> 170.5 | E3: =G$1*C3 -> 155
B4: Azucar Impalpable | C4: 0 | D4: =C4*'Valores y Totales'!C4 -> 0 | E4: =G$1*C4 -> 0
B5: Cacao | C5: 50 | D5: =C5*'Valores y Totales'!C5 -> 1250 | E5: =G$1*C5 -> 50
B6: Huevo (unidad) | C6: 2 | D6: =C6*'Valores y Totales'!B6 -> 420 | E6: =G$1*C6 -> 2
B7: Azucar Común | C7: 0 | D7: =C7*'Valores y Totales'!C7 -> 0 | E7: =G$1*C7 -> 0
B8: Maizena | C8: 0 | D8: =C8*'Valores y Totales'!C8 -> 0 | E8: =G$1*C8 -> 0
B9: Chocolate Taza | C9: 225 | D9: =C9*'Valores y Totales'!C9 -> 5850 | E9: =G$1*C9 -> 225
B10: Nueces | C10: 0 | D10: =C10*'Valores y Totales'!C10 -> 0 | E10: =G$1*C10 -> 0
B11: Dulce de Leche | C11: 0 | D11: =C11*'Valores y Totales'!C11 -> 0 | E11: =G$1*C11 -> 0
B12: Crema | C12: 0 | D12: =C12*'Valores y Totales'!C12 -> 0 | E12: =G$1*C12 -> 0
B13: Harina Leudante | C13: 0 | D13: =C13*'Valores y Totales'!C13 -> 0 | E13: =G$1*C13 -> 0
B14: Limon | C14: 0 | D14: =C14*'Valores y Totales'!C14 -> 0 | E14: =G$1*C14 -> 0
B15: Bicarbonato | C15: 0 | D15: =C15*'Valores y Totales'!C15 -> 0 | E15: =G$1*C15 -> 0
B16: Polveo Hornear | C16: 10 | D16: =C16*'Valores y Totales'!C16 -> 40 | E16: =G$1*C16 -> 10
B17: Leche | C17: 70 | D17: =C17*'Valores y Totales'!C17 -> 175 | E17: =G$1*C17 -> 70
B18: Conac | C18: 0 | D18: =C18*'Valores y Totales'!C18 -> 0 | E18: =G$1*C18 -> 0
... B26: Chocochips | C26: 100 | D26: =C26*'Valores y Totales'!C26 -> 800 | E26: =G$1*C26 -> 100
B27: Chips Cobertura | C27: 0 | D27: =C27*'Valores y Totales'!#REF! -> #REF! | E27: =G$1*C27 -> 0
B28: Almendras | C28: 100 | D28: ='Valores y Totales'!C51 -> 9.9 | E28: =G$1*C28 -> 100
C29: Una Receta | D29: Por Cantidad de Recetas
B30: Cantidad de Porciones | C30: 55 | D30: =C30*G$1 -> 55
B31: Costo Receta | C31: =SUM(D2:D27) -> #REF! | D31: =C31*G$1 -> #REF!
B32: Costo Docena | C32: =C31/C30*12 -> #REF! | D32: =C32 -> #REF!
B33: Costo Individual | C33: =C31/C30 -> #REF! | D33: =C33 -> #REF!
B34: Las masitas son de 5 cm de diámetro

Sheet Lista de Precios Clientes
B1: Producto | C1: Costo Individual | D1: Precio al Público | E1: Precio por Docena | F1: Porciones | G1: Costo Receta | H1: Valor Venta Receta
B2: Alfajores Mini Chocolate (3cm) | C2: =G2/F2 -> 176.0625 | D2: =H2/F2 -> 528.1875 | E2: =Tabla134[[#This Row],[Precio al Público]]*12 -> 6338.25 | F2: ='Alfajores de Chocolate'!C29 -> 80 | G2: ='Alfajores de Chocolate'!C30 -> 14085 | H2: =G2*3 -> 42255
B3: Alfajores Mini Maicena (3cm) | C3: =G3/F3 -> 118.58333 | D3: =H3/F3 -> 355.75 | E3: =Tabla134[[#This Row],[Precio al Público]]*12 -> 4269 | F3: ='Alfajores de Maicena'!C29 -> 80 | G3: ='Alfajores de Maicena'!C30 -> 9486.6667 | H3: =G3*3 -> 28460
B4: Alfajores Mini Rogel | C4: =G4/F4 -> 95.875 | D4: =H4/F4 -> 287.625 | E4: =Tabla134[[#This Row],[Precio al Público]]*12 -> 3451.5 | F4: =MiniRogel!C29 -> 80 | G4: =MiniRogel!C30 -> 7670 | H4: =G4*3 -> 23010
B5: Alfajores de Nuez Mini (3cm) | C5: ='Alfajores de Nuez'!C32 -> 209.08333 | D5: =H5/F5 -> 627.25 | E5: =Tabla134[[#This Row],[Precio al Público]]*12 -> 7527 | F5: ='Alfajores de Nuez'!C29 -> 60 | G5: ='Alfajores de Nuez'!C30 -> 12545 | H5: =G5*3 -> 37635
B6: Brownies Plancha Completa | C6: =G6/F6 -> 15388 | D6: =H6*Tabla134[[#This Row],[Porciones]] -> 46164 | F6: 1 | G6: =Brownies!C30 -> 15388 | H6: =G6*3 -> 46164
B7: Brownies DDL 24 cm MERENGUE | C7: =G7/F7 -> 12104 | D7: =H7/F7 -> 36312 | F7: 1 | G7: =Brownies!C$30*1/2+'Valores y Totales'!C$21*200+'Merengue Italiano'!D32+'Valores y Totales'!C$11*300 -> 12104 | H7: =G7*3 -> 36312
B8: Brownies DDL 20 cm MERENGUE | C8: =G8/F8 -> 8584.3333 | D8: =H8/F8 -> 25753 | F8: 1 | G8: =Brownies!C$30*1/3+'Valores y Totales'!C$21*100+'Merengue Italiano'!D32*1/2++'Valores y Totales'!C$21*200 -> 8584.3333 | H8: =G8*3 -> 25753
B9: Brownies Bariloche 24 cm | C9: =G9/F9 -> 17194 | D9: =H9/F9 -> 51582 | F9: 1 | G9: =Brownies!C$30*1/2+'Frosting Bariloche'!D$32*1+'Valores y Totales'!C$21*200 -> 17194 | H9: =G9*3 -> 51582
B10: Brownies Bariloche 20 cm | C10: =G10/F10 -> 9879.3333 | D10: =H10/F10 -> 29638 | F10: 1 | G10: =Brownies!C$30*1/3+'Frosting Bariloche'!D$32*1/2+'Valores y Totales'!C$21*100 -> 9879.3333 | H10: =G10*3 -> 29638
B11: Budín de Banana 500 gr. | C11: =G11/F11 -> 2250 | D11: =H11/F11 -> 6750 | F11: ='Budin de Banana'!C29 -> 2 | G11: ='Budin de Banana'!C30 -> 4500 | H11: =G11*3 -> 13500
B12: Budín de Manzanas 500 gr. | C12: =G12/F12 -> 1500 | D12: =H12/F12 -> 4500 | F12: ='Budin de Manzanas'!C29 -> 2 | G12: ='Budin de Manzanas'!C30 -> 3000 | H12: =G12*3 -> 9000
B13: Cakepops | C13: =G13/F13 -> 180.90278 | D13: =H13/F13 -> 542.70833 | E13: =Tabla134[[#This Row],[Precio al Público]]*12 -> 6512.5 | F13: =Cakepops!D30 -> 36 | G13: =Cakepops!C31 -> 6512.5 | H13: =G13*3 -> 19537.5
B14: Cookies de Pasas Y Nueces | C14: =G14/F14 -> 77.5815 | D14: =H14/F14 -> 232.7445 | E14: =Tabla134[[#This Row],[Precio al Público]]*12 -> 2792.934 | F14: ='Cookies Pasas y Nueces'!C29 -> 100 | G14: ='Cookies Pasas y Nueces'!C30 -> 7758.15 | H14: =G14*3 -> 23274.45
B15: Cookies Choco Chips Rocklets | C15: =G15/F15 -> 92.25 | D15: =H15/F15 -> 276.75 | E15: =Tabla134[[#This Row],[Precio al Público]]*12 -> 3321 | F15: ='Cookies Vaini-Chips Rocklets'!C29 -> 80 | G15: ='Cookies Vaini-Chips Rocklets'!C30 -> 7380 | H15: =G15*3 -> 22140
B16: Donas de Vinilla | C16: =G16/F16 -> 147.22222 | D16: =H16/F16 -> 441.66667 | E16: =Tabla134[[#This Row],[Precio al Público]]*12 -> 5300 | F16: ='Donas de Vainilla'!C29 -> 36 | G16: ='Donas de Vainilla'!C30 -> 5300 | H16: =G16*3 -> 15900
B17: Espumita de Limón Plancha 20x30 | C17: =G17/F17 -> 4855.5 | D17: =H17/F17 -> 14566.5 | F17: 1 | G17: ='Espumita de Limon'!C30 -> 4855.5 | H17: =G17*3 -> 14566.5
B18: Masitas Manteca Vainilla | C18: =G18/F18 -> 95.45 | D18: =H18/F18 -> 286.35 | E18: =Tabla134[[#This Row],[Precio al Público]]*12 -> 3436.2 | F18: ='Masitas de Manteca'!C29 -> 40 | G18: ='Masitas de Manteca'!C30 -> 3818 | H18: =G18*3 -> 11454
B19: Torta Galesa | C19: =G19/F19 -> 4808.0667 | D19: =H19/F19 -> 14424.2 | F19: ='Torta Galesa'!C29 -> 2 | G19: ='Torta Galesa'!C30 -> 9616.1333 | H19: =G19*3 -> 28848.4
B20: Torta Butter Cream 18 cm | C20: =G20/F20 -> 23662.5 | D20: =H20/F20 -> 70987.5 | F20: 1 | G20: ='Torta Butter Cream 18'!E6 -> 23662.5 | H20: =G20*3 -> 70987.5
B21: Torta Butter Cream 15 cm | C21: =G21/F21 -> 14025 | D21: =H21/F21 -> 42075 | F21: 1 | G21: ='Torta Butter Cream 15 cm'!E6 -> 14025 | H21: =G21*3 -> 42075
B22: Torta Number | C22: =G22/F22 -> 12210 | D22: =H22/F22 -> 36630 | F22: 1 | G22: ='Torta Number'!E6 -> 12210 | H22: =G22*3 -> 36630
B23: Pasta frola Dulce de Leche | C23: =G23/F23 -> 5305 | D23: =H23/F23 -> 15915 | F23: ='Pastafrola Dulce de Leche'!C29 -> 2 | G23: ='Pastafrola Dulce de Leche'!C30 -> 10610 | H23: =G23*3 -> 31830
B24: Cascaritas 100 gr | C24: =G24/F24 -> 1380.1 | D24: =H24/F24 -> 4140.3 | F24: 1 | G24: =Cascaritas!D$32/5 -> 1380.1 | H24: =G24*3 -> 4140.3
B25: Pepas | C25: =Pepas!C33 -> 96.5 | D25: =C25*3 -> 289.5 | E25: =D25*12 -> 3474
B26: Crema Bariloche | C26: ='Crema Bariloche'!C30 -> 8160 | D26: =C26*3 -> 24480
B27: Butter Cream ODRA | C27: ='Butter Cream Odra'!C30 -> 6900 | D27: =C27*3 -> 20700
B28: Torta Manteca ODRA | C28: ='Torta Manteca ODRA'!C30 -> 6775 | D28: =C28*3 -> 20325
B29: Nuez Chocolate | C29: ='Bombon Nuez con Chocolate'!C30/'Bombon Nuez con Chocolate'!C29 -> 326 | D29: =C29*3 -> 978
B30: Alfajores Choco-Nutella 4cm | C30: ='Alfajores de Chocolate 4 cm NUT'!C32 -> 211.585 | D30: =C30*3 -> 634.755 | E30: =D30*12 -> 7617.06
B31: Alfajores de Maicena 4 cm | C31: ='Alfajores de Maicena 4 cm'!C33 -> 178.38095 | D31: =C31*3 -> 535.14286 | E31: =D31*12 -> 6421.7143
B32: Alfajores Chocolate 4cm | C32: ='Alfajores de Chocolate 4 cm'!C32 -> 302.125 | D32: =C32*3 -> 906.375 | E32: =D32*12 -> 10876.5
B33: Mini Frola Membrillo | C33: ='Minifrola-Membrillo'!C33 -> 779 | D33: =C33*3 -> 2337
B34: Tarta de Coco 20x30 | C34: ='Tarta de Coco placa 20x30'!C33 -> 292.26667 | D34: =C34*3 -> 876.8 | E34: =D34*12 -> 10521.6 | F34: 30 | G34: ='Tarta de Coco placa 20x30'!C31 -> 8768 | H34: =G34*3 -> 26304

Sheet Frecuentes
B1: Producto | C1: Costo Individual | D1: Valor Venta Individual | E1: Porciones | F1: Costo Receta | G1: Valor Venta Receta
B2: Alfajores Chocolate | C2: =F2/E2 -> 176.0625 | D2: =G2/E2 -> 528.1875 | E2: ='Alfajores de Chocolate'!C29 -> 80 | F2: ='Alfajores de Chocolate'!C30 -> 14085 | G2: =F2*3 -> 42255
B3: Alfajores Maicena | C3: =F3/E3 -> 118.58333 | D3: =G3/E3 -> 355.75 | E3: ='Alfajores de Maicena'!C29 -> 80 | F3: ='Alfajores de Maicena'!C30 -> 9486.6667 | G3: =F3*3 -> 28460
B4: Alfajores Mini Rogel | C4: =F4/E4 -> 95.875 | D4: =G4/E4 -> 287.625 | E4: =MiniRogel!C29 -> 80 | F4: =MiniRogel!C30 -> 7670 | G4: =F4*3 -> 23010
B5: Alfajores de Nuez | C5: ='Alfajores de Nuez'!C32 -> 209.08333 | D5: =G5/E5 -> 627.25 | E5: ='Alfajores de Nuez'!C29 -> 60 | F5: ='Alfajores de Nuez'!C30 -> 12545 | G5: =F5*3 -> 37635
B6: Brownies | C6: =F6/E6 -> 256.46667 | D6: =G6/E6 -> 769.4 | E6: =Brownies!C29 -> 60 | F6: =Brownies!C30 -> 15388 | G6: =F6*3 -> 46164
B7: Brownies DDL 24 cm MERENGUE | C7: =F7/E7 -> 12104 | D7: =G7/E7 -> 36312 | E7: 1 | F7: =Brownies!C$30*1/2+'Valores y Totales'!C$21*200+'Merengue Italiano'!D32+'Valores y Totales'!C$11*300 -> 12104 | G7: =F7*3 -> 36312
B8: Brownies DDL 20 cm MERENGUE | C8: =F8/E8 -> 8584.3333 | D8: =G8/E8 -> 25753 | E8: 1 | F8: =Brownies!C$30*1/3+'Valores y Totales'!C$21*100+'Merengue Italiano'!D32*1/2++'Valores y Totales'!C$21*200 -> 8584.3333 | G8: =F8*3 -> 25753
B9: Brownies Bariloche 24 cm | C9: =F9/E9 -> 17194 | D9: =G9/E9 -> 51582 | E9: 1 | F9: =Brownies!C$30*1/2+'Frosting Bariloche'!D$32*1+'Valores y Totales'!C$21*200 -> 17194 | G9: =F9*3 -> 51582
B10: Brownies Bariloche 20 cm | C10: =F10/E10 -> 9879.3333 | D10: =G10/E10 -> 29638 | E10: 1 | F10: =Brownies!C$30*1/3+'Frosting Bariloche'!D$32*1/2+'Valores y Totales'!C$21*100 -> 9879.3333 | G10: =F10*3 -> 29638
B11: Budín de Banana | C11: =F11/E11 -> 2250 | D11: =G11/E11 -> 6750 | E11: ='Budin de Banana'!C29 -> 2 | F11: ='Budin de Banana'!C30 -> 4500 | G11: =F11*3 -> 13500
B12: Budín de Manzanas | C12: =F12/E12 -> 1500 | D12: =G12/E12 -> 4500 | E12: ='Budin de Manzanas'!C29 -> 2 | F12: ='Budin de Manzanas'!C30 -> 3000 | G12: =F12*3 -> 9000
B13: Cakepops | C13: =F13/E13 -> 180.90278 | D13: =G13/E13 -> 542.70833 | E13: =Cakepops!D30 -> 36 | F13: =Cakepops!C31 -> 6512.5 | G13: =F13*3 -> 19537.5
B14: Cookies Choco-chips | C14: =F14/E14 -> 98.333333 | D14: =G14/E14 -> 295 | E14: ='Cookies Chocochips'!C28 -> 66 | F14: ='Cookies Chocochips'!C29 -> 6490 | G14: =F14*3 -> 19470
B15: Cookies de Pasas Y Nueces | C15: =F15/E15 -> 77.5815 | D15: =G15/E15 -> 232.7445 | E15: ='Cookies Pasas y Nueces'!C29 -> 100 | F15: ='Cookies Pasas y Nueces'!C30 -> 7758.15 | G15: =F15*3 -> 23274.45
B16: Cookies Choco Chips Rocklets | C16: =F16/E16 -> 92.25 | D16: =G16/E16 -> 276.75 | E16: ='Cookies Vaini-Chips Rocklets'!C29 -> 80 | F16: ='Cookies Vaini-Chips Rocklets'!C30 -> 7380 | G16: =F16*3 -> 22140
B17: Donas de Chocolate | C17: =F17/E17 -> 163.25 | D17: =G17/E17 -> 489.75 | E17: 36 | F17: ='Donas de Chocolate'!C30 -> 5877 | G17: =F17*3 -> 17631
B18: Brookies Cookies doble choco | C18: =F18/E18 -> 313.47059 | D18: =G18/E18 -> 940.41176 | E18: ='Browkies - Cookies doble choco'!C28 -> 34 | F18: ='Browkies - Cookies doble choco'!C29 -> 10658 | G18: =F18*3 -> 31974
B19: Cookies Chip Taller | C19: =F19/E19 -> 137.97917 | D19: =G19/E19 -> 413.9375 | E19: ='Cookies Chip Taller'!C29 -> 24 | F19: ='Cookies Chip Taller'!C30 -> 3311.5 | G19: =F19*3 -> 9934.5
B20: Donas de Vinilla | C20: =F20/E20 -> 147.22222 | D20: =G20/E20 -> 441.66667 | E20: ='Donas de Vainilla'!C29 -> 36 | F20: ='Donas de Vainilla'!C30 -> 5300 | G20: =F20*3 -> 15900
B21: Espumita de Limón | C21: =F21/E21 -> 161.85 | D21: =G21/E21 -> 485.55 | E21: ='Espumita de Limon'!C29 -> 30 | F21: ='Espumita de Limon'!C30 -> 4855.5 | G21: =F21*3 -> 14566.5
B22: Ganache | C22: =F22/E22 -> #REF! | D22: =G22/E22 -> #REF! | E22: =Ganache!C29 -> 1 | F22: =Ganache!C30 -> #REF! | G22: =F22*3 -> #REF!
B23: Genoise | C23: =F23/E23 -> 2150 | D23: =G23/E23 -> 6450 | E23: 1 | F23: =Genoise!C30 -> 2150 | G23: =F23*3 -> 6450
B24: Masitas Manteca Vainilla | C24: =F24/E24 -> 95.45 | D24: =G24/E24 -> 286.35 | E24: ='Masitas de Manteca'!C29 -> 40 | F24: ='Masitas de Manteca'!C30 -> 3818 | G24: =F24*3 -> 11454
B25: Torta Galesa | C25: =F25/E25 -> 4808.0667 | D25: =G25/E25 -> 14424.2 | E25: ='Torta Galesa'!C29 -> 2 | F25: ='Torta Galesa'!C30 -> 9616.1333 | G25: =F25*3 -> 28848.4
B26: Torta Forrada 20 cm | C26: =F26/E26 -> #REF! | D26: =G26/E26 -> #REF! | E26: 1 | F26: ='Torta Forrada'!E8 -> #REF! | G26: =F26*3 -> #REF!
B27: Torta Butter Cream 18 cm | C27: =F27/E27 -> 23662.5 | D27: =G27/E27 -> 70987.5 | E27: 1 | F27: ='Torta Butter Cream 18'!E6 -> 23662.5 | G27: =F27*3 -> 70987.5
B28: Torta Butter Cream 15 cm | C28: =F28/E28 -> 14025 | D28: =G28/E28 -> 42075 | E28: 1 | F28: ='Torta Butter Cream 15 cm'!E6 -> 14025 | G28: =F28*3 -> 42075
B29: Torta Forrada 15 cm | C29: =C26*0.5 -> #REF! | D29: =G29/E29 -> #REF! | E29: 1 | F29: =F26*0.5 -> #REF! | G29: =F29*3 -> #REF!
B30: Torta Forrada 18 cm | C30: =C26*0.75 -> #REF! | D30: =G30/E30 -> #REF! | E30: 1 | F30: =F26*0.75 -> #REF! | G30: =F30*3 -> #REF!
B31: Torta Number | C31: =F31/E31 -> 12210 | D31: =G31/E31 -> 36630 | E31: 1 | F31: ='Torta Number'!E6 -> 12210 | G31: =F31*3 -> 36630
B32: Pasta frola Dulce de Leche | C32: =F32/E32 -> 5305 | D32: =G32/E32 -> 15915 | E32: ='Pastafrola Dulce de Leche'!C29 -> 2 | F32: ='Pastafrola Dulce de Leche'!C30 -> 10610 | G32: =F32*3 -> 31830
B33: Pasta frola Membrillo (2 Planchas) | C33: ='Pastafrola Membrillo'!C33 -> 194.75 | D33: =G33/E33 -> 584.25 | E33: ='Pastafrola Membrillo'!C30 -> 60 | F33: ='Pastafrola Membrillo'!C31 -> 11685 | G33: =F33*3 -> 35055
B34: Cascaritas 100 gr | C34: =F34/E34 -> 1380.1 | D34: =G34/E34 -> 4140.3 | E34: 1 | F34: =Cascaritas!D$32/5 -> 1380.1 | G34: =F34*3 -> 4140.3
B35: Pepas | C35: =Pepas!C33 -> 96.5 | D35: =C35*3 -> 289.5
B36: Crema Bariloche | C36: ='Crema Bariloche'!C30 -> 8160 | D36: =C36*3 -> 24480
B37: Butter Cream ODRA | C37: ='Butter Cream Odra'!C30 -> 6900 | D37: =C37*3 -> 20700
B38: Torta Manteca ODRA | C38: ='Torta Manteca ODRA'!C30 -> 6775 | D38: =C38*3 -> 20325
B39: Nuez Chocolate | C39: ='Bombon Nuez con Chocolate'!C30/'Bombon Nuez con Chocolate'!C29 -> 326 | D39: =C39*3 -> 978
B40: Alfajores Choco-Nutella 4cm | C40: ='Alfajores de Chocolate 4 cm NUT'!C32 -> 211.585 | D40: =C40*3 -> 634.755
B41: Alfajores de Maicena 4 cm | C41: ='Alfajores de Maicena 4 cm'!C33 -> 178.38095 | D41: =C41*3 -> 535.14286
B42: Alfajores Chocolate 4cm | C42: ='Alfajores de Chocolate 4 cm'!C32 -> 302.125 | D42: =C42*3 -> 906.375
B43: Mini Frola Membrillo | C43: ='Minifrola-Membrillo'!C33 -> 779 | D43: =C43*3 -> 2337
B44: Mini Frola DDL | C44: ='Minifrola-DDL'!C33 -> 700.33333 | D44: =C44*3 -> 2101
B45: Mini Frola DDL + Coco | C45: ='Minifrola-DDL-Coco'!C33 -> 1054.3333 | D45: =C45*3 -> 3163
B46: Mini Frola Manzana | C46: ='Minifrola-Manzana'!C33 -> 788.6 | D46: =C46*3 -> 2365.8
B47: Tarta de Coco | C47: ='Tarta de Coco placa 20x30'!C32 -> 292.26667 | D47: =G47/E47 -> 876.8 | E47: ='Tarta de Coco placa 20x30'!C30 -> 30 | F47: ='Tarta de Coco placa 20x30'!C31 -> 8768 | G47: =F47*3 -> 26304
B48: Torta Galesa | C48: ='Torta Galesa'!C32 -> 4808.0667 | D48: =C48*3 -> 14424.2
B49: Budin de Arandanos | C49: ='Budin de Arandanos'!C32 -> 3250.5 | D49: =C49*3 -> 9751.5

Sheet Torta Number
B2: Merengue Italiano | C2: 1 | D2: ='Merengue Italiano'!C30 -> 910 | E2: =C2*D2 -> 910
B3: Genoise | C3: 2 | D3: =Genoise!C30 -> 2150 | E3: =C3*D3 -> 4300
B4: Dulce de Leche | C4: 1000 | D4: ='Valores y Totales'!C11 -> 5 | E4: =C4*D4 -> 5000
B5: Chips de Chocolate | C5: 250 | D5: ='Valores y Totales'!C26 -> 8 | E5: =C5*D5 -> 2000
E6: =SUM(E2:E5) -> 12210

Sheet Torta Butter Cream 15 cm
B2: Torta Manteca ODRA | C2: 1 | D2: ='Torta Manteca ODRA'!C30 -> 6775 | E2: =C2*D2 -> 6775
B3: Butter Cream | C3: 0.5 | D3: ='Butter Cream Odra'!C30 -> 6900 | E3: =C3*D3 -> 3450
B4: Dulce de Leche | C4: 600 | D4: ='Valores y Totales'!C11 -> 5 | E4: =C4*D4 -> 3000
B5: Chips de Chocolate | C5: 100 | D5: ='Valores y Totales'!C26 -> 8 | E5: =C5*D5 -> 800
E6: =SUM(E2:E5) -> 14025

Sheet Torta Butter Cream 18
B2: Torta Manteca ODRA | C2: 1.5 | D2: ='Torta Manteca ODRA'!C30 -> 6775 | E2: =C2*D2 -> 10162.5
B3: Butter Cream | C3: 1 | D3: ='Butter Cream Odra'!C30 -> 6900 | E3: =C3*D3 -> 6900
B4: Dulce de Leche | C4: 1000 | D4: ='Valores y Totales'!C11 -> 5 | E4: =C4*D4 -> 5000
B5: Chips de Chocolate | C5: 200 | D5: ='Valores y Totales'!C26 -> 8 | E5: =C5*D5 -> 1600
E6: =SUM(E2:E5) -> 23662.5

Sheet Butter Cream Odra
B1: Ingrediente | C1: Gramos | D1: Precio | E1: Total Recetas | F1: Cantidad de Recetas: | G1: 1
B2: Manteca | C2: 500 | D2: =C2*'Valores y Totales'!C2 -> 5500 | E2: =G$1*C2 -> 500
B3: Harina 0000 | C3: 0 | D3: =C3*'Valores y Totales'!C3 -> 0 | E3: =G$1*C3 -> 0
B4: Azucar Impalpable | C4: 0 | D4: =C4*'Valores y Totales'!C4 -> 0 | E4: =G$1*C4 -> 0
B5: Cacao | C5: 0 | D5: =C5*'Valores y Totales'!C5 -> 0 | E5: =G$1*C5 -> 0
B6: Huevo (unidad) | C6: 4 | D6: =C6*'Valores y Totales'!B6 -> 840 | E6: =G$1*C6 -> 4
B7: Azucar Común | C7: 400 | D7: =C7*'Valores y Totales'!C7 -> 560 | E7: =G$1*C7 -> 400
B8: Maizena | C8: 0 | D8: =C8*'Valores y Totales'!C8 -> 0 | E8: =G$1*C8 -> 0
B9: Chocolate Taza | C9: 0 | D9: =C9*'Valores y Totales'!C9 -> 0 | E9: =G$1*C9 -> 0
B10: Nueces | C10: 0 | D10: =C10*'Valores y Totales'!C10 -> 0 | E10: =G$1*C10 -> 0
B11: Dulce de Leche | C11: 0 | D11: =C11*'Valores y Totales'!C11 -> 0 | E11: =G$1*C11 -> 0
B12: Crema | C12: 0 | D12: =C12*'Valores y Totales'!C12 -> 0 | E12: =G$1*C12 -> 0
B13: Harina Leudante | C13: 0 | D13: =C13*'Valores y Totales'!C13 -> 0 | E13: =G$1*C13 -> 0
B14: Limon | C14: 0 | D14: =C14*'Valores y Totales'!C14 -> 0 | E14: =G$1*C14 -> 0
B15: Bicarbonato | C15: 0 | D15: =C15*'Valores y Totales'!C15 -> 0 | E15: =G$1*C15 -> 0
B16: Polveo Hornear | C16: 0 | D16: =C16*'Valores y Totales'!C16 -> 0 | E16: =G$1*C16 -> 0
B17: Leche | C17: 0 | D17: =C17*'Valores y Totales'!C17 -> 0 | E17: =G$1*C17 -> 0
B18: Conac | C18: 0 | D18: =C18*'Valores y Totales'!C18 -> 0 | E18: =G$1*C18 -> 0
... B26: Chocochips | C26: 0 | D26: =C26*'Valores y Totales'!C26 -> 0 | E26: =G$1*C26 -> 0
C28: Una Receta | D28: Por Cantidad de Recetas
B29: Cantidad de Porciones | C29: 1 | D29: =C29*G$1 -> 1
B30: Costo Receta | C30: =SUM(D2:D26) -> 6900 | D30: =C30*G$1 -> 6900
B32: Costo Individual | C32: =C30/C29 -> 6900 | D32: =C32 -> 6900

Sheet Butter Cream Vainilla
B1: Ingrediente | C1: Gramos | D1: Precio | E1: Total Recetas | F1: Cantidad de Recetas: | G1: 1
B2: Manteca | C2: 250 | D2: =C2*'Valores y Totales'!C2 -> 2750 | E2: =G$1*C2 -> 250
B3: Harina 0000 | C3: 0 | D3: =C3*'Valores y Totales'!C3 -> 0 | E3: =G$1*C3 -> 0
B4: Azucar Impalpable | C4: 325 | D4: =C4*'Valores y Totales'!C4 -> 487.5 | E4: =G$1*C4 -> 325
B5: Cacao | C5: 0 | D5: =C5*'Valores y Totales'!C5 -> 0 | E5: =G$1*C5 -> 0
B6: Huevo (unidad) | C6: 0 | D6: =C6*'Valores y Totales'!B6 -> 0 | E6: =G$1*C6 -> 0
B7: Azucar Común | C7: 0 | D7: =C7*'Valores y Totales'!C7 -> 0 | E7: =G$1*C7 -> 0
B8: Maizena | C8: 0 | D8: =C8*'Valores y Totales'!C8 -> 0 | E8: =G$1*C8 -> 0
B9: Chocolate Taza | C9: 0 | D9: =C9*'Valores y Totales'!C9 -> 0 | E9: =G$1*C9 -> 0
B10: Nueces | C10: 0 | D10: =C10*'Valores y Totales'!C10 -> 0 | E10: =G$1*C10 -> 0
B11: Dulce de Leche | C11: 0 | D11: =C11*'Valores y Totales'!C11 -> 0 | E11: =G$1*C11 -> 0
B12: Crema | C12: 0 | D12: =C12*'Valores y Totales'!C12 -> 0 | E12: =G$1*C12 -> 0
B13: Harina Leudante | C13: 0 | D13: =C13*'Valores y Totales'!C13 -> 0 | E13: =G$1*C13 -> 0
B14: Limon | C14: 0 | D14: =C14*'Valores y Totales'!C14 -> 0 | E14: =G$1*C14 -> 0
B15: Bicarbonato | C15: 0 | D15: =C15*'Valores y Totales'!C15 -> 0 | E15: =G$1*C15 -> 0
B16: Polveo Hornear | C16: 0 | D16: =C16*'Valores y Totales'!C16 -> 0 | E16: =G$1*C16 -> 0
B17: Leche | C17: 30 | D17: =C17*'Valores y Totales'!C17 -> 75 | E17: =G$1*C17 -> 30
B18: Conac | C18: 0 | D18: =C18*'Valores y Totales'!C18 -> 0 | E18: =G$1*C18 -> 0
... B26: Chocochips | C26: 0 | D26: =C26*'Valores y Totales'!C26 -> 0 | E26: =G$1*C26 -> 0
C28: Una Receta | D28: Por Cantidad de Recetas
B29: Cantidad de Porciones | C29: 1 | D29: =C29*G$1 -> 1
B30: Costo Receta | C30: =SUM(D2:D26) -> 3312.5 | D30: =C30*G$1 -> 3312.5
B32: Costo Individual | C32: =C30/C29 -> 3312.5 | D32: =C32 -> 3312.5

Sheet Genoise
B1: Ingrediente | C1: Gramos | D1: Precio | E1: Total Recetas | F1: Cantidad de Recetas: | G1: 1
B2: Manteca | C2: 40 | D2: =C2*'Valores y Totales'!C2 -> 440 | E2: =G$1*C2 -> 40
B3: Harina 0000 | C3: 180 | D3: =C3*'Valores y Totales'!C3 -> 198 | E3: =G$1*C3 -> 180
B4: Azucar Impalpable | C4: 0 | D4: =C4*'Valores y Totales'!C4 -> 0 | E4: =G$1*C4 -> 0
B5: Cacao | C5: 0 | D5: =C5*'Valores y Totales'!C5 -> 0 | E5: =G$1*C5 -> 0
B6: Huevo (unidad) | C6: 6 | D6: =C6*'Valores y Totales'!B6 -> 1260 | E6: =G$1*C6 -> 6
B7: Azucar Común | C7: 180 | D7: =C7*'Valores y Totales'!C7 -> 252 | E7: =G$1*C7 -> 180
B8: Maizena | C8: 0 | D8: =C8*'Valores y Totales'!C8 -> 0 | E8: =G$1*C8 -> 0
B9: Chocolate Taza | C9: 0 | D9: =C9*'Valores y Totales'!C9 -> 0 | E9: =G$1*C9 -> 0
B10: Nueces | C10: 0 | D10: =C10*'Valores y Totales'!C10 -> 0 | E10: =G$1*C10 -> 0
B11: Dulce de Leche | C11: 0 | D11: =C11*'Valores y Totales'!C11 -> 0 | E11: =G$1*C11 -> 0
B12: Crema | C12: 0 | D12: =C12*'Valores y Totales'!C12 -> 0 | E12: =G$1*C12 -> 0
B13: Harina Leudante | C13: 0 | D13: =C13*'Valores y Totales'!C13 -> 0 | E13: =G$1*C13 -> 0
B14: Limon | C14: 0 | D14: =C14*'Valores y Totales'!C14 -> 0 | E14: =G$1*C14 -> 0
B15: Bicarbonato | C15: 0 | D15: =C15*'Valores y Totales'!C15 -> 0 | E15: =G$1*C15 -> 0
B16: Polveo Hornear | C16: 0 | D16: =C16*'Valores y Totales'!C16 -> 0 | E16: =G$1*C16 -> 0
B17: Leche | C17: 0 | D17: =C17*'Valores y Totales'!C17 -> 0 | E17: =G$1*C17 -> 0
B18: Conac | C18: 0 | D18: =C18*'Valores y Totales'!C18 -> 0 | E18: =G$1*C18 -> 0
... B26: Chocochips | C26: 0 | D26: =C26*'Valores y Totales'!C26 -> 0 | E26: =G$1*C26 -> 0
C28: Una Receta | D28: Por Cantidad de Recetas
B29: Cantidad de Porciones | C29: 1 | D29: =C29*G$1 -> 1
B30: Costo Receta | C30: =SUM(D2:D26) -> 2150 | D30: =C30*G$1 -> 2150
B32: Costo Individual | C32: =C30/C29 -> 2150 | D32: =C32 -> 2150

Sheet Bundt Chocolate
B1: Ingrediente | C1: Gramos | D1: Precio | E1: Total Recetas | F1: Cantidad de Recetas: | G1: 1
B2: Manteca | C2: 150 | D2: =C2*'Valores y Totales'!C2 -> 1650 | E2: =G$1*C2 -> 150
B3: Harina 0000 | C3: 0 | D3: =C3*'Valores y Totales'!C3 -> 0 | E3: =G$1*C3 -> 0
B4: Azucar Impalpable | C4: 0 | D4: =C4*'Valores y Totales'!C4 -> 0 | E4: =G$1*C4 -> 0
B5: Cacao | C5: 60 | D5: =C5*'Valores y Totales'!C5 -> 1500 | E5: =G$1*C5 -> 60
B6: Huevo (unidad) | C6: 3 | D6: =C6*'Valores y Totales'!B6 -> 630 | E6: =G$1*C6 -> 3
B7: Azucar Común | C7: 0 | D7: =C7*'Valores y Totales'!C7 -> 0 | E7: =G$1*C7 -> 0
B8: Maizena | C8: 0 | D8: =C8*'Valores y Totales'!C8 -> 0 | E8: =G$1*C8 -> 0
B9: Chocolate Taza | C9: 0 | D9: =C9*'Valores y Totales'!C9 -> 0 | E9: =G$1*C9 -> 0
B10: Nueces | C10: 0 | D10: =C10*'Valores y Totales'!C10 -> 0 | E10: =G$1*C10 -> 0
B11: Dulce de Leche | C11: 0 | D11: =C11*'Valores y Totales'!C11 -> 0 | E11: =G$1*C11 -> 0
B12: Crema | C12: 50 | D12: =C12*'Valores y Totales'!C12 -> 500 | E12: =G$1*C12 -> 50
B13: Harina Leudante | C13: 200 | D13: =C13*'Valores y Totales'!C13 -> 420 | E13: =G$1*C13 -> 200
B14: Limon | C14: 0 | D14: =C14*'Valores y Totales'!C14 -> 0 | E14: =G$1*C14 -> 0
B15: Bicarbonato | C15: 0 | D15: =C15*'Valores y Totales'!C15 -> 0 | E15: =G$1*C15 -> 0
B16: Polveo Hornear | C16: 0 | D16: =C16*'Valores y Totales'!C16 -> 0 | E16: =G$1*C16 -> 0
B17: Leche | C17: 0 | D17: =C17*'Valores y Totales'!C17 -> 0 | E17: =G$1*C17 -> 0
B18: Conac | C18: 0 | D18: =C18*'Valores y Totales'!C18 -> 0 | E18: =G$1*C18 -> 0
... B26: Chocochips | C26: 100 | D26: =C26*'Valores y Totales'!C26 -> 800 | E26: =G$1*C26 -> 100
C28: Una Receta | D28: Por Cantidad de Recetas
B29: Cantidad de Porciones | C29: 2 | D29: =C29*G$1 -> 2
B30: Costo Receta | C30: =SUM(D2:D26) -> 7460 | D30: =C30*G$1 -> 7460
B32: Costo Individual | C32: =C30/C29 -> 3730 | D32: =C32 -> 3730

Sheet Torta Forrada
B2: Torta Manteca ODRA | C2: 1 | D2: ='Torta Manteca ODRA'!C30 -> 6775 | E2: =C2*D2 -> 6775
B3: Torta Chocolate | C3: 0.5 | D3: ='Torta Chocolate'!C30 -> 5885 | E3: =C3*D3 -> 2942.5 | F3: lleva media
B4: Ganache | C4: 1 | D4: =Ganache!C30 -> #REF! | E4: =C4*D4 -> #REF!
B5: Pasta de Forrar | C5: 1000 | D5: ='Valores y Totales'!C31 -> 6 | E5: =C5*D5 -> 6000
B6: Dulce de Leche | C6: 1000 | D6: ='Valores y Totales'!C11 -> 5 | E6: =C6*D6 -> 5000
B7: Chips de Chocolate | C7: 100 | D7: ='Valores y Totales'!C26 -> 8 | E7: =C7*D7 -> 800
E8: =SUM(E2:E7) -> #REF!

Sheet Torta Manteca Butter Cream
B1: Ingrediente | C1: Gramos | D1: Precio | E1: Total Recetas | F1: Cantidad de Recetas: | G1: 1
B2: Manteca | C2: 250 | D2: =C2*'Valores y Totales'!C2 -> 2750 | E2: =G$1*C2 -> 250
B3: Harina 0000 | C3: 250 | D3: =C3*'Valores y Totales'!C3 -> 275 | E3: =G$1*C3 -> 250
B4: Azucar Impalpable | C4: 0 | D4: =C4*'Valores y Totales'!C4 -> 0 | E4: =G$1*C4 -> 0
B5: Cacao | C5: 0 | D5: =C5*'Valores y Totales'!C5 -> 0 | E5: =G$1*C5 -> 0
B6: Huevo (unidad) | C6: 5 | D6: =C6*'Valores y Totales'!B6 -> 1050 | E6: =G$1*C6 -> 5
B7: Azucar Común | C7: 250 | D7: =C7*'Valores y Totales'!C7 -> 350 | E7: =G$1*C7 -> 250
B8: Maizena | C8: 0 | D8: =C8*'Valores y Totales'!C8 -> 0 | E8: =G$1*C8 -> 0
B9: Chocolate Taza | C9: 0 | D9: =C9*'Valores y Totales'!C9 -> 0 | E9: =G$1*C9 -> 0
B10: Nueces | C10: 0 | D10: =C10*'Valores y Totales'!C10 -> 0 | E10: =G$1*C10 -> 0
B11: Dulce de Leche | C11: 0 | D11: =C11*'Valores y Totales'!C11 -> 0 | E11: =G$1*C11 -> 0
B12: Crema | C12: 0 | D12: =C12*'Valores y Totales'!C12 -> 0 | E12: =G$1*C12 -> 0
B13: Harina Leudante | C13: 0 | D13: =C13*'Valores y Totales'!C13 -> 0 | E13: =G$1*C13 -> 0
B14: Limon | C14: 0 | D14: =C14*'Valores y Totales'!C14 -> 0 | E14: =G$1*C14 -> 0
B15: Bicarbonato | C15: 0 | D15: =C15*'Valores y Totales'!C15 -> 0 | E15: =G$1*C15 -> 0
B16: Polveo Hornear | C16: 10 | D16: =C16*'Valores y Totales'!C16 -> 40 | E16: =G$1*C16 -> 10
B17: Leche | C17: 0 | D17: =C17*'Valores y Totales'!C17 -> 0 | E17: =G$1*C17 -> 0
B18: Conac | C18: 0 | D18: =C18*'Valores y Totales'!C18 -> 0 | E18: =G$1*C18 -> 0
... B26: Chocochips | C26: 0 | D26: =C26*'Valores y Totales'!C26 -> 0 | E26: =G$1*C26 -> 0
C28: Una Receta | D28: Por Cantidad de Recetas
B29: Cantidad de Porciones | C29: 1 | D29: =C29*G$1 -> 1
B30: Costo Receta | C30: =SUM(D2:D20) -> 4465 | D30: =C30*G$1 -> 4465
B32: Costo Individual | C32: =C30/C29 -> 4465 | D32: =C32 -> 4465

Sheet Donas de Vainilla
B1: Ingrediente | C1: Gramos | D1: Precio | E1: Total Recetas | F1: Cantidad de Recetas: | G1: 1
B2: Manteca | C2: 0 | D2: =C2*'Valores y Totales'!C2 -> 0 | E2: =G$1*C2 -> 0
B3: Harina 0000 | C3: 0 | D3: =C3*'Valores y Totales'!C3 -> 0 | E3: =G$1*C3 -> 0
B4: Azucar Impalpable | C4: 0 | D4: =C4*'Valores y Totales'!C4 -> 0 | E4: =G$1*C4 -> 0
B5: Cacao | C5: 0 | D5: =C5*'Valores y Totales'!C5 -> 0 | E5: =G$1*C5 -> 0
B6: Huevo (unidad) | C6: 3 | D6: =C6*'Valores y Totales'!B6 -> 630 | E6: =G$1*C6 -> 3
B7: Azucar Común | C7: 170 | D7: =C7*'Valores y Totales'!C7 -> 238 | E7: =G$1*C7 -> 170
B8: Maizena | C8: 0 | D8: =C8*'Valores y Totales'!C8 -> 0 | E8: =G$1*C8 -> 0
B9: Chocolate Taza | C9: 0 | D9: =C9*'Valores y Totales'!C9 -> 0 | E9: =G$1*C9 -> 0
B10: Nueces | C10: 0 | D10: =C10*'Valores y Totales'!C10 -> 0 | E10: =G$1*C10 -> 0
B11: Dulce de Leche | C11: 0 | D11: =C11*'Valores y Totales'!C11 -> 0 | E11: =G$1*C11 -> 0
B12: Crema | C12: 0 | D12: =C12*'Valores y Totales'!C12 -> 0 | E12: =G$1*C12 -> 0
B13: Harina Leudante | C13: 220 | D13: =C13*'Valores y Totales'!C13 -> 462 | E13: =G$1*C13 -> 220
B14: Limon | C14: 0 | D14: =C14*'Valores y Totales'!C14 -> 0 | E14: =G$1*C14 -> 0
B15: Bicarbonato | C15: 0 | D15: =C15*'Valores y Totales'!C15 -> 0 | E15: =G$1*C15 -> 0
B16: Polveo Hornear | C16: 0 | D16: =C16*'Valores y Totales'!C16 -> 0 | E16: =G$1*C16 -> 0
B17: Leche | C17: 100 | D17: =C17*'Valores y Totales'!C17 -> 250 | E17: =G$1*C17 -> 100
B18: Conac | C18: 0 | D18: =C18*'Valores y Totales'!C18 -> 0 | E18: =G$1*C18 -> 0
... B25: Yogur | C25: 0 | D25: =C25*'Valores y Totales'!C25 -> 0 | E25: =G$1*C25 -> 0
B26: Aceite | C26: 100 | D26: =C26*'Valores y Totales'!C41 -> 120 | E26: =G$1*C26 -> 100
C28: Una Receta | D28: Por Cantidad de Recetas
B29: Cantidad de Porciones | C29: 36 | D29: =C29*G$1 -> 36
B30: Costo Receta | C30: =SUM(D2:D26) -> 5300 | D30: =C30*G$1 -> 5300
B32: Costo Individual | C32: =C30/C29 -> 147.22222 | D32: =C32 -> 147.22222

Sheet Donas de Chocolate
B1: Ingrediente | C1: Gramos | D1: Precio | E1: Total Recetas | F1: Cantidad de Recetas: | G1: 1
B2: Manteca | C2: 120 | D2: =C2*'Valores y Totales'!C2 -> 1320 | E2: =G$1*C2 -> 120
B3: Harina 0000 | C3: 0 | D3: =C3*'Valores y Totales'!C3 -> 0 | E3: =G$1*C3 -> 0
B4: Azucar Impalpable | C4: 0 | D4: =C4*'Valores y Totales'!C4 -> 0 | E4: =G$1*C4 -> 0
B5: Cacao | C5: 40 | D5: =C5*'Valores y Totales'!C5 -> 1000 | E5: =G$1*C5 -> 40
B6: Huevo (unidad) | C6: 3 | D6: =C6*'Valores y Totales'!B6 -> 630 | E6: =G$1*C6 -> 3
B7: Azucar Común | C7: 0 | D7: =C7*'Valores y Totales'!C7 -> 0 | E7: =G$1*C7 -> 0
B8: Maizena | C8: 0 | D8: =C8*'Valores y Totales'!C8 -> 0 | E8: =G$1*C8 -> 0
B9: Chocolate Taza | C9: 0 | D9: =C9*'Valores y Totales'!C9 -> 0 | E9: =G$1*C9 -> 0
B10: Nueces | C10: 0 | D10: =C10*'Valores y Totales'!C10 -> 0 | E10: =G$1*C10 -> 0
B11: Dulce de Leche | C11: 0 | D11: =C11*'Valores y Totales'!C11 -> 0 | E11: =G$1*C11 -> 0
B12: Crema | C12: 50 | D12: =C12*'Valores y Totales'!C12 -> 500 | E12: =G$1*C12 -> 50
B13: Harina Leudante | C13: 160 | D13: =C13*'Valores y Totales'!C13 -> 336 | E13: =G$1*C13 -> 160
B14: Limon | C14: 0 | D14: =C14*'Valores y Totales'!C14 -> 0 | E14: =G$1*C14 -> 0
B15: Bicarbonato | C15: 0 | D15: =C15*'Valores y Totales'!C15 -> 0 | E15: =G$1*C15 -> 0
B16: Polveo Hornear | C16: 0 | D16: =C16*'Valores y Totales'!C16 -> 0 | E16: =G$1*C16 -> 0
B17: Leche | C17: 80 | D17: =C17*'Valores y Totales'!C17 -> 200 | E17: =G$1*C17 -> 80
B18: Conac | C18: 0 | D18: =C18*'Valores y Totales'!C18 -> 0 | E18: =G$1*C18 -> 0
... B26: Chocochips | C26: 0 | D26: =C26*'Valores y Totales'!C26 -> 0 | E26: =G$1*C26 -> 0
C28: Una Receta | D28: Por Cantidad de Recetas
B29: Cantidad de Porciones | C29: 36 | D29: =C29*G$1 -> 36
B30: Costo Receta | C30: =SUM(D2:D26) -> 5877 | D30: =C30*G$1 -> 5877
B32: Costo Individual | C32: =C30/C29 -> 163.25 | D32: =C32 -> 163.25

Sheet Bundt Naranja
B1: Ingrediente | C1: Gramos | D1: Precio
B2: Manteca | C2: 150 | D2: =C2*'Valores y Totales'!C2 -> 1650
B3: Harina 0000 | C3: 0 | D3: =C3*'Valores y Totales'!C3 -> 0
B4: Azucar Impalpable | C4: 250 | D4: =C4*'Valores y Totales'!C4 -> 375
B5: Cacao | C5: 0 | D5: =C5*'Valores y Totales'!C5 -> 0
B6: Huevo (unidad) | C6: 2 | D6: =C6*'Valores y Totales'!B6 -> 420
B7: Azucar Común | C7: 150 | D7: =C7*'Valores y Totales'!C7 -> 210
B8: Maizena | C8: 0 | D8: =C8*'Valores y Totales'!C8 -> 0
B9: Chocolate Taza | C9: 0 | D9: =C9*'Valores y Totales'!C9 -> 0
B10: Nueces | C10: 0 | D10: =C10*'Valores y Totales'!C10 -> 0
B11: Dulce de Leche | D11: =C11*'Valores y Totales'!C11 -> 0
B12: Crema | D12: =C12*'Valores y Totales'!C12 -> 0
B13: Harina Leudante | C13: 250 | D13: =C13*'Valores y Totales'!C13 -> 525
B14: Limon | C14: 1 | D14: =C14*'Valores y Totales'!C14 -> 500
B15: Bicarbonato | C15: 0 | D15: =C15*'Valores y Totales'!C15 -> 0
B16: Polveo Hornear | C16: 0 | D16: =C16*'Valores y Totales'!C16 -> 0
B17: Leche | C17: 100 | D17: =C17*'Valores y Totales'!C17 -> 250
B18: Conac | C18: 0 | D18: =C18*'Valores y Totales'!C18 -> 0
B19: Naranja | C19: 0 | D19: =C19*'Valores y Totales'!C19 -> 0
B20: Azucar Negro | C20: 0 | D20: =C20*'Valores y Totales'!C20 -> 0
B21: Chocolate Baño | C21: 0 | D21: =C21*'Valores y Totales'!C21 -> 0
B22: Biscochuelo | C22: 0 | D22: =C22*'Valores y Totales'!C22 -> 0
B23: Ciruelas | C23: 0 | D23: =C23*'Valores y Totales'!C23 -> 0
B24: Pasas | C24: 0 | D24: =C24*'Valores y Totales'!C24 -> 0
B25: Yogur | D25: =C25*'Valores y Totales'!C25 -> 0
B26: Chocochips | D26: =C26*'Valores y Totales'!C26 -> 0
C28: Una Receta | D28: Por Cantidad de Recetas
B29: Cantidad de Masitas | C29: 2
B30: Costo Receta | C30: =SUM(D2:D26) -> 3930
B32: Costo Individual | C32: =C30/C29 -> 1965 | D32: =C32 -> 1965

Sheet Budin Cítrico
B1: Ingrediente | C1: Gramos | D1: Precio | E1: Total Recetas | F1: Cantidad de Recetas: | G1: 1
B2: Manteca | C2: 150 | D2: =C2*'Valores y Totales'!C2 -> 1650 | E2: =G$1*C2 -> 150
B3: Harina 0000 | C3: 0 | D3: =C3*'Valores y Totales'!C3 -> 0 | E3: =G$1*C3 -> 0
B4: Azucar Impalpable | C4: 250 | D4: =C4*'Valores y Totales'!C4 -> 375 | E4: =G$1*C4 -> 250
B5: Cacao | C5: 0 | D5: =C5*'Valores y Totales'!C5 -> 0 | E5: =G$1*C5 -> 0
B6: Huevo (unidad) | C6: 2 | D6: =C6*'Valores y Totales'!B6 -> 420 | E6: =G$1*C6 -> 2
B7: Azucar Común | C7: 150 | D7: =C7*'Valores y Totales'!C7 -> 210 | E7: =G$1*C7 -> 150
B8: Maizena | C8: 0 | D8: =C8*'Valores y Totales'!C8 -> 0 | E8: =G$1*C8 -> 0
B9: Chocolate Taza | C9: 0 | D9: =C9*'Valores y Totales'!C9 -> 0 | E9: =G$1*C9 -> 0
B10: Nueces | C10: 0 | D10: =C10*'Valores y Totales'!C10 -> 0 | E10: =G$1*C10 -> 0
B11: Dulce de Leche | C11: 0 | D11: =C11*'Valores y Totales'!C11 -> 0 | E11: =G$1*C11 -> 0
B12: Crema | C12: 0 | D12: =C12*'Valores y Totales'!C12 -> 0 | E12: =G$1*C12 -> 0
B13: Harina Leudante | C13: 250 | D13: =C13*'Valores y Totales'!C13 -> 525 | E13: =G$1*C13 -> 250
B14: Limon | C14: 2 | D14: =C14*'Valores y Totales'!C14 -> 1000 | E14: =G$1*C14 -> 2
B15: Bicarbonato | C15: 0 | D15: =C15*'Valores y Totales'!C15 -> 0 | E15: =G$1*C15 -> 0
B16: Polveo Hornear | C16: 0 | D16: =C16*'Valores y Totales'!C16 -> 0 | E16: =G$1*C16 -> 0
B17: Leche | C17: 50 | D17: =C17*'Valores y Totales'!C17 -> 125 | E17: =G$1*C17 -> 50
B18: Conac | C18: 0 | D18: =C18*'Valores y Totales'!C18 -> 0 | E18: =G$1*C18 -> 0
... B26: Chocochips | C26: 100 | D26: =C26*'Valores y Totales'!C26 -> 800 | E26: =G$1*C26 -> 100
B27: Pera | C27: 0 | D27: =C27*'Valores y Totales'!C36 -> 0
C28: Una Receta | D28: Por Cantidad de Recetas
B29: Cantidad de Masitas | C29: 2 | D29: =C29*G$1 -> 2
B30: Costo Receta | C30: =SUM(D2:D27) -> 5105 | D30: =C30*G$1 -> 5105
B32: Costo Individual | C32: =C30/C29 -> 2552.5 | D32: =C32 -> 2552.5

Sheet Merengue Italiano
B1: Ingrediente | C1: Gramos | D1: Precio | E1: Total Recetas | F1: Cantidad de Recetas: | G1: 1
B2: Manteca | C2: 0 | D2: =C2*'Valores y Totales'!C2 -> 0 | E2: =G$1*C2 -> 0
B3: Harina 0000 | C3: 0 | D3: =C3*'Valores y Totales'!C3 -> 0 | E3: =G$1*C3 -> 0
B4: Azucar Impalpable | C4: 0 | D4: =C4*'Valores y Totales'!C4 -> 0 | E4: =G$1*C4 -> 0
B5: Cacao | C5: 0 | D5: =C5*'Valores y Totales'!C5 -> 0 | E5: =G$1*C5 -> 0
B6: Huevo (unidad) | C6: 3 | D6: =C6*'Valores y Totales'!B6 -> 630 | E6: =G$1*C6 -> 3
B7: Azucar Común | C7: 200 | D7: =C7*'Valores y Totales'!C7 -> 280 | E7: =G$1*C7 -> 200
B8: Maizena | C8: 0 | D8: =C8*'Valores y Totales'!C8 -> 0 | E8: =G$1*C8 -> 0
B9: Chocolate Taza | C9: 0 | D9: =C9*'Valores y Totales'!C9 -> 0 | E9: =G$1*C9 -> 0
B10: Nueces | C10: 0 | D10: =C10*'Valores y Totales'!C10 -> 0 | E10: =G$1*C10 -> 0
B11: Dulce de Leche | C11: 0 | D11: =C11*'Valores y Totales'!C11 -> 0 | E11: =G$1*C11 -> 0
B12: Crema | C12: 0 | D12: =C12*'Valores y Totales'!C12 -> 0 | E12: =G$1*C12 -> 0
B13: Harina Leudante | C13: 0 | D13: =C13*'Valores y Totales'!C13 -> 0 | E13: =G$1*C13 -> 0
B14: Limon | C14: 0 | D14: =C14*'Valores y Totales'!C14 -> 0 | E14: =G$1*C14 -> 0
B15: Bicarbonato | C15: 0 | D15: =C15*'Valores y Totales'!C15 -> 0 | E15: =G$1*C15 -> 0
B16: Polveo Hornear | C16: 0 | D16: =C16*'Valores y Totales'!C16 -> 0 | E16: =G$1*C16 -> 0
B17: Leche | C17: 0 | D17: =C17*'Valores y Totales'!C17 -> 0 | E17: =G$1*C17 -> 0
B18: Conac | C18: 0 | D18: =C18*'Valores y Totales'!C18 -> 0 | E18: =G$1*C18 -> 0
... B26: Chocochips | C26: 0 | D26: =C26*'Valores y Totales'!C26 -> 0 | E26: =G$1*C26 -> 0
C28: Una Receta | D28: Por Cantidad de Recetas
B29: Cantidad de Alfajores | C29: 1 | D29: =C29*G$1 -> 1
B30: Costo Receta | C30: =SUM(D2:D20) -> 910 | D30: =C30*G$1 -> 910
B31: Costo Docena | D31: =C31 -> 0
B32: Costo Individual | C32: =C30/C29 -> 910 | D32: =C32 -> 910

Sheet Pastafrola Dulce de Leche
B1: Ingrediente | C1: Gramos | D1: Precio | E1: Total Recetas | F1: Cantidad de Recetas: | G1: 1
B2: Manteca | C2: 150 | D2: =C2*'Valores y Totales'!C2 -> 1650 | E2: =G$1*C2 -> 150
B3: Harina 0000 | C3: 400 | D3: =C3*'Valores y Totales'!C3 -> 440 | E3: =G$1*C3 -> 400
B4: Azucar Impalpable | C4: 100 | D4: =C4*'Valores y Totales'!C4 -> 150 | E4: =G$1*C4 -> 100
B5: Cacao | C5: 0 | D5: =C5*'Valores y Totales'!C5 -> 0 | E5: =G$1*C5 -> 0
B6: Huevo (unidad) | C6: 3 | D6: =C6*'Valores y Totales'!B6 -> 630 | E6: =G$1*C6 -> 3
B7: Azucar Común | C7: 0 | D7: =C7*'Valores y Totales'!C7 -> 0 | E7: =G$1*C7 -> 0
B8: Maizena | C8: 0 | D8: =C8*'Valores y Totales'!C8 -> 0 | E8: =G$1*C8 -> 0
B9: Chocolate Taza | C9: 0 | D9: =C9*'Valores y Totales'!C9 -> 0 | E9: =G$1*C9 -> 0
B10: Nueces | C10: 100 | D10: =C10*'Valores y Totales'!C10 -> 2200 | E10: =G$1*C10 -> 100
B11: Dulce de Leche | C11: 1000 | D11: =C11*'Valores y Totales'!C11 -> 5000 | E11: =G$1*C11 -> 1000
B12: Crema | C12: 0 | D12: =C12*'Valores y Totales'!C12 -> 0 | E12: =G$1*C12 -> 0
B13: Harina Leudante | C13: 0 | D13: =C13*'Valores y Totales'!C13 -> 0 | E13: =G$1*C13 -> 0
B14: Limon | C14: 1 | D14: =C14*'Valores y Totales'!C14 -> 500 | E14: =G$1*C14 -> 1
B15: Bicarbonato | C15: 0 | D15: =C15*'Valores y Totales'!C15 -> 0 | E15: =G$1*C15 -> 0
B16: Polveo Hornear | C16: 10 | D16: =C16*'Valores y Totales'!C16 -> 40 | E16: =G$1*C16 -> 10
B17: Leche | C17: 0 | D17: =C17*'Valores y Totales'!C17 -> 0 | E17: =G$1*C17 -> 0
B18: Conac | C18: 0 | D18: =C18*'Valores y Totales'!C18 -> 0 | E18: =G$1*C18 -> 0
... B26: Chocochips | C26: 0 | D26: =C26*'Valores y Totales'!C26 -> 0 | E26: =G$1*C26 -> 0
C28: Una Receta | D28: Por Cantidad de Recetas
B29: Cantidad | C29: 2 | D29: =C29*G$1 -> 2
B30: Costo Receta | C30: =SUM(D2:D21) -> 10610 | D30: =C30*G$1 -> 10610
B31: Costo Docena
B32: Costo Individual | C32: =C30/C29 -> 5305 | D32: =C32 -> 5305

Sheet Cookies Vaini-Chips Rocklets
B1: Ingrediente | C1: Gramos | D1: Precio | E1: Total Recetas | F1: Cantidad de Recetas: | G1: 1
B2: Manteca | C2: 200 | D2: =C2*'Valores y Totales'!C2 -> 2200 | E2: =G$1*C2 -> 200
B3: Harina 0000 | C3: 400 | D3: =C3*'Valores y Totales'!C3 -> 440 | E3: =G$1*C3 -> 400
B4: Azucar Impalpable | C4: 0 | D4: =C4*'Valores y Totales'!C4 -> 0 | E4: =G$1*C4 -> 0
B5: Cacao | C5: 0 | D5: =C5*'Valores y Totales'!C5 -> 0 | E5: =G$1*C5 -> 0
B6: Huevo (unidad) | C6: 2 | D6: =C6*'Valores y Totales'!B6 -> 420 | E6: =G$1*C6 -> 2
B7: Azucar Común | C7: 400 | D7: =C7*'Valores y Totales'!C7 -> 560 | E7: =G$1*C7 -> 400
B8: Maizena | C8: 0 | D8: =C8*'Valores y Totales'!C8 -> 0 | E8: =G$1*C8 -> 0
B9: Chocolate Taza | C9: 0 | D9: =C9*'Valores y Totales'!C9 -> 0 | E9: =G$1*C9 -> 0
B10: Nueces | C10: 0 | D10: =C10*'Valores y Totales'!C10 -> 0 | E10: =G$1*C10 -> 0
B11: Dulce de Leche | C11: 0 | D11: =C11*'Valores y Totales'!C11 -> 0 | E11: =G$1*C11 -> 0
B12: Crema | C12: 0 | D12: =C12*'Valores y Totales'!C12 -> 0 | E12: =G$1*C12 -> 0
B13: Harina Leudante | C13: 0 | D13: =C13*'Valores y Totales'!C13 -> 0 | E13: =G$1*C13 -> 0
B14: Limon | C14: 0 | D14: =C14*'Valores y Totales'!C14 -> 0 | E14: =G$1*C14 -> 0
B15: Bicarbonato | C15: 0 | D15: =C15*'Valores y Totales'!C15 -> 0 | E15: =G$1*C15 -> 0
B16: Polveo Hornear | C16: 15 | D16: =C16*'Valores y Totales'!C16 -> 60 | E16: =G$1*C16 -> 15
B17: Leche | C17: 0 | D17: =C17*'Valores y Totales'!C17 -> 0 | E17: =G$1*C17 -> 0
B18: Conac | C18: 0 | D18: =C18*'Valores y Totales'!C18 -> 0 | E18: =G$1*C18 -> 0
... B26: Chocochips | C26: 150 | D26: =C26*'Valores y Totales'!C26 -> 1200 | E26: =G$1*C26 -> 150
B27: Rocklets | C27: 200 | D27: =C27*'Valores y Totales'!C42 -> 2500 | E27: =G$1*C27 -> 200
C28: Una Receta | D28: Por Cantidad de Recetas
B29: Cantidad de Porciones | C29: 80 | D29: =C29*G$1 -> 80
B30: Costo Receta | C30: =SUM(D2:D27) -> 7380 | D30: =C30*G$1 -> 7380
B31: Costo Docena | C31: =C30/C29*12 -> 1107 | D31: =C31 -> 1107
B32: Costo Individual | C32: =C30/C29 -> 92.25 | D32: =C32 -> 92.25
B33: Las masitas son de 5 cm de diámetro

Sheet Budin de Manzanas
B1: Ingrediente | C1: Gramos | D1: Precio | E1: Total Recetas | F1: Cantidad de Recetas: | G1: 1
B2: Aceite | C2: 100 | D2: =C2*'Valores y Totales'!C41 -> 120 | E2: =G$1*C2 -> 100
B3: Harina 0000 | C3: 0 | D3: =C3*'Valores y Totales'!C3 -> 0 | E3: =G$1*C3 -> 0 | H3: Una Receta | I3: Por Cantidad de Recetas
B4: Azucar Impalpable | C4: 200 | D4: =C4*'Valores y Totales'!C4 -> 300 | E4: =G$1*C4 -> 200 | G4: Cantidad de Porciones | H4: 1 | I4: =H4*G$1 -> 1
B5: Cacao | C5: 0 | D5: =C5*'Valores y Totales'!C5 -> 0 | E5: =G$1*C5 -> 0 | G5: Costo Receta | H5: =SUM(D2:D30) -> 6002 | I5: =H5*G$1 -> 6002
B6: Huevo (unidad) | C6: 2 | D6: =C6*'Valores y Totales'!B6 -> 420 | E6: =G$1*C6 -> 2 | G6: Costo Docena | I6: =H6 -> 0
B7: Azucar Común | C7: 200 | D7: =C7*'Valores y Totales'!C7 -> 280 | E7: =G$1*C7 -> 200 | G7: Costo Individual | H7: =H5/H4 -> 6002 | I7: =H7 -> 6002
B8: Maizena | C8: 0 | D8: =C8*'Valores y Totales'!C8 -> 0 | E8: =G$1*C8 -> 0
B9: Chocolate Taza | C9: 0 | D9: =C9*'Valores y Totales'!C9 -> 0 | E9: =G$1*C9 -> 0
B10: Nueces | C10: 0 | D10: =C10*'Valores y Totales'!C10 -> 0 | E10: =G$1*C10 -> 0
B11: Dulce de Leche | D11: =C11*'Valores y Totales'!C11 -> 0 | E11: =G$1*C11 -> 0
B12: Crema | D12: =C12*'Valores y Totales'!C12 -> 0 | E12: =G$1*C12 -> 0
B13: Harina Leudante | C13: 300 | D13: =C13*'Valores y Totales'!C13 -> 630 | E13: =G$1*C13 -> 300
B14: Limon | C14: 1 | D14: =C14*'Valores y Totales'!C14 -> 500 | E14: =G$1*C14 -> 1
B15: Bicarbonato | C15: 0 | D15: =C15*'Valores y Totales'!C15 -> 0 | E15: =G$1*C15 -> 0
B16: Polveo Hornear | C16: 0 | D16: =C16*'Valores y Totales'!C16 -> 0 | E16: =G$1*C16 -> 0
B17: Leche | C17: 100 | D17: =C17*'Valores y Totales'!C17 -> 250 | E17: =G$1*C17 -> 100
B18: Conac | C18: 0 | D18: =C18*'Valores y Totales'!C18 -> 0 | E18: =G$1*C18 -> 0
B19: Naranja | C19: 1 | D19: =C19*'Valores y Totales'!C19 -> 500 | E19: =G$1*C19 -> 1 | F19: Cambiar por la fruta deseada
B20: Azucar Negro | C20: 0 | D20: =C20*'Valores y Totales'!C20 -> 0 | E20: =G$1*C20 -> 0
B21: Chocolate Baño | C21: 0 | D21: =C21*'Valores y Totales'!C21 -> 0 | E21: =G$1*C21 -> 0
B22: Biscochuelo | C22: 0 | D22: =C22*'Valores y Totales'!C22 -> 0 | E22: =G$1*C22 -> 0
B23: Ciruelas | C23: 0 | D23: =C23*'Valores y Totales'!C23 -> 0 | E23: =G$1*C23 -> 0
B24: Pasas | C24: 0 | D24: =C24*'Valores y Totales'!C24 -> 0 | E24: =G$1*C24 -> 0
B25: Yogur | C25: 0 | D25: =C25*'Valores y Totales'!C25 -> 0 | E25: =G$1*C25 -> 0
B26: Chocochips | C26: 0 | D26: =C26*'Valores y Totales'!C26 -> 0 | E26: =G$1*C26 -> 0
C28: Una Receta | D28: Por Cantidad de Recetas
B29: Cantidad de Masitas | C29: 2 | D29: =C29*G$1 -> 2 | E29: 500 gm c/u o 18 muff
B30: Costo Receta | C30: =SUM(D2:D27) -> 3000 | D30: =C30*G$1 -> 3000
B32: Costo Individual | C32: =C30/C29 -> 1500 | D32: =C32 -> 1500

Sheet Precios
B1: Producto | C1: Costo Individual | D1: Valor Venta Individual | E1: Porciones | F1: Costo Receta | G1: Valor Venta Receta
B2: Alfajores Chocolate | C2: =F2/E2 -> 176.0625 | D2: =G2/E2 -> 528.1875 | E2: ='Alfajores de Chocolate'!C29 -> 80 | F2: ='Alfajores de Chocolate'!C30 -> 14085 | G2: =F2*3 -> 42255
B3: Alfajores Maicena | C3: =F3/E3 -> 118.58333 | D3: =G3/E3 -> 355.75 | E3: ='Alfajores de Maicena'!C29 -> 80 | F3: ='Alfajores de Maicena'!C30 -> 9486.6667 | G3: =F3*3 -> 28460
B4: Alfajores Mini Rogel | C4: =F4/E4 -> 95.875 | D4: =G4/E4 -> 287.625 | E4: =MiniRogel!C29 -> 80 | F4: =MiniRogel!C30 -> 7670 | G4: =F4*3 -> 23010
B5: Biscuit Chocolate | C5: =F5/E5 -> 8846.5 | D5: =G5/E5 -> 26539.5 | E5: ='Biscuit Chocolate'!C29 -> 1 | F5: ='Biscuit Chocolate'!C30 -> 8846.5 | G5: =F5*3 -> 26539.5
B6: Brownies | C6: =F6/E6 -> 256.46667 | D6: =G6/E6 -> 769.4 | E6: =Brownies!C29 -> 60 | F6: =Brownies!C30 -> 15388 | G6: =F6*3 -> 46164
B7: Budín Cítrico | C7: =F7/E7 -> 2552.5 | D7: =G7/E7 -> 7657.5 | E7: 2 | F7: ='Budin Cítrico'!C30 -> 5105 | G7: =F7*3 -> 15315
B8: Budín de Banana | C8: =F8/E8 -> 2250 | D8: =G8/E8 -> 6750 | E8: ='Budin de Banana'!C29 -> 2 | F8: ='Budin de Banana'!C30 -> 4500 | G8: =F8*3 -> 13500
B9: Budín de Peras | C9: =F9/E9 -> 1975 | D9: =G9/E9 -> 5925 | E9: 2 | F9: ='Budin de Peras'!C30 -> 3950 | G9: =F9*3 -> 11850
B10: Bundt Chololate | C10: =F10/E10 -> 3730 | D10: =G10/E10 -> 11190 | E10: 2 | F10: ='Bundt Chocolate'!C30 -> 7460 | G10: =F10*3 -> 22380
B11: Bundt Naranja | C11: =F11/E11 -> 3930 | D11: =G11/E11 -> 11790 | E11: 1 | F11: ='Bundt Naranja'!C30 -> 3930 | G11: =F11*3 -> 11790
B12: Butter Cream Chocolate | C12: =F12/E12 -> 4400 | D12: =G12/E12 -> 13200 | E12: 1 | F12: ='Butter Cream Chocolate'!C30 -> 4400 | G12: =F12*3 -> 13200
B13: Butter Cream Vainilla | C13: =F13/E13 -> 3312.5 | D13: =G13/E13 -> 9937.5 | E13: 1 | F13: ='Butter Cream Vainilla'!C30 -> 3312.5 | G13: =F13*3 -> 9937.5
B14: Cakepops | C14: =F14/E14 -> 180.90278 | D14: =G14/E14 -> 542.70833 | E14: =Cakepops!D30 -> 36 | F14: =Cakepops!C31 -> 6512.5 | G14: =F14*3 -> 19537.5
B15: Cookies Chocolate | C15: =F15/E15 -> 98.333333 | D15: =G15/E15 -> 295 | E15: ='Cookies Chocochips'!C28 -> 66 | F15: ='Cookies Chocochips'!C29 -> 6490 | G15: =F15*3 -> 19470
B16: Cookies de Pasas Y Nueces | C16: =F16/E16 -> 77.5815 | D16: =G16/E16 -> 232.7445 | E16: ='Cookies Pasas y Nueces'!C29 -> 100 | F16: ='Cookies Pasas y Nueces'!C30 -> 7758.15 | G16: =F16*3 -> 23274.45
B17: Cremoso de Fruta | C17: =F17/E17 -> 396.803 | D17: =G17/E17 -> 1190.409 | E17: ='Cremoso de Fruta'!H4 -> 20 | F17: ='Cremoso de Fruta'!H5 -> 7936.06 | G17: =F17*3 -> 23808.18
B18: Cupcakes Chocolate | C18: =F18/E18 -> 350.25 | D18: =G18/E18 -> 1050.75 | E18: ='Cupcakes Chocolate'!C37 -> 12 | F18: ='Cupcakes Chocolate'!C38 -> 4203 | G18: =F18*3 -> 12609
B19: Cupcakes Limón | C19: =F19/E19 -> 472.33333 | D19: =G19/E19 -> 1417 | E19: ='Cupcakes Limón'!C37 -> 12 | F19: ='Cupcakes Limón'!C38 -> 5668 | G19: =F19*3 -> 17004
B20: Donas de Chocolate | C20: =F20/E20 -> 163.25 | D20: =G20/E20 -> 489.75 | E20: 36 | F20: ='Donas de Chocolate'!C30 -> 5877 | G20: =F20*3 -> 17631
B21: Duo Chocolate | C21: =F21/E21 -> 26124 | D21: =G21/E21 -> 78372 | E21: ='Duo Chocolate'!H4 -> 1 | F21: ='Duo Chocolate'!H5 -> 26124 | G21: =F21*3 -> 78372
B22: Espumita de Limón | C22: =F22/E22 -> 161.85 | D22: =G22/E22 -> 485.55 | E22: ='Espumita de Limon'!C29 -> 30 | F22: ='Espumita de Limon'!C30 -> 4855.5 | G22: =F22*3 -> 14566.5
B23: Frosting Bariloche | C23: =F23/E23 -> 7500 | D23: =G23/E23 -> 22500 | E23: ='Frosting Bariloche'!C29 -> 1 | F23: ='Frosting Bariloche'!C30 -> 7500 | G23: =F23*3 -> 22500
B24: Ganache | C24: =F24/E24 -> #REF! | D24: =G24/E24 -> #REF! | E24: =Ganache!C29 -> 1 | F24: =Ganache!C30 -> #REF! | G24: =F24*3 -> #REF!
B25: Ganache Isabel Vermal | C25: =F25/E25 -> 11270 | D25: =G25/E25 -> 33810 | E25: ='Ganache Isabel Vermal'!C29 -> 1 | F25: ='Ganache Isabel Vermal'!C30 -> 11270 | G25: =F25*3 -> 33810
B26: Genoise | C26: =F26/E26 -> 2150 | D26: =G26/E26 -> 6450 | E26: 1 | F26: =Genoise!C30 -> 2150 | G26: =F26*3 -> 6450
B27: Masitas Manteca (Choc) | C27: =F27/E27 -> 50.29 | D27: =G27/E27 -> 150.87 | E27: ='Masitas de Manteca (choc)'!C29 -> 50 | F27: ='Masitas de Manteca (choc)'!C30 -> 2514.5 | G27: =F27*3 -> 7543.5
B28: Masitas Manteca Vainilla | C28: =F28/E28 -> 95.45 | D28: =G28/E28 -> 286.35 | E28: ='Masitas de Manteca'!C29 -> 40 | F28: ='Masitas de Manteca'!C30 -> 3818 | G28: =F28*3 -> 11454
B29: Alfajores de Nuez | C29: ='Alfajores de Nuez'!C32 -> 209.08333 | D29: =G29/E29 -> 627.25 | E29: ='Alfajores de Nuez'!C29 -> 60 | F29: ='Alfajores de Nuez'!C30 -> 12545 | G29: =F29*3 -> 37635
B30: Number-Letter Tipo Chocolate | C30: =F30/E30 -> 21328.8 | D30: =G30/E30 -> 63986.4 | E30: 1 | F30: =2*F16+F13+'Valores y Totales'!B11/2 -> 21328.8 | G30: =F30*3 -> 63986.4
B31: Number-Letter Tipo Merengue | C31: =F31/E31 -> 18926.3 | D31: =G31/E31 -> 56778.9 | E31: 1 | F31: =2*F16+'Valores y Totales'!B11/2+'Merengue Italiano'!C30 -> 18926.3 | G31: =F31*3 -> 56778.9
B32: Receta Torta Espumita | C32: =F32/E32 -> 3335 | D32: =G32/E32 -> 10005 | E32: 1 | F32: ='Receta Torta Espumita'!C30 -> 3335 | G32: =F32*3 -> 10005
B33: Tartitas de Chocolate | C33: =F33/E33 -> 249.6 | D33: =G33/E33 -> 748.8 | E33: =TartitasChocolate!C29 -> 50 | F33: =TartitasChocolate!C30 -> 12480 | G33: =F33*3 -> 37440
B34: Torta Butter Cream | C34: =F34/E34 -> 15318 | D34: =G34/E34 -> 45954 | E34: 1 | F34: =F26+F22+'Valores y Totales'!B11+Precios!F13 -> 15318 | G34: =F34*3 -> 45954
B35: Torta Choc Isabel Vermal | C35: =F35/E35 -> 7210 | D35: =G35/E35 -> 21630 | E35: ='Torta Choc Isabel Vermal'!C29 -> 1 | F35: ='Torta Choc Isabel Vermal'!C30 -> 7210 | G35: =F35*3 -> 21630
B36: Torta Chocolate | C36: =F36/E36 -> 5885 | D36: =G36/E36 -> 17655 | E36: ='Torta Chocolate'!C29 -> 1 | F36: ='Torta Chocolate'!C30 -> 5885 | G36: =F36*3 -> 17655
B37: Torta Forrada | C37: =F37/E37 -> #REF! | D37: =G37/E37 -> #REF! | E37: 1 | F37: =F26+F32+F24+'Valores y Totales'!B31+'Valores y Totales'!B11+'Valores y Totales'!#REF!/10 -> #REF! | G37: =F37*3 -> #REF!
B38: Torta Galesa | C38: =F38/E38 -> 3205.3778 | D38: =G38/E38 -> 9616.1333 | E38: 3 | F38: ='Torta Galesa'!C30 -> 9616.1333 | G38: =F38*3 -> 28848.4
B39: Torta Ganache Chocolate | C39: =F39/E39 -> 17985 | D39: =G39/E39 -> 53955 | E39: 1 | F39: =F32+F26+F23+'Valores y Totales'!B11 -> 17985 | G39: =F39*3 -> 53955
B40: Torta Vainilla | C40: =F40/E40 -> 3350 | D40: =G40/E40 -> 10050 | E40: ='Torta Vainilla'!C29 -> 1 | F40: ='Torta Vainilla'!C30 -> 3350 | G40: =F40*3 -> 10050
B41: Vaso Geng y Limón | C41: =F41/E41 -> 335.753 | D41: =G41/E41 -> 1007.259 | E41: ='Vaso Geng y Limon'!H4 -> 30 | F41: ='Vaso Geng y Limon'!H5 -> 10072.59 | G41: =F41*3 -> 30217.77
B42: Pasta frola Dulce de Leche | C42: =F42/E42 -> 5305 | D42: =G42/E42 -> 15915 | E42: ='Pastafrola Dulce de Leche'!C29 -> 2 | F42: ='Pastafrola Dulce de Leche'!C30 -> 10610 | G42: =F42*3 -> 31830

Sheet Bombon Nuez con Chocolate
B1: Ingrediente | C1: Gramos | D1: Precio | E1: Total Recetas | F1: Cantidad de Recetas: | G1: 1
B2: Manteca | C2: 0 | D2: =C2*'Valores y Totales'!C2 -> 0 | E2: =G$1*C2 -> 0
B3: Harina 0000 | C3: 0 | D3: =C3*'Valores y Totales'!C3 -> 0 | E3: =G$1*C3 -> 0
B4: Azucar Impalpable | C4: 0 | D4: =C4*'Valores y Totales'!C4 -> 0 | E4: =G$1*C4 -> 0
B5: Cacao | C5: 0 | D5: =C5*'Valores y Totales'!C5 -> 0 | E5: =G$1*C5 -> 0
B6: Huevo (unidad) | C6: 0 | D6: =C6*'Valores y Totales'!B6 -> 0 | E6: =G$1*C6 -> 0
B7: Azucar Común | C7: 0 | D7: =C7*'Valores y Totales'!C7 -> 0 | E7: =G$1*C7 -> 0
B8: Maizena | C8: 0 | D8: =C8*'Valores y Totales'!C8 -> 0 | E8: =G$1*C8 -> 0
B9: Chocolate Taza | C9: 0 | D9: =C9*'Valores y Totales'!C9 -> 0 | E9: =G$1*C9 -> 0
B10: Nueces | C10: 8 | D10: =C10*'Valores y Totales'!C10 -> 176 | E10: =G$1*C10 -> 8
B11: Dulce de Leche | C11: 10 | D11: =C11*'Valores y Totales'!C11 -> 50 | E11: =G$1*C11 -> 10
B12: Crema | C12: 0 | D12: =C12*'Valores y Totales'!C12 -> 0 | E12: =G$1*C12 -> 0
B13: Harina Leudante | C13: 0 | D13: =C13*'Valores y Totales'!C13 -> 0 | E13: =G$1*C13 -> 0
B14: Limon | C14: 0 | D14: =C14*'Valores y Totales'!C14 -> 0 | E14: =G$1*C14 -> 0
B15: Bicarbonato | C15: 0 | D15: =C15*'Valores y Totales'!C15 -> 0 | E15: =G$1*C15 -> 0
B16: Polveo Hornear | C16: 0 | D16: =C16*'Valores y Totales'!C16 -> 0 | E16: =G$1*C16 -> 0
B17: Leche | C17: 0 | D17: =C17*'Valores y Totales'!C17 -> 0 | E17: =G$1*C17 -> 0
B18: Conac | C18: 0 | D18: =C18*'Valores y Totales'!C18 -> 0 | E18: =G$1*C18 -> 0
... B26: Chocochips | C26: 0 | D26: =C26*'Valores y Totales'!C26 -> 0 | E26: =G$1*C26 -> 0
B27: Pera | C27: 0 | D27: =C27*'Valores y Totales'!C36 -> 0
C28: Una Receta | D28: Por Cantidad de Recetas
B29: Cantidad de Masitas | C29: 1 | D29: =C29*G$1 -> 1
B30: Costo Receta | C30: =SUM(D2:D27) -> 326 | D30: =C30*G$1 -> 326
B32: Costo Individual | C32: =SUM(D4:D27) -> 326 | D32: =C32 -> 326

Sheet Cascaritas
B1: Ingrediente | C1: Gramos | D1: Precio | E1: Total Recetas | F1: Cantidad de Recetas: | G1: 1
B2: Manteca | C2: 0 | D2: =C2*'Valores y Totales'!C2 -> 0 | E2: =G$1*C2 -> 0
B3: Harina 0000 | C3: 0 | D3: =C3*'Valores y Totales'!C3 -> 0 | E3: =G$1*C3 -> 0
B4: Azucar Impalpable | C4: 0 | D4: =C4*'Valores y Totales'!C4 -> 0 | E4: =G$1*C4 -> 0
B5: Cacao | C5: 0 | D5: =C5*'Valores y Totales'!C5 -> 0 | E5: =G$1*C5 -> 0
B6: Huevo (unidad) | C6: 0 | D6: =C6*'Valores y Totales'!B6 -> 0 | E6: =G$1*C6 -> 0
B7: Azucar Común | C7: 1000 | D7: =C7*'Valores y Totales'!C7 -> 1400 | E7: =G$1*C7 -> 1000
B8: Maizena | C8: 0 | D8: =C8*'Valores y Totales'!C8 -> 0 | E8: =G$1*C8 -> 0
B9: Chocolate Taza | C9: 0 | D9: =C9*'Valores y Totales'!C9 -> 0 | E9: =G$1*C9 -> 0
B10: Nueces | C10: 0 | D10: =C10*'Valores y Totales'!C10 -> 0 | E10: =G$1*C10 -> 0
B11: Dulce de Leche | C11: 0 | D11: =C11*'Valores y Totales'!C11 -> 0 | E11: =G$1*C11 -> 0
B12: Crema | C12: 0 | D12: =C12*'Valores y Totales'!C12 -> 0 | E12: =G$1*C12 -> 0
B13: Harina Leudante | C13: 0 | D13: =C13*'Valores y Totales'!C13 -> 0 | E13: =G$1*C13 -> 0
B14: Limon | C14: 0 | D14: =C14*'Valores y Totales'!C14 -> 0 | E14: =G$1*C14 -> 0
B15: Bicarbonato | C15: 0 | D15: =C15*'Valores y Totales'!C15 -> 0 | E15: =G$1*C15 -> 0
B16: Polveo Hornear | C16: 0 | D16: =C16*'Valores y Totales'!C16 -> 0 | E16: =G$1*C16 -> 0
B17: Leche | C17: 0 | D17: =C17*'Valores y Totales'!C17 -> 0 | E17: =G$1*C17 -> 0
B18: Conac | C18: 0 | D18: =C18*'Valores y Totales'!C18 -> 0 | E18: =G$1*C18 -> 0
... B26: Chocochips | C26: 0 | D26: =C26*'Valores y Totales'!C26 -> 0 | E26: =G$1*C26 -> 0
B27: Pera | C27: 0 | D27: =C27*'Valores y Totales'!C36 -> 0
C28: Una Receta | D28: Por Cantidad de Recetas
B29: Cantidad de Masitas | C29: 0.5 | D29: =C29*G$1 -> 0.5
B30: Costo Receta | C30: =SUM(D2:D27) -> 6900 | D30: =C30*G$1 -> 6900
B32: Costo Individual | C32: =SUM(D4:D29) -> 6900.5 | D32: =C32 -> 6900.5 | G32: =Cascaritas!D$32 -> 6900.5

Sheet Panes
B1: Ingrediente | C1: Gramos | D1: Precio | E1: Total Recetas | F1: Cantidad de Recetas: | G1: 1
B2: Manteca | C2: 0 | D2: =C2*'Valores y Totales'!C2 -> 0 | E2: =G$1*C2 -> 0
B3: Harina 0000 | C3: 500 | D3: =C3*'Valores y Totales'!C3 -> 550 | E3: =G$1*C3 -> 500
B4: Azucar Impalpable | C4: 0 | D4: =C4*'Valores y Totales'!C4 -> 0 | E4: =G$1*C4 -> 0
B5: Cacao | C5: 0 | D5: =C5*'Valores y Totales'!C5 -> 0 | E5: =G$1*C5 -> 0
B6: Huevo (unidad) | C6: 0 | D6: =C6*'Valores y Totales'!B6 -> 0 | E6: =G$1*C6 -> 0
B7: Azucar Común | C7: 10 | D7: =C7*'Valores y Totales'!C7 -> 14 | E7: =G$1*C7 -> 10
B8: Maizena | C8: 0 | D8: =C8*'Valores y Totales'!C8 -> 0 | E8: =G$1*C8 -> 0
B9: Chocolate Taza | C9: 0 | D9: =C9*'Valores y Totales'!C9 -> 0 | E9: =G$1*C9 -> 0
B10: Nueces | C10: 0 | D10: =C10*'Valores y Totales'!C10 -> 0 | E10: =G$1*C10 -> 0
B11: Dulce de Leche | C11: 0 | D11: =C11*'Valores y Totales'!C11 -> 0 | E11: =G$1*C11 -> 0
B12: Crema | C12: 0 | D12: =C12*'Valores y Totales'!C12 -> 0 | E12: =G$1*C12 -> 0
B13: Harina Leudante | C13: 0 | D13: =C13*'Valores y Totales'!C13 -> 0 | E13: =G$1*C13 -> 0
B14: Limon | C14: 0 | D14: =C14*'Valores y Totales'!C14 -> 0 | E14: =G$1*C14 -> 0
B15: Bicarbonato | C15: 0 | D15: =C15*'Valores y Totales'!C15 -> 0 | E15: =G$1*C15 -> 0
B16: Polveo Hornear | C16: 0 | D16: =C16*'Valores y Totales'!C16 -> 0 | E16: =G$1*C16 -> 0
B17: Leche | C17: 160 | D17: =C17*'Valores y Totales'!C17 -> 400 | E17: =G$1*C17 -> 160
B18: Conac | C18: 0 | D18: =C18*'Valores y Totales'!C18 -> 0 | E18: =G$1*C18 -> 0
... B26: Chocochips | C26: 0 | D26: =C26*'Valores y Totales'!C26 -> 0 | E26: =G$1*C26 -> 0
B27: Aceite | C27: 30 | D27: =C27*'Valores y Totales'!C41 -> 36 | E27: =G$1*C27 -> 30
B28: Levadura | C28: 0.5 | D28: =C28*'Valores y Totales'!C43 -> 12.5 | E28: =G$1*C28 -> 0.5
C29: Una Receta | D29: Por Cantidad de Recetas
B30: Cantidad de Masitas | C30: 1 | D30: =C30*G$1 -> 1
B31: Costo Receta | C31: =SUM(D2:D28) -> 1012.5 | D31: =C31*G$1 -> 1012.5
B33: Costo Individual | C33: =SUM(D2:D28) -> 1012.5 | D33: =C33 -> 1012.5

Sheet Valores y Totales
B1: Precio x Kg | C1: Por Gramo | E1: Totales Recetas | F1: Monto Aprox Recetas | H1: Otros Gastos | I1: Total | J1: Unidad
A2: Manteca | B2: 11000 | C2: =B2/1000 -> 11 | E2: =Brownies!E2+'Masitas de Manteca (choc)'!E2+'Alfajores de Maicena'!E2+'Alfajores de Chocolate'!E2+MiniRogel!E2+'Espumita de Limon'!E2+TartitasChocolate!E2+'Bombones de Chocolate'!E2+Cakepops!E2+'Torta Galesa'!E2 -> 1280 | F2: =E2*C2 -> 14080 | H2: Bandejas Descartables | I2: 120 | M2: Vainilla | N2: 6900 | O2: 250 | P2: =O2/7 -> 35.714286 | Q2: =N2/P2 -> 193.2
A3: Harina 0000 | B3: 1100 | C3: =B3/1000 -> 1.1 | E3: =Brownies!E3+'Masitas de Manteca (choc)'!E3+'Alfajores de Maicena'!E3+'Alfajores de Chocolate'!E3+MiniRogel!E3+'Espumita de Limon'!E3+TartitasChocolate!E3+'Bombones de Chocolate'!E3+Cakepops!E3+'Torta Galesa'!E3 -> 1420 | F3: =E3*C3 -> 1562 | H3: Papel Bombones | I3: 6
A4: Azucar Impalpable | B4: 1500 | C4: =B4/1000 -> 1.5 | E4: =Brownies!E4+'Masitas de Manteca (choc)'!E4+'Alfajores de Maicena'!E4+'Alfajores de Chocolate'!E4+MiniRogel!E4+'Espumita de Limon'!E4+TartitasChocolate!E4+'Bombones de Chocolate'!E4+Cakepops!E4+'Torta Galesa'!E4 -> 415 | F4: =E4*C4 -> 622.5 | H4: Imágenes Comestibles | I4: 170
A5: Cacao | B5: 25000 | C5: =B5/1000 -> 25 | E5: =Brownies!E5+'Masitas de Manteca (choc)'!E5+'Alfajores de Maicena'!E5+'Alfajores de Chocolate'!E5+MiniRogel!E5+'Espumita de Limon'!E5+TartitasChocolate!E5+'Bombones de Chocolate'!E5+Cakepops!E5+'Torta Galesa'!E5 -> 75 | F5: =E5*C5 -> 1875 | H5: Film | I5: 5
A6: Huevo (unidad) | B6: 210 | C6: =B6 -> 210 | E6: =Brownies!E6+'Masitas de Manteca (choc)'!E6+'Alfajores de Maicena'!E6+'Alfajores de Chocolate'!E6+MiniRogel!E6+'Espumita de Limon'!E6+TartitasChocolate!E6+'Bombones de Chocolate'!E6+Cakepops!E6+'Torta Galesa'!E6 -> 25.5 | F6: =E6*C6 -> 5355 | H6: Folex | I6: 5
A7: Azucar Común | B7: 1400 | C7: =B7/1000 -> 1.4 | E7: =Brownies!E7+'Masitas de Manteca (choc)'!E7+'Alfajores de Maicena'!E7+'Alfajores de Chocolate'!E7+MiniRogel!E7+'Espumita de Limon'!E7+TartitasChocolate!E7+'Bombones de Chocolate'!E7+Cakepops!E7+'Torta Galesa'!E7 -> 1100 | F7: =E7*C7 -> 1540 | H7: Carton Vinilos Palitos | I7: 150
A8: Maizena | B8: 2100 | C8: =B8/1000 -> 2.1 | E8: =Brownies!E8+'Masitas de Manteca (choc)'!E8+'Alfajores de Maicena'!E8+'Alfajores de Chocolate'!E8+MiniRogel!E8+'Espumita de Limon'!E8+TartitasChocolate!E8+'Bombones de Chocolate'!E8+Cakepops!E8+'Torta Galesa'!E8 -> 350 | F8: =E8*C8 -> 735 | H8: Pirotines | I8: 40
A9: Chocolate Taza | B9: 26000 | C9: =B9/1000 -> 26 | E9: =Brownies!E9+'Masitas de Manteca (choc)'!E9+'Alfajores de Maicena'!E9+'Alfajores de Chocolate'!E9+MiniRogel!E9+'Espumita de Limon'!E9+TartitasChocolate!E9+'Bombones de Chocolate'!E9+Cakepops!E9+'Torta Galesa'!E9 -> 360 | F9: =E9*C9 -> 9360 | H9: Discos Dorado | I9: 15
A10: Nueces | B10: 22000 | C10: =B10/1000 -> 22 | E10: =Brownies!E10+'Masitas de Manteca (choc)'!E10+'Alfajores de Maicena'!E10+'Alfajores de Chocolate'!E10+MiniRogel!E10+'Espumita de Limon'!E10+TartitasChocolate!E10+'Bombones de Chocolate'!E10+Cakepops!E10+'Torta Galesa'!E10 -> 100 | F10: =E10*C10 -> 2200 | H10: Base Tergopol | I10: 30
A11: Dulce de Leche | B11: 5000 | C11: =B11/1000 -> 5 | E11: =Brownies!E11+'Masitas de Manteca (choc)'!E11+'Alfajores de Maicena'!E11+'Alfajores de Chocolate'!E11+MiniRogel!E11+'Espumita de Limon'!E11+TartitasChocolate!E11+'Bombones de Chocolate'!E11+Cakepops!E11+'Torta Galesa'!E11 -> 3220 | F11: =E11*C11 -> 16100 | H11: Bandeja Brownie Espumita | I11: 600
A12: Crema | B12: 10000 | C12: =B12/1000 -> 10 | E12: =Brownies!E12+'Masitas de Manteca (choc)'!E12+'Alfajores de Maicena'!E12+'Alfajores de Chocolate'!E12+MiniRogel!E12+'Espumita de Limon'!E12+TartitasChocolate!E12+'Bombones de Chocolate'!E12+Cakepops!E12+'Torta Galesa'!E12 -> 0 | F12: =E12*C12 -> 0
A13: Harina Leudante | B13: 2100 | C13: =B13/1000 -> 2.1 | E13: =Brownies!E13+'Masitas de Manteca (choc)'!E13+'Alfajores de Maicena'!E13+'Alfajores de Chocolate'!E13+MiniRogel!E13+'Espumita de Limon'!E13+TartitasChocolate!E13+'Bombones de Chocolate'!E13+Cakepops!E13+'Torta Galesa'!E13 -> 400 | F13: =E13*C13 -> 840
A14: Limon | B14: 500 | C14: =B14 -> 500 | E14: =Brownies!E14+'Masitas de Manteca (choc)'!E14+'Alfajores de Maicena'!E14+'Alfajores de Chocolate'!E14+MiniRogel!E14+'Espumita de Limon'!E14+TartitasChocolate!E14+'Bombones de Chocolate'!E14+Cakepops!E14+'Torta Galesa'!E14 -> 3 | F14: =E14*C14 -> 1500
A15: Bicarbonato | B15: 900 | C15: =B15/1000 -> 0.9 | E15: =Brownies!E15+'Masitas de Manteca (choc)'!E15+'Alfajores de Maicena'!E15+'Alfajores de Chocolate'!E15+MiniRogel!E15+'Espumita de Limon'!E15+TartitasChocolate!E15+'Bombones de Chocolate'!E15+Cakepops!E15+'Torta Galesa'!E15 -> 0 | F15: =E15*C15 -> 0
A16: Polvo Hornear | B16: 4000 | C16: =B16/1000 -> 4 | E16: =Brownies!E16+'Masitas de Manteca (choc)'!E16+'Alfajores de Maicena'!E16+'Alfajores de Chocolate'!E16+MiniRogel!E16+'Espumita de Limon'!E16+TartitasChocolate!E16+'Bombones de Chocolate'!E16+Cakepops!E16+'Torta Galesa'!E16 -> 22 | F16: =E16*C16 -> 88 | I16: 0.75
A17: Leche | B17: 2500 | C17: =B17/1000 -> 2.5 | E17: =Brownies!E17+'Masitas de Manteca (choc)'!E17+'Alfajores de Maicena'!E17+'Alfajores de Chocolate'!E17+MiniRogel!E17+'Espumita de Limon'!E17+TartitasChocolate!E17+'Bombones de Chocolate'!E17+Cakepops!E17+'Torta Galesa'!E17 -> 0 | F17: =E17*C17 -> 0
A18: Conac | B18: 10000 | C18: =B18/750 -> 13.333333 | E18: =Brownies!E18+'Masitas de Manteca (choc)'!E18+'Alfajores de Maicena'!E18+'Alfajores de Chocolate'!E18+MiniRogel!E18+'Espumita de Limon'!E18+TartitasChocolate!E18+'Bombones de Chocolate'!E18+Cakepops!E18+'Torta Galesa'!E18 -> 120 | F18: =E18*C18 -> 1600
A19: Naranja | B19: 500 | C19: =B19 -> 500 | E19: =Brownies!E19+'Masitas de Manteca (choc)'!E19+'Alfajores de Maicena'!E19+'Alfajores de Chocolate'!E19+MiniRogel!E19+'Espumita de Limon'!E19+TartitasChocolate!E19+'Bombones de Chocolate'!E19+Cakepops!E19+'Torta Galesa'!E19 -> 0 | F19: =E19*C19 -> 0 | L19: 290 | M19: 2500
A20: Azucar Negro | B20: 2300 | C20: =B20/1000 -> 2.3 | E20: =Brownies!E20+'Masitas de Manteca (choc)'!E20+'Alfajores de Maicena'!E20+'Alfajores de Chocolate'!E20+MiniRogel!E20+'Espumita de Limon'!E20+TartitasChocolate!E20+'Bombones de Chocolate'!E20+Cakepops!E20+'Torta Galesa'!E20 -> 660 | F20: =E20*C20 -> 1518 | L20: 1000
A21: Chocolate Alfajores | B21: 10000 | C21: =B21/1000 -> 10 | E21: =Brownies!E21+'Masitas de Manteca (choc)'!E21+'Alfajores de Maicena'!E21+'Alfajores de Chocolate'!E21+MiniRogel!E21+'Espumita de Limon'!E21+TartitasChocolate!E21+'Bombones de Chocolate'!E21+Cakepops!E21+'Torta Galesa'!E21 -> 900 | F21: =E21*C21 -> 9000 | H21: Alfajorero y Moldeo
A22: Biscochuelo | B22: 130 | C22: =B22/1000 -> 0.13 | E22: =Brownies!E22+'Masitas de Manteca (choc)'!E22+'Alfajores de Maicena'!E22+'Alfajores de Chocolate'!E22+MiniRogel!E22+'Espumita de Limon'!E22+TartitasChocolate!E22+'Bombones de Chocolate'!E22+Cakepops!E22+'Torta Galesa'!E22 -> 0 | F22: =E22*C22 -> 0
A23: Ciruelas | B23: 6807 | C23: =B23/1000 -> 6.807 | E23: =Brownies!E23+'Masitas de Manteca (choc)'!E23+'Alfajores de Maicena'!E23+'Alfajores de Chocolate'!E23+MiniRogel!E23+'Espumita de Limon'!E23+TartitasChocolate!E23+'Bombones de Chocolate'!E23+Cakepops!E23+'Torta Galesa'!E23 -> 100 | F23: =E23*C23 -> 680.7
A24: Pasas | B24: 4821 | C24: =B24/1000 -> 4.821 | E24: =Brownies!E24+'Masitas de Manteca (choc)'!E24+'Alfajores de Maicena'!E24+'Alfajores de Chocolate'!E24+MiniRogel!E24+'Espumita de Limon'!E24+TartitasChocolate!E24+'Bombones de Chocolate'!E24+Cakepops!E24+'Torta Galesa'!E24 -> 100 | F24: =E24*C24 -> 482.1
A25: Yogur | B25: 1200 | C25: =B25 -> 1200 | E25: =Brownies!E25+'Masitas de Manteca (choc)'!E25+'Alfajores de Maicena'!E25+'Alfajores de Chocolate'!E25+MiniRogel!E25+'Espumita de Limon'!E25+TartitasChocolate!E25+'Bombones de Chocolate'!E25+Cakepops!E25+'Torta Galesa'!E25 -> 0 | F25: =E25*C25 -> 0
A26: Chocochips | B26: 8000 | C26: =B26/1000 -> 8 | E26: =Brownies!E26+'Masitas de Manteca (choc)'!E26+'Alfajores de Maicena'!E26+'Alfajores de Chocolate'!E26+MiniRogel!E26+'Espumita de Limon'!E26+TartitasChocolate!E26+'Bombones de Chocolate'!E26+Cakepops!E26+'Torta Galesa'!E26 -> 90 | F26: =E26*C26 -> 720
A27: Leche Condensada (Unidad) | B27: 170 | C27: =B27 -> 170
A28: Gelatina SS (Unidad) | B28: 6 | C28: =B28 -> 6
A29: Frutos Rojos | B29: 150 | C29: =B29/1000 -> 0.15
A30: Vasitos | B30: 3 | C30: =B30/1000 -> 0.003
A31: Pasta de Forrar | B31: 6000 | C31: =B31/1000 -> 6
A32: Bandeja | B32: 1 | C32: 20
A33: Goma Eva | B33: 1 | C33: 15
A34: Cinta | B34: 1 | C34: 15
A35: Pirotines | B35: 12 | C35: =15/B35 -> 1.25
A36: Peras | B36: 600 | C36: 10 | G36: UNIDAD
A37: Palitos | B37: 5 | C37: 5
A38: Queso Crema | B38: 9000 | C38: =B38/1000 -> 9
A39: Pasta de Goma | B39: 7000 | C39: =B39/1000 -> 7
A40: Mix Europeo | B40: 600 | C40: =B40/1000 -> 0.6
A41: Aceite | B41: 1200 | C41: =B41/1000 -> 1.2
A42: Rocklets | B42: 12500 | C42: =B42/1000 -> 12.5
A43: Levadura | B43: 25 | C43: =B43/1 -> 25 | G43: x Sobre
A44: Coco Rayado | B44: 12000 | C44: =B44/1000 -> 12
A45: Dulce Membrillo | B45: 6000 | C45: =B45/1000 -> 6
A46: Oreo | B46: 4300 | C46: =B46/33 -> 130.30303
A47: Nutella | B47: 860 | C47: =B47/1000 -> 0.86
A48: Esencia de Vainilla | B48: 26520 | C48: =B48/1000 -> 26.52 | D48: =C48/1000 -> 0.02652
A49: Manzana | B49: 600 | C49: =B49 -> 600 | G49: x unidad
A50: Arandanos | B50: 3325 | C50: =B50/1000 -> 3.325 | G50: x kg
A51: Almendras | B51: 9900 | C51: =B51/1000 -> 9.9
A52: Miel | B52: 8000 | C52: =B52/1000 -> 8
A53: Mani | B53: 2600 | C53: =B53/1000 -> 2.6
A54: Pasta de Mani | B54: 6300 | C54: =B54/1000 -> 6.3
A55: Baño Moldeo (pins) | B55: 11667 | C55: 11.667

Sheet Vaso Geng y Limon
B1: Ingrediente | C1: Gramos | D1: Precio | E1: Total Recetas | F1: Cantidad de Recetas: | G1: 1
B2: Manteca | C2: 50 | D2: =C2*'Valores y Totales'!C2 -> 550 | E2: =G$1*C2 -> 50
B3: Harina 0000 | C3: 0 | D3: =C3*'Valores y Totales'!C3 -> 0 | E3: =G$1*C3 -> 0 | H3: Una Receta | I3: Por Cantidad de Recetas
B4: Azucar Impalpable | C4: 0 | D4: =C4*'Valores y Totales'!C4 -> 0 | E4: =G$1*C4 -> 0 | G4: Cantidad de Porciones | H4: 30 | I4: =H4*G$1 -> 30
B5: Cacao | C5: 0 | D5: =C5*'Valores y Totales'!C5 -> 0 | E5: =G$1*C5 -> 0 | G5: Costo Receta | H5: =SUM(D2:D30) -> 10072.59 | I5: =H5*G$1 -> 10072.59
B6: Huevo (unidad) | C6: 3 | D6: =C6*'Valores y Totales'!B6 -> 630 | E6: =G$1*C6 -> 3 | G6: Costo Docena | I6: =H6 -> 0
B7: Azucar Común | C7: 100 | D7: =C7*'Valores y Totales'!C7 -> 140 | E7: =G$1*C7 -> 100 | G7: Costo Individual | H7: =H5/H4 -> 335.753 | I7: =H7 -> 335.753
B8: Maizena | C8: 25 | D8: =C8*'Valores y Totales'!C8 -> 52.5 | E8: =G$1*C8 -> 25
B9: Chocolate Taza | C9: 200 | D9: =C9*'Valores y Totales'!C9 -> 5200 | E9: =G$1*C9 -> 200
B10: Nueces | C10: 0 | D10: =C10*'Valores y Totales'!C10 -> 0 | E10: =G$1*C10 -> 0
B11: Dulce de Leche | C11: 0 | D11: =C11*'Valores y Totales'!C11 -> 0 | E11: =G$1*C11 -> 0
B12: Crema | C12: 100 | D12: =C12*'Valores y Totales'!C12 -> 1000 | E12: =G$1*C12 -> 100
B13: Harina Leudante | C13: 0 | D13: =C13*'Valores y Totales'!C13 -> 0 | E13: =G$1*C13 -> 0
B14: Limon | C14: 5 | D14: =C14*'Valores y Totales'!C14 -> 2500 | E14: =G$1*C14 -> 5
B15: Bicarbonato | C15: 0 | D15: =C15*'Valores y Totales'!C15 -> 0 | E15: =G$1*C15 -> 0
B16: Polveo Hornear | C16: 0 | D16: =C16*'Valores y Totales'!C16 -> 0 | E16: =G$1*C16 -> 0
B17: Leche | C17: 0 | D17: =C17*'Valores y Totales'!C17 -> 0 | E17: =G$1*C17 -> 0
B18: Conac | C18: 0 | D18: =C18*'Valores y Totales'!C18 -> 0 | E18: =G$1*C18 -> 0
B19: Naranja | C19: 0 | D19: =C19*'Valores y Totales'!C19 -> 0 | E19: =G$1*C19 -> 0
... B26: Chocochips | C26: 0 | D26: =C26*'Valores y Totales'!C26 -> 0 | E26: =G$1*C26 -> 0
B27: ='Valores y Totales'!A27 -> Leche Condensada (Unidad) | C27: 0 | D27: =C27*'Valores y Totales'!C27 -> 0 | E27: =G$1*C27 -> 0
B28: ='Valores y Totales'!A28 -> Gelatina SS (Unidad) | C28: 0 | D28: =C28*'Valores y Totales'!C28 -> 0 | E28: =G$1*C28 -> 0
B29: ='Valores y Totales'!A29 -> Frutos Rojos | C29: 0 | D29: =C29*'Valores y Totales'!C29 -> 0 | E29: =G$1*C29 -> 0
B30: ='Valores y Totales'!A30 -> Vasitos | C30: 30 | D30: =C30*'Valores y Totales'!C30 -> 0.09 | E30: =G$1*C30 -> 30

Sheet Cremoso de Fruta
B1: Ingrediente | C1: Gramos | D1: Precio | E1: Total Recetas | F1: Cantidad de Recetas: | G1: 1
B2: Manteca | C2: 0 | D2: =C2*'Valores y Totales'!C2 -> 0 | E2: =G$1*C2 -> 0
B3: Harina 0000 | C3: 0 | D3: =C3*'Valores y Totales'!C3 -> 0 | E3: =G$1*C3 -> 0 | H3: Una Receta | I3: Por Cantidad de Recetas
B4: Azucar Impalpable | C4: 0 | D4: =C4*'Valores y Totales'!C4 -> 0 | E4: =G$1*C4 -> 0 | G4: Cantidad de Porciones | H4: 20 | I4: =H4*G$1 -> 20
B5: Cacao | C5: 0 | D5: =C5*'Valores y Totales'!C5 -> 0 | E5: =G$1*C5 -> 0 | G5: Costo Receta | H5: =SUM(D2:D30) -> 7936.06 | I5: =H5*G$1 -> 7936.06
B6: Huevo (unidad) | C6: 0 | D6: =C6*'Valores y Totales'!B6 -> 0 | E6: =G$1*C6 -> 0 | G6: Costo Docena | I6: =H6 -> 0
B7: Azucar Común | C7: 30 | D7: =C7*'Valores y Totales'!C7 -> 42 | E7: =G$1*C7 -> 30 | G7: Costo Individual | H7: =H5/H4 -> 396.803 | I7: =H7 -> 396.803
B8: Maizena | C8: 0 | D8: =C8*'Valores y Totales'!C8 -> 0 | E8: =G$1*C8 -> 0
B9: Chocolate Taza | C9: 200 | D9: =C9*'Valores y Totales'!C9 -> 5200 | E9: =G$1*C9 -> 200
B10: Nueces | C10: 0 | D10: =C10*'Valores y Totales'!C10 -> 0 | E10: =G$1*C10 -> 0
B11: Dulce de Leche | C11: 0 | D11: =C11*'Valores y Totales'!C11 -> 0 | E11: =G$1*C11 -> 0
B12: Crema | C12: 0 | D12: =C12*'Valores y Totales'!C12 -> 0 | E12: =G$1*C12 -> 0
B13: Harina Leudante | C13: 0 | D13: =C13*'Valores y Totales'!C13 -> 0 | E13: =G$1*C13 -> 0
B14: Limon | C14: 4 | D14: =C14*'Valores y Totales'!C14 -> 2000 | E14: =G$1*C14 -> 4
B15: Bicarbonato | C15: 0 | D15: =C15*'Valores y Totales'!C15 -> 0 | E15: =G$1*C15 -> 0
B16: Polveo Hornear | C16: 0 | D16: =C16*'Valores y Totales'!C16 -> 0 | E16: =G$1*C16 -> 0
B17: Leche | C17: 200 | D17: =C17*'Valores y Totales'!C17 -> 500 | E17: =G$1*C17 -> 200
B18: Conac | C18: 0 | D18: =C18*'Valores y Totales'!C18 -> 0 | E18: =G$1*C18 -> 0
B19: Naranja | C19: 0 | D19: =C19*'Valores y Totales'!C19 -> 0 | E19: =G$1*C19 -> 0
... B26: Chocochips | C26: 0 | D26: =C26*'Valores y Totales'!C26 -> 0 | E26: =G$1*C26 -> 0
B27: ='Valores y Totales'!A27 -> Leche Condensada (Unidad) | C27: 1 | D27: =C27*'Valores y Totales'!C27 -> 170 | E27: =G$1*C27 -> 1
B28: ='Valores y Totales'!A28 -> Gelatina SS (Unidad) | C28: 1.5 | D28: =C28*'Valores y Totales'!C28 -> 9 | E28: =G$1*C28 -> 1.5
B29: ='Valores y Totales'!A29 -> Frutos Rojos | C29: 100 | D29: =C29*'Valores y Totales'!C29 -> 15 | E29: =G$1*C29 -> 100
B30: ='Valores y Totales'!A30 -> Vasitos | C30: 20 | D30: =C30*'Valores y Totales'!C30 -> 0.06 | E30: =G$1*C30 -> 20

Sheet Duo Chocolate
B1: Ingrediente | C1: Gramos | D1: Precio | E1: Total Recetas | F1: Cantidad de Recetas: | G1: 1
B2: Manteca | C2: 0 | D2: =C2*'Valores y Totales'!C2 -> 0 | E2: =G$1*C2 -> 0
B3: Harina 0000 | C3: 0 | D3: =C3*'Valores y Totales'!C3 -> 0 | E3: =G$1*C3 -> 0 | H3: Una Receta | I3: Por Cantidad de Recetas
B4: Azucar Impalpable | C4: 0 | D4: =C4*'Valores y Totales'!C4 -> 0 | E4: =G$1*C4 -> 0 | G4: Cantidad de Porciones | H4: 1 | I4: =H4*G$1 -> 1
B5: Cacao | C5: 0 | D5: =C5*'Valores y Totales'!C5 -> 0 | E5: =G$1*C5 -> 0 | G5: Costo Receta | H5: =SUM(D2:D30) -> 26124 | I5: =H5*G$1 -> 26124
B6: Huevo (unidad) | C6: 10 | D6: =C6*'Valores y Totales'!B6 -> 2100 | E6: =G$1*C6 -> 10 | G6: Costo Docena | I6: =H6 -> 0
B7: Azucar Común | C7: 160 | D7: =C7*'Valores y Totales'!C7 -> 224 | E7: =G$1*C7 -> 160 | G7: Costo Individual | H7: =H5/H4 -> 26124 | I7: =H7 -> 26124
B8: Maizena | C8: 0 | D8: =C8*'Valores y Totales'!C8 -> 0 | E8: =G$1*C8 -> 0
B9: Chocolate Taza | C9: 600 | D9: =C9*'Valores y Totales'!C9 -> 15600 | E9: =G$1*C9 -> 600
B10: Nueces | C10: 0 | D10: =C10*'Valores y Totales'!C10 -> 0 | E10: =G$1*C10 -> 0
B11: Dulce de Leche | C11: 0 | D11: =C11*'Valores y Totales'!C11 -> 0 | E11: =G$1*C11 -> 0
B12: Crema | C12: 720 | D12: =C12*'Valores y Totales'!C12 -> 7200 | E12: =G$1*C12 -> 720
B13: Harina Leudante | C13: 0 | D13: =C13*'Valores y Totales'!C13 -> 0 | E13: =G$1*C13 -> 0
B14: Limon | C14: 0 | D14: =C14*'Valores y Totales'!C14 -> 0 | E14: =G$1*C14 -> 0
B15: Bicarbonato | C15: 0 | D15: =C15*'Valores y Totales'!C15 -> 0 | E15: =G$1*C15 -> 0
B16: Polveo Hornear | C16: 0 | D16: =C16*'Valores y Totales'!C16 -> 0 | E16: =G$1*C16 -> 0
B17: Leche | C17: 400 | D17: =C17*'Valores y Totales'!C17 -> 1000 | E17: =G$1*C17 -> 400
B18: Conac | C18: 0 | D18: =C18*'Valores y Totales'!C18 -> 0 | E18: =G$1*C18 -> 0
B19: Naranja | C19: 0 | D19: =C19*'Valores y Totales'!C19 -> 0 | E19: =G$1*C19 -> 0
... B26: Chocochips | C26: 0 | D26: =C26*'Valores y Totales'!C26 -> 0 | E26: =G$1*C26 -> 0
B27: ='Valores y Totales'!A27 -> Leche Condensada (Unidad) | C27: 0 | D27: =C27*'Valores y Totales'!C27 -> 0 | E27: =G$1*C27 -> 0
B28: ='Valores y Totales'!A28 -> Gelatina SS (Unidad) | C28: 0 | D28: =C28*'Valores y Totales'!C28 -> 0 | E28: =G$1*C28 -> 0

Sheet Budin de Peras
B1: Ingrediente | C1: Gramos | D1: Precio | E1: Total Recetas | F1: Cantidad de Recetas: | G1: 1
B2: Manteca | C2: 150 | D2: =C2*'Valores y Totales'!C2 -> 1650 | E2: =G$1*C2 -> 150
B3: Harina 0000 | C3: 0 | D3: =C3*'Valores y Totales'!C3 -> 0 | E3: =G$1*C3 -> 0
B4: Azucar Impalpable | C4: 0 | D4: =C4*'Valores y Totales'!C4 -> 0 | E4: =G$1*C4 -> 0
B5: Cacao | C5: 0 | D5: =C5*'Valores y Totales'!C5 -> 0 | E5: =G$1*C5 -> 0
B6: Huevo (unidad) | C6: 2 | D6: =C6*'Valores y Totales'!B6 -> 420 | E6: =G$1*C6 -> 2
B7: Azucar Común | C7: 150 | D7: =C7*'Valores y Totales'!C7 -> 210 | E7: =G$1*C7 -> 150
B8: Maizena | C8: 0 | D8: =C8*'Valores y Totales'!C8 -> 0 | E8: =G$1*C8 -> 0
B9: Chocolate Taza | C9: 0 | D9: =C9*'Valores y Totales'!C9 -> 0 | E9: =G$1*C9 -> 0
B10: Nueces | C10: 0 | D10: =C10*'Valores y Totales'!C10 -> 0 | E10: =G$1*C10 -> 0
B11: Dulce de Leche | C11: 0 | D11: =C11*'Valores y Totales'!C11 -> 0 | E11: =G$1*C11 -> 0
B12: Crema | C12: 0 | D12: =C12*'Valores y Totales'!C12 -> 0 | E12: =G$1*C12 -> 0
B13: Harina Leudante | C13: 250 | D13: =C13*'Valores y Totales'!C13 -> 525 | E13: =G$1*C13 -> 250
B14: Limon | C14: 2 | D14: =C14*'Valores y Totales'!C14 -> 1000 | E14: =G$1*C14 -> 2
B15: Bicarbonato | C15: 0 | D15: =C15*'Valores y Totales'!C15 -> 0 | E15: =G$1*C15 -> 0
B16: Polveo Hornear | C16: 0 | D16: =C16*'Valores y Totales'!C16 -> 0 | E16: =G$1*C16 -> 0
B17: Leche | C17: 50 | D17: =C17*'Valores y Totales'!C17 -> 125 | E17: =G$1*C17 -> 50
B18: Conac | C18: 0 | D18: =C18*'Valores y Totales'!C18 -> 0 | E18: =G$1*C18 -> 0
... B26: Chocochips | C26: 0 | D26: =C26*'Valores y Totales'!C26 -> 0 | E26: =G$1*C26 -> 0
B27: Pera | C27: 2 | D27: =C27*'Valores y Totales'!C36 -> 20
C28: Una Receta | D28: Por Cantidad de Recetas
B29: Cantidad de Masitas | C29: 2 | D29: =C29*G$1 -> 2
B30: Costo Receta | C30: =SUM(D2:D27) -> 3950 | D30: =C30*G$1 -> 3950
B32: Costo Individual | C32: =C30/C29 -> 1975 | D32: =C32 -> 1975

Sheet Budin de Banana
B1: Ingrediente | C1: Gramos | D1: Precio | E1: Total Recetas | F1: Cantidad de Recetas: | G1: 1
B2: Aceite | C2: 100 | D2: =C2*'Valores y Totales'!C41 -> 120 | E2: =G$1*C2 -> 100
B3: Harina 0000 | C3: 0 | D3: =C3*'Valores y Totales'!C3 -> 0 | E3: =G$1*C3 -> 0 | H3: Una Receta | I3: Por Cantidad de Recetas
B4: Azucar Impalpable | C4: 0 | D4: =C4*'Valores y Totales'!C4 -> 0 | E4: =G$1*C4 -> 0 | G4: Cantidad de Porciones | H4: 1 | I4: =H4*G$1 -> 1
B5: Cacao | C5: 0 | D5: =C5*'Valores y Totales'!C5 -> 0 | E5: =G$1*C5 -> 0 | G5: Costo Receta | H5: =SUM(D2:D30) -> 9002 | I5: =H5*G$1 -> 9002
B6: Huevo (unidad) | C6: 2 | D6: =C6*'Valores y Totales'!B6 -> 420 | E6: =G$1*C6 -> 2 | G6: Costo Docena | I6: =H6 -> 0
B7: Azucar Común | C7: 200 | D7: =C7*'Valores y Totales'!C7 -> 280 | E7: =G$1*C7 -> 200 | G7: Costo Individual | H7: =H5/H4 -> 9002 | I7: =H7 -> 9002
B8: Maizena | C8: 0 | D8: =C8*'Valores y Totales'!C8 -> 0 | E8: =G$1*C8 -> 0
B9: Chocolate Taza | C9: 0 | D9: =C9*'Valores y Totales'!C9 -> 0 | E9: =G$1*C9 -> 0
B10: Nueces | C10: 0 | D10: =C10*'Valores y Totales'!C10 -> 0 | E10: =G$1*C10 -> 0 | K10: 130 | L10: 1500
B11: Dulce de Leche | D11: =C11*'Valores y Totales'!C11 -> 0 | E11: =G$1*C11 -> 0 | K11: =L11*K10/L10 -> 8.6666667 | L11: 100
B12: Crema | D12: =C12*'Valores y Totales'!C12 -> 0 | E12: =G$1*C12 -> 0
B13: Harina Leudante | C13: 300 | D13: =C13*'Valores y Totales'!C13 -> 630 | E13: =G$1*C13 -> 300
B14: Limon | C14: 0 | D14: =C14*'Valores y Totales'!C14 -> 0 | E14: =G$1*C14 -> 0
B15: Bicarbonato | C15: 0 | D15: =C15*'Valores y Totales'!C15 -> 0 | E15: =G$1*C15 -> 0
B16: Polveo Hornear | C16: 0 | D16: =C16*'Valores y Totales'!C16 -> 0 | E16: =G$1*C16 -> 0
B17: Leche | C17: 100 | D17: =C17*'Valores y Totales'!C17 -> 250 | E17: =G$1*C17 -> 100
B18: Conac | C18: 0 | D18: =C18*'Valores y Totales'!C18 -> 0 | E18: =G$1*C18 -> 0
B19: Banana | C19: 2 | D19: =C19*'Valores y Totales'!C19 -> 1000 | E19: =G$1*C19 -> 2
B20: Azucar Negro | C20: 0 | D20: =C20*'Valores y Totales'!C20 -> 0 | E20: =G$1*C20 -> 0
B21: Chocolate Baño | C21: 100 | D21: =C21*'Valores y Totales'!C21 -> 1000 | E21: =G$1*C21 -> 100
B22: Biscochuelo | C22: 0 | D22: =C22*'Valores y Totales'!C22 -> 0 | E22: =G$1*C22 -> 0
B23: Ciruelas | C23: 0 | D23: =C23*'Valores y Totales'!C23 -> 0 | E23: =G$1*C23 -> 0
B24: Pasas | C24: 0 | D24: =C24*'Valores y Totales'!C24 -> 0 | E24: =G$1*C24 -> 0
... B26: Chocochips | C26: 100 | D26: =C26*'Valores y Totales'!C26 -> 800 | E26: =G$1*C26 -> 100
C28: Una Receta | D28: Por Cantidad de Recetas
B29: Cantidad de Masitas | C29: 2 | D29: =C29*G$1 -> 2 | E29: 500 gm c/u o 18 muff
B30: Costo Receta | C30: =SUM(D2:D27) -> 4500 | D30: =C30*G$1 -> 4500
B32: Costo Individual | C32: =C30/C29 -> 2250 | D32: =C32 -> 2250

Sheet Ganache
B1: Ingrediente | C1: Gramos | D1: Precio | E1: Total Recetas | F1: Cantidad de Recetas: | G1: 1
B2: Manteca | D2: =C2*'Valores y Totales'!C2 -> 0 | E2: =G$1*C2 -> 0
B3: Harina 0000 | D3: =C3*'Valores y Totales'!C3 -> 0 | E3: =G$1*C3 -> 0
B4: Azucar Impalpable | D4: =C4*'Valores y Totales'!C4 -> 0 | E4: =G$1*C4 -> 0
B5: Cacao | D5: =C5*'Valores y Totales'!C5 -> 0 | E5: =G$1*C5 -> 0
B6: Huevo (unidad) | D6: =C6*'Valores y Totales'!B6 -> 0 | E6: =G$1*C6 -> 0
B7: Azucar Común | D7: =C7*'Valores y Totales'!C7 -> 0 | E7: =G$1*C7 -> 0
B8: Maizena | D8: =C8*'Valores y Totales'!C8 -> 0 | E8: =G$1*C8 -> 0
B9: Chocolate Taza | D9: 0 | E9: =G$1*C9 -> 0
B10: Nueces | D10: =C10*'Valores y Totales'!C10 -> 0 | E10: =G$1*C10 -> 0
B11: Dulce de Leche | D11: =C11*'Valores y Totales'!C11 -> 0 | E11: =G$1*C11 -> 0
B12: Crema | C12: 360 | D12: =C12*'Valores y Totales'!C12 -> 3600 | E12: =G$1*C12 -> 360
B13: Harina Leudante | D13: =C13*'Valores y Totales'!C13 -> 0 | E13: =G$1*C13 -> 0
B14: Limon | D14: =C14*'Valores y Totales'!C14 -> 0 | E14: =G$1*C14 -> 0
B15: Bicarbonato | D15: =C15*'Valores y Totales'!C15 -> 0 | E15: =G$1*C15 -> 0
B16: Polveo Hornear | D16: =C16*'Valores y Totales'!C16 -> 0 | E16: =G$1*C16 -> 0
B17: Leche | D17: =C17*'Valores y Totales'!C17 -> 0 | E17: =G$1*C17 -> 0
B18: Conac | D18: =C18*'Valores y Totales'!C18 -> 0 | E18: =G$1*C18 -> 0
B19: Naranja | D19: =C19*'Valores y Totales'!C19 -> 0 | E19: =G$1*C19 -> 0
B20: Azucar Negro | D20: =C20*'Valores y Totales'!C20 -> 0 | E20: =G$1*C20 -> 0
B21: Chocolate Ganache | C21: 1000 | D21: =C21*'Valores y Totales'!#REF! -> #REF! | E21: =G$1*C21 -> 1000
B22: Biscochuelo | D22: =C22*'Valores y Totales'!C22 -> 0 | E22: =G$1*C22 -> 0
B23: Ciruelas | C23: 0 | D23: =C23*'Valores y Totales'!C23 -> 0 | E23: =G$1*C23 -> 0
B24: Pasas | C24: 0 | D24: 0 | E24: =G$1*C24 -> 0
B25: Yogur | C25: 0 | D25: 0 | E25: =G$1*C25 -> 0
B26: Chocochips | C26: 0 | D26: 0 | E26: =G$1*C26 -> 0
C28: Una Receta | D28: Por Cantidad de Recetas
B29: Cantidad de Porciones | C29: 1 | D29: 1
B30: Costo Receta | C30: =SUM(D2:D22) -> #REF! | D30: =C30*G$1 -> #REF!
B31: Costo Docena | C31: 0 | D31: =C31 -> 0
B32: Costo Individual | C32: =C30/C29 -> #REF! | D32: =C32 -> #REF!

Sheet Cakepops
B1: Ingrediente | C1: Gramos | D1: Precio | E1: Total Recetas | F1: Cantidad de Recetas: | G1: 1
B2: Manteca | C2: 125 | D2: =C2*'Valores y Totales'!C2 -> 1375 | E2: =G$1*C2 -> 125
B3: Harina 0000 | C3: 125 | D3: =C3*'Valores y Totales'!C3 -> 137.5 | E3: =G$1*C3 -> 125
B4: Azucar Impalpable | D4: =C4*'Valores y Totales'!C4 -> 0 | E4: =G$1*C4 -> 0
B5: Cacao | D5: =C5*'Valores y Totales'!C5 -> 0 | E5: =G$1*C5 -> 0
B6: Huevo (unidad) | C6: 2.5 | D6: =C6*'Valores y Totales'!B6 -> 525 | E6: =G$1*C6 -> 2.5
B7: Azucar Común | C7: 125 | D7: =C7*'Valores y Totales'!C7 -> 175 | E7: =G$1*C7 -> 125
B8: Maizena | D8: =C8*'Valores y Totales'!C8 -> 0 | E8: =G$1*C8 -> 0
B9: Chocolate Taza | D9: 0 | E9: =G$1*C9 -> 0
B10: Nueces | D10: =C10*'Valores y Totales'!C10 -> 0 | E10: =G$1*C10 -> 0
B11: Dulce de Leche | C11: 220 | D11: =C11*'Valores y Totales'!C11 -> 1100 | E11: =G$1*C11 -> 220
B12: Crema | D12: =C12*'Valores y Totales'!C12 -> 0 | E12: =G$1*C12 -> 0
B13: Harina Leudante | D13: =C13*'Valores y Totales'!C13 -> 0 | E13: =G$1*C13 -> 0
B14: Limon | D14: =C14*'Valores y Totales'!C14 -> 0 | E14: =G$1*C14 -> 0
B15: Bicarbonato | D15: =C15*'Valores y Totales'!C15 -> 0 | E15: =G$1*C15 -> 0
B16: Polveo Hornear | C16: 5 | D16: =C16*'Valores y Totales'!C16 -> 20 | E16: =G$1*C16 -> 5
B17: Leche | D17: =C17*'Valores y Totales'!C17 -> 0 | E17: =G$1*C17 -> 0
B18: Conac | D18: =C18*'Valores y Totales'!C18 -> 0 | E18: =G$1*C18 -> 0
B19: Naranja | D19: =C19*'Valores y Totales'!C19 -> 0 | E19: =G$1*C19 -> 0
B20: Azucar Negro | D20: =C20*'Valores y Totales'!C20 -> 0 | E20: =G$1*C20 -> 0
B21: Chocolate Baño | C21: 300 | D21: =C21*'Valores y Totales'!C21 -> 3000 | E21: =G$1*C21 -> 300
B22: Biscochuelo | C22: 0 | D22: =C22*'Valores y Totales'!C22 -> 0 | E22: =G$1*C22 -> 0
B23: Ciruelas | C23: 0 | D23: =C23*'Valores y Totales'!C23 -> 0 | E23: =G$1*C23 -> 0
B24: Pasas | C24: 0 | D24: 0 | E24: =G$1*C24 -> 0
B25: Yogur | C25: 0 | D25: 0 | E25: =G$1*C25 -> 0
B26: Chocochips | C26: 0 | D26: 0 | E26: =G$1*C26 -> 0
B27: Ganache | C27: 0 | D27: =Precios!F26/1300*C27 -> 0
B28: Palitos | C28: 36 | D28: =C28*'Valores y Totales'!B37 -> 180
C29: Una Receta | D29: Por Cantidad de Recetas
B30: Cantidad de Porciones | C30: 36 | D30: =C30*G$1 -> 36 | E30: 20 gramos x cackepop
B31: Costo Receta | C31: =SUM(D2:D28) -> 6512.5 | D31: =C31*G$1 -> 6512.5
B32: Costo Docena | C32: =C31/C30*12 -> 2170.8333 | D32: =C32 -> 2170.8333
B33: Costo Individual | C33: =C31/C30 -> 180.90278 | D33: =C33 -> 180.90278

Sheet Bombones de Chocolate
B1: Ingrediente | C1: Gramos | D1: Precio | E1: Total Recetas | F1: Cantidad de Recetas: | G1: 2
B2: Manteca | C2: 0 | D2: =C2*'Valores y Totales'!C2 -> 0 | E2: =G$1*C2 -> 0
B3: Harina 0000 | C3: 0 | D3: =C3*'Valores y Totales'!C3 -> 0 | E3: =G$1*C3 -> 0
B4: Azucar Impalpable | C4: 0 | D4: =C4*'Valores y Totales'!C4 -> 0 | E4: =G$1*C4 -> 0
B5: Cacao | C5: 0 | D5: =C5*'Valores y Totales'!C5 -> 0 | E5: =G$1*C5 -> 0
B6: Huevo (unidad) | C6: 0 | D6: =C6*'Valores y Totales'!B6 -> 0 | E6: =G$1*C6 -> 0
B7: Azucar Común | C7: 0 | D7: =C7*'Valores y Totales'!C7 -> 0 | E7: =G$1*C7 -> 0
B8: Maizena | C8: 0 | D8: =C8*'Valores y Totales'!C8 -> 0 | E8: =G$1*C8 -> 0
B9: Chocolate Taza | C9: 0 | D9: 0 | E9: 0
B10: Nueces | C10: 0 | D10: =C10*'Valores y Totales'!C10 -> 0 | E10: =G$1*C10 -> 0
B11: Dulce de Leche | C11: 0 | D11: =C11*'Valores y Totales'!C11 -> 0 | E11: =G$1*C11 -> 0
B12: Crema | C12: 0 | D12: =C12*'Valores y Totales'!C12 -> 0 | E12: =G$1*C12 -> 0
B13: Harina Leudante | C13: 0 | D13: =C13*'Valores y Totales'!C13 -> 0 | E13: =G$1*C13 -> 0
B14: Limon | C14: 0 | D14: =C14*'Valores y Totales'!C14 -> 0 | E14: =G$1*C14 -> 0
B15: Bicarbonato | C15: 0 | D15: =C15*'Valores y Totales'!C15 -> 0 | E15: =G$1*C15 -> 0
B16: Polveo Hornear | C16: 0 | D16: =C16*'Valores y Totales'!C16 -> 0 | E16: =G$1*C16 -> 0
B17: Leche | C17: 0 | D17: =C17*'Valores y Totales'!C17 -> 0 | E17: =G$1*C17 -> 0
B18: Conac | C18: 0 | D18: =C18*'Valores y Totales'!C18 -> 0 | E18: =G$1*C18 -> 0
B19: Naranja | C19: 0 | D19: =C19*'Valores y Totales'!C19 -> 0 | E19: =G$1*C19 -> 0
B20: Azucar Negro | C20: 0 | D20: =C20*'Valores y Totales'!C20 -> 0 | E20: =G$1*C20 -> 0
B21: Chocolate Baño | C21: 0 | D21: =C21*'Valores y Totales'!C21 -> 0 | E21: =G$1*C21 -> 0
... B26: Chocochips | C26: 0 | D26: =C26*'Valores y Totales'!C26 -> 0 | E26: =G$1*C26 -> 0
C28: Una Receta | D28: Por Cantidad de Recetas
B29: Cantidad de Porciones | C29: 70 | D29: =C29*G$1 -> 140
B30: Costo Receta | C30: =SUM(D2:D21) -> 0 | D30: =C30*G$1 -> 0
B31: Costo Docena | C31: =C30/C29*12 -> 0 | D31: =C31 -> 0
B32: Costo Individual | C32: =C30/C29 -> 0 | D32: =C32 -> 0

Sheet TartitasChocolate
B1: Ingrediente | C1: Gramos | D1: Precio | E1: Total Recetas | F1: Cantidad de Recetas: | G1: 0
B2: Manteca | C2: 125 | D2: =C2*'Valores y Totales'!C2 -> 1375 | E2: =G$1*C2 -> 0
B3: Harina 0000 | C3: 250 | D3: =C3*'Valores y Totales'!C3 -> 275 | E3: =G$1*C3 -> 0
B4: Azucar Impalpable | C4: 125 | D4: =C4*'Valores y Totales'!C4 -> 187.5 | E4: =G$1*C4 -> 0
B5: Cacao | C5: 10 | D5: =C5*'Valores y Totales'!C5 -> 250 | E5: =G$1*C5 -> 0
B6: Huevo (unidad) | C6: 3 | D6: =C6*'Valores y Totales'!B6 -> 630 | E6: =G$1*C6 -> 0
B7: Azucar Común | C7: 0 | D7: =C7*'Valores y Totales'!C7 -> 0 | E7: =G$1*C7 -> 0
B8: Maizena | C8: 0 | D8: =C8*'Valores y Totales'!C8 -> 0 | E8: =G$1*C8 -> 0
B9: Chocolate Taza | C9: 200 | D9: =C9*'Valores y Totales'!C9 -> 5200 | E9: =G$1*C9 -> 0
B10: Nueces | C10: 0 | D10: =C10*'Valores y Totales'!C10 -> 0 | E10: =G$1*C10 -> 0
B11: Dulce de Leche | C11: 0 | D11: =C11*'Valores y Totales'!C11 -> 0 | E11: =G$1*C11 -> 0
B12: Crema | C12: 375 | D12: =C12*'Valores y Totales'!C12 -> 3750 | E12: =G$1*C12 -> 0
B13: Harina Leudante | C13: 0 | D13: =C13*'Valores y Totales'!C13 -> 0 | E13: =G$1*C13 -> 0
B14: Limon | C14: 0 | D14: =C14*'Valores y Totales'!C14 -> 0 | E14: =G$1*C14 -> 0
B15: Bicarbonato | C15: 0 | D15: =C15*'Valores y Totales'!C15 -> 0 | E15: =G$1*C15 -> 0
B16: Polveo Hornear | C16: 0 | D16: =C16*'Valores y Totales'!C16 -> 0 | E16: =G$1*C16 -> 0
B17: Leche | C17: 125 | D17: =C17*'Valores y Totales'!C17 -> 312.5 | E17: =G$1*C17 -> 0
B18: Conac | C18: 0 | D18: =C18*'Valores y Totales'!C18 -> 0 | E18: =G$1*C18 -> 0
... B21: Chocolate Baño | C21: 0 | D21: =C21*'Valores y Totales'!C21 -> 0 | E21: =G$1*C21 -> 0
B22: Biscochuelo | C22: 0 | D22: 0
B23: Ciruelas | C23: 0 | D23: 0
B24: Pasas | C24: 0 | D24: 0
B25: Yogur | C25: 0 | D25: 0
B26: Chocochips | C26: 0 | D26: 0
C28: Una Receta | D28: Por Cantidad de Recetas
B29: Cantidad de Masitas | C29: 50 | D29: =C29*G$1 -> 0
B30: Costo Receta | C30: =SUM(D2:D21) -> 12480 | D30: =C30*G$1 -> 0
B31: Costo Docena | C31: =C30/C29*12 -> 2995.2 | D31: =C31 -> 2995.2
B32: Costo Individual | C32: =C30/C29 -> 249.6 | D32: =C32 -> 249.6

Sheet Espumita de Limon
B1: Ingrediente | C1: Gramos | D1: Precio | E1: Total Recetas | F1: Cantidad de Recetas: | G1: 1
B2: Manteca | C2: 130 | D2: =C2*'Valores y Totales'!C2 -> 1430 | E2: =G$1*C2 -> 130
B3: Harina 0000 | C3: 175 | D3: =C3*'Valores y Totales'!C3 -> 192.5 | E3: =G$1*C3 -> 175
B4: Azucar Impalpable | C4: 300 | D4: =C4*'Valores y Totales'!C4 -> 450 | E4: =G$1*C4 -> 300
B5: Cacao | C5: 0 | D5: =C5*'Valores y Totales'!C5 -> 0 | E5: =G$1*C5 -> 0
B6: Huevo (unidad) | C6: 3 | D6: =C6*'Valores y Totales'!B6 -> 630 | E6: =G$1*C6 -> 3
B7: Azucar Común | C7: 225 | D7: =C7*'Valores y Totales'!C7 -> 315 | E7: =G$1*C7 -> 225
B8: Maizena | C8: 0 | D8: =C8*'Valores y Totales'!C8 -> 0 | E8: =G$1*C8 -> 0
B9: Chocolate Taza | C9: 0 | D9: =C9*'Valores y Totales'!C9 -> 0 | E9: =G$1*C9 -> 0
B10: Nueces | C10: 0 | D10: =C10*'Valores y Totales'!C10 -> 0 | E10: =G$1*C10 -> 0
B11: Dulce de Leche | C11: 0 | D11: =C11*'Valores y Totales'!C11 -> 0 | E11: =G$1*C11 -> 0
B12: Crema | C12: 0 | D12: =C12*'Valores y Totales'!C12 -> 0 | E12: =G$1*C12 -> 0
B13: Harina Leudante | C13: 0 | D13: =C13*'Valores y Totales'!C13 -> 0 | E13: =G$1*C13 -> 0
B14: Limon | C14: 2 | D14: =C14*'Valores y Totales'!C14 -> 1000 | E14: =G$1*C14 -> 2
B15: Bicarbonato | C15: 0 | D15: =C15*'Valores y Totales'!C15 -> 0 | E15: =G$1*C15 -> 0
B16: Polveo Hornear | C16: 7 | D16: =C16*'Valores y Totales'!C16 -> 28 | E16: =G$1*C16 -> 7
B17: Leche | C17: 0 | D17: =C17*'Valores y Totales'!C17 -> 0 | E17: =G$1*C17 -> 0
B18: Conac | C18: 0 | D18: =C18*'Valores y Totales'!C18 -> 0 | E18: =G$1*C18 -> 0
... B25: Yogur | C25: 0 | D25: =C25*'Valores y Totales'!C25 -> 0 | E25: =G$1*C25 -> 0
B26: Queso Crema | C26: 90 | D26: =C26*'Valores y Totales'!C38 -> 810 | E26: =G$1*C26 -> 90
C28: Una Receta | D28: Por Cantidad de Recetas
B29: Cantidad de Masitas | C29: 30 | D29: =C29*G$1 -> 30
B30: Costo Receta | C30: =SUM(D2:D26) -> 4855.5 | D30: =C30*G$1 -> 4855.5
B31: Costo Docena | C31: =C30/C29*12 -> 1942.2 | D31: =C31 -> 1942.2
B32: Costo Individual | C32: =C30/C29 -> 161.85 | D32: =C32 -> 161.85

Sheet Budin de Arandanos
B1: Ingrediente | C1: Gramos | D1: Precio | E1: Total Recetas | F1: Cantidad de Recetas: | G1: 1
B2: Manteca | C2: 120 | D2: =C2*'Valores y Totales'!C2 -> 1320 | E2: =G$1*C2 -> 120
B3: Harina 0000 | C3: 0 | D3: =C3*'Valores y Totales'!C3 -> 0 | E3: =G$1*C3 -> 0
B4: Azucar Impalpable | C4: 270 | D4: =C4*'Valores y Totales'!C4 -> 405 | E4: =G$1*C4 -> 270
B5: Cacao | C5: 0 | D5: =C5*'Valores y Totales'!C5 -> 0 | E5: =G$1*C5 -> 0
B6: Huevo (unidad) | C6: 2 | D6: =C6*'Valores y Totales'!B6 -> 420 | E6: =G$1*C6 -> 2
B7: Azucar Común | C7: 0 | D7: =C7*'Valores y Totales'!C7 -> 0 | E7: =G$1*C7 -> 0
B8: Maizena | C8: 0 | D8: =C8*'Valores y Totales'!C8 -> 0 | E8: =G$1*C8 -> 0
B9: Chocolate Taza | C9: 0 | D9: =C9*'Valores y Totales'!C9 -> 0 | E9: =G$1*C9 -> 0
B10: Nueces | C10: 0 | D10: =C10*'Valores y Totales'!C10 -> 0 | E10: =G$1*C10 -> 0
B11: Dulce de Leche | C11: 0 | D11: =C11*'Valores y Totales'!C11 -> 0 | E11: =G$1*C11 -> 0
B12: Crema | C12: 0 | D12: =C12*'Valores y Totales'!C12 -> 0 | E12: =G$1*C12 -> 0
B13: Harina Leudante | C13: 130 | D13: =C13*'Valores y Totales'!C13 -> 273 | E13: =G$1*C13 -> 130
B14: Limon | C14: 1 | D14: =C14*'Valores y Totales'!C14 -> 500 | E14: =G$1*C14 -> 1
B15: Bicarbonato | C15: 0 | D15: =C15*'Valores y Totales'!C15 -> 0 | E15: =G$1*C15 -> 0
B16: Polveo Hornear | C16: 0 | D16: =C16*'Valores y Totales'!C16 -> 0 | E16: =G$1*C16 -> 0
B17: Leche | C17: 0 | D17: =C17*'Valores y Totales'!C17 -> 0 | E17: =G$1*C17 -> 0
B18: Conac | C18: 0 | D18: =C18*'Valores y Totales'!C18 -> 0 | E18: =G$1*C18 -> 0
... B24: Pasas | C24: 0 | D24: =C24*'Valores y Totales'!C24 -> 0 | E24: =G$1*C24 -> 0
B25: Mix Europero | C25: 0 | D25: ='Valores y Totales'!C40*C25 -> 0 | E25: =G$1*C25 -> 0
B26: Chocochips | C26: 0 | D26: =C26*'Valores y Totales'!C26 -> 0 | E26: =G$1*C26 -> 0
B27: Arandanos | C27: 100 | D27: =C27*'Valores y Totales'!C50 -> 332.5 | E27: =G$1*C27 -> 100
C28: Una Receta | D28: Por Cantidad de Recetas
B29: Cantidad de Porciones | C29: 1 | D29: 1
B30: Costo Receta | C30: =SUM(D2:D27) -> 3250.5 | D30: =C30*G$1 -> 3250.5
B31: Costo Docena | C31: 0 | D31: =C31 -> 0
B32: Costo Individual | C32: =C30/C29 -> 3250.5 | D32: =C32 -> 3250.5

Sheet Torta Galesa
B1: Ingrediente | C1: Gramos | D1: Precio | E1: Total Recetas | F1: Cantidad de Recetas: | G1: 1
B2: Manteca | C2: 200 | D2: =C2*'Valores y Totales'!C2 -> 2200 | E2: =G$1*C2 -> 200
B3: Harina 0000 | C3: 0 | D3: =C3*'Valores y Totales'!C3 -> 0 | E3: =G$1*C3 -> 0
B4: Azucar Impalpable | C4: 0 | D4: =C4*'Valores y Totales'!C4 -> 0 | E4: =G$1*C4 -> 0
B5: Cacao | C5: 0 | D5: =C5*'Valores y Totales'!C5 -> 0 | E5: =G$1*C5 -> 0
B6: Huevo (unidad) | C6: 2 | D6: =C6*'Valores y Totales'!B6 -> 420 | E6: =G$1*C6 -> 2
B7: Azucar Común | C7: 0 | D7: =C7*'Valores y Totales'!C7 -> 0 | E7: =G$1*C7 -> 0
B8: Maizena | C8: 0 | D8: =C8*'Valores y Totales'!C8 -> 0 | E8: =G$1*C8 -> 0
B9: Chocolate Taza | C9: 0 | D9: =C9*'Valores y Totales'!C9 -> 0 | E9: =G$1*C9 -> 0
B10: Nueces | C10: 100 | D10: =C10*'Valores y Totales'!C10 -> 2200 | E10: =G$1*C10 -> 100
B11: Dulce de Leche | C11: 0 | D11: =C11*'Valores y Totales'!C11 -> 0 | E11: =G$1*C11 -> 0
B12: Crema | C12: 0 | D12: =C12*'Valores y Totales'!C12 -> 0 | E12: =G$1*C12 -> 0
B13: Harina Leudante | C13: 400 | D13: =C13*'Valores y Totales'!C13 -> 840 | E13: =G$1*C13 -> 400
B14: Limon | C14: 0 | D14: =C14*'Valores y Totales'!C14 -> 0 | E14: =G$1*C14 -> 0
B15: Bicarbonato | C15: 0 | D15: =C15*'Valores y Totales'!C15 -> 0 | E15: =G$1*C15 -> 0
B16: Polveo Hornear | C16: 0 | D16: =C16*'Valores y Totales'!C16 -> 0 | E16: =G$1*C16 -> 0
B17: Leche | C17: 0 | D17: =C17*'Valores y Totales'!C17 -> 0 | E17: =G$1*C17 -> 0
B18: Conac | C18: 100 | D18: =C18*'Valores y Totales'!C18 -> 1333.3333 | E18: =G$1*C18 -> 100
... B24: Pasas | C24: 100 | D24: =C24*'Valores y Totales'!C24 -> 482.1 | E24: =G$1*C24 -> 100
B25: Mix Europero | C25: 0 | D25: ='Valores y Totales'!C40*C25 -> 0 | E25: =G$1*C25 -> 0
B26: Chocochips | C26: 0 | D26: =C26*'Valores y Totales'!C26 -> 0 | E26: =G$1*C26 -> 0
C28: Una Receta | D28: Por Cantidad de Recetas
B29: Cantidad de Porciones | C29: 2 | D29: =C29*G$1 -> 2
B30: Costo Receta | C30: =SUM(D2:D27) -> 9616.1333 | D30: =C30*G$1 -> 9616.1333
B31: Costo Docena | C31: 0 | D31: =C31 -> 0
B32: Costo Individual | C32: =C30/C29 -> 4808.0667 | D32: =C32 -> 4808.0667

Sheet MiniRogel
B1: Ingrediente | C1: Gramos | D1: Precio | E1: Total Recetas | F1: Cantidad de Recetas: | G1: 1
B2: Manteca | C2: 60 | D2: =C2*'Valores y Totales'!C2 -> 660 | E2: =G$1*C2 -> 60
B3: Harina 0000 | C3: 300 | D3: =C3*'Valores y Totales'!C3 -> 330 | E3: =G$1*C3 -> 300
B4: Azucar Impalpable | C4: 0 | D4: =C4*'Valores y Totales'!C4 -> 0 | E4: =G$1*C4 -> 0
B5: Cacao | C5: 0 | D5: =C5*'Valores y Totales'!C5 -> 0 | E5: =G$1*C5 -> 0
B6: Huevo (unidad) | C6: 6 | D6: =C6*'Valores y Totales'!B6 -> 1260 | E6: =G$1*C6 -> 6
B7: Azucar Común | C7: 300 | D7: =C7*'Valores y Totales'!C7 -> 420 | E7: =G$1*C7 -> 300
B8: Maizena | C8: 0 | D8: =C8*'Valores y Totales'!C8 -> 0 | E8: =G$1*C8 -> 0
B9: Chocolate Taza | C9: 0 | D9: =C9*'Valores y Totales'!C9 -> 0 | E9: =G$1*C9 -> 0
B10: Nueces | C10: 0 | D10: =C10*'Valores y Totales'!C10 -> 0 | E10: =G$1*C10 -> 0
B11: Dulce de Leche | C11: 1000 | D11: =C11*'Valores y Totales'!C11 -> 5000 | E11: =G$1*C11 -> 1000
B12: Crema | C12: 0 | D12: =C12*'Valores y Totales'!C12 -> 0 | E12: =G$1*C12 -> 0
B13: Harina Leudante | C13: 0 | D13: =C13*'Valores y Totales'!C13 -> 0 | E13: =G$1*C13 -> 0
B14: Limon | C14: 0 | D14: =C14*'Valores y Totales'!C14 -> 0 | E14: =G$1*C14 -> 0
B15: Bicarbonato | C15: 0 | D15: =C15*'Valores y Totales'!C15 -> 0 | E15: =G$1*C15 -> 0
B16: Polveo Hornear | C16: 0 | D16: =C16*'Valores y Totales'!C16 -> 0 | E16: =G$1*C16 -> 0
B17: Leche | C17: 0 | D17: =C17*'Valores y Totales'!C17 -> 0 | E17: =G$1*C17 -> 0
B18: Conac | C18: 0 | D18: =C18*'Valores y Totales'!C18 -> 0 | E18: =G$1*C18 -> 0
... B26: Chocochips | C26: 0 | D26: =C26*'Valores y Totales'!C26 -> 0 | E26: =G$1*C26 -> 0
C28: Una Receta | D28: Por Cantidad de Recetas
B29: Cantidad de Alfajores | C29: 80 | D29: =C29*G$1 -> 80
B30: Costo Receta | C30: =SUM(D2:D20) -> 7670 | D30: =C30*G$1 -> 7670
B31: Costo Docena | C31: =C30/C29*12 -> 1150.5 | D31: =C31 -> 1150.5
B32: Costo Individual | C32: =C30/C29 -> 95.875 | D32: =C32 -> 95.875

Sheet Alfajores de Chocolate
B1: Ingrediente | C1: Gramos | D1: Precio | E1: Total Recetas | F1: Cantidad de Recetas: | G1: 1
B2: Manteca | C2: 150 | D2: =C2*'Valores y Totales'!C2 -> 1650 | E2: =G$1*C2 -> 150
B3: Harina 0000 | C3: 200 | D3: =C3*'Valores y Totales'!C3 -> 220 | E3: =G$1*C3 -> 200
B4: Azucar Impalpable | C4: 0 | D4: =C4*'Valores y Totales'!C4 -> 0 | E4: =G$1*C4 -> 0
B5: Cacao | C5: 50 | D5: =C5*'Valores y Totales'!C5 -> 1250 | E5: =G$1*C5 -> 50
B6: Huevo (unidad) | C6: 3 | D6: =C6*'Valores y Totales'!B6 -> 630 | E6: =G$1*C6 -> 3
B7: Azucar Común | C7: 0 | D7: =C7*'Valores y Totales'!C7 -> 0 | E7: =G$1*C7 -> 0
B8: Maizena | C8: 50 | D8: =C8*'Valores y Totales'!C8 -> 105 | E8: =G$1*C8 -> 50
B9: Chocolate Taza | C9: 0 | D9: =C9*'Valores y Totales'!C9 -> 0 | E9: =G$1*C9 -> 0
B10: Nueces | C10: 0 | D10: =C10*'Valores y Totales'!C10 -> 0 | E10: =G$1*C10 -> 0
B11: Dulce de Leche | C11: 1000 | D11: =C11*'Valores y Totales'!C11 -> 5000 | E11: =G$1*C11 -> 1000
B12: Crema | C12: 0 | D12: =C12*'Valores y Totales'!C12 -> 0 | E12: =G$1*C12 -> 0
B13: Harina Leudante | C13: 0 | D13: =C13*'Valores y Totales'!C13 -> 0 | E13: =G$1*C13 -> 0
B14: Limon | C14: 0 | D14: =C14*'Valores y Totales'!C14 -> 0 | E14: =G$1*C14 -> 0
B15: Bicarbonato | C15: 0 | D15: =C15*'Valores y Totales'!C15 -> 0 | E15: =G$1*C15 -> 0
B16: Polveo Hornear | C16: 0 | D16: =C16*'Valores y Totales'!C16 -> 0 | E16: =G$1*C16 -> 0
B17: Leche | C17: 0 | D17: =C17*'Valores y Totales'!C17 -> 0 | E17: =G$1*C17 -> 0
B18: Conac | C18: 0 | D18: =C18*'Valores y Totales'!C18 -> 0 | E18: =G$1*C18 -> 0
... B26: Chocochips | C26: 0 | D26: =C26*'Valores y Totales'!C26 -> 0 | E26: =G$1*C26 -> 0
C28: Una Receta | D28: Por Cantidad de Recetas
B29: Cantidad de Alfajores | C29: 80 | D29: =C29*G$1 -> 80 | E29: 3cm
B30: Costo Receta | C30: =SUM(D2:D26) -> 14085 | D30: =C30*G$1 -> 14085
B31: Costo Docena | C31: =C30/C29*12 -> 2112.75 | D31: =C31 -> 2112.75
B32: Costo Individual | C32: =C30/C29 -> 176.0625 | D32: =C32 -> 176.0625

Sheet Alfajores de Maicena
B1: Ingrediente | C1: Gramos | D1: Precio | E1: Total Recetas | F1: Cantidad de Recetas: | G1: 1
B2: Manteca | C2: 200 | D2: =C2*'Valores y Totales'!C2 -> 2200 | E2: =G$1*C2 -> 200
B3: Harina 0000 | C3: 200 | D3: =C3*'Valores y Totales'!C3 -> 220 | E3: =G$1*C3 -> 200
B4: Azucar Impalpable | C4: 0 | D4: =C4*'Valores y Totales'!C4 -> 0 | E4: =G$1*C4 -> 0
B5: Cacao | C5: 0 | D5: =C5*'Valores y Totales'!C5 -> 0 | E5: =G$1*C5 -> 0
B6: Huevo (unidad) | C6: 2 | D6: =C6*'Valores y Totales'!B6 -> 420 | E6: =G$1*C6 -> 2
B7: Azucar Común | C7: 150 | D7: =C7*'Valores y Totales'!C7 -> 210 | E7: =G$1*C7 -> 150
B8: Maizena | C8: 300 | D8: =C8*'Valores y Totales'!C8 -> 630 | E8: =G$1*C8 -> 300
B9: Chocolate Taza | C9: 0 | D9: =C9*'Valores y Totales'!C9 -> 0 | E9: =G$1*C9 -> 0
B10: Nueces | C10: 0 | D10: =C10*'Valores y Totales'!C10 -> 0 | E10: =G$1*C10 -> 0
B11: Dulce de Leche | C11: 1000 | D11: =C11*'Valores y Totales'!C11 -> 5000 | E11: =G$1*C11 -> 1000
B12: Crema | C12: 0 | D12: =C12*'Valores y Totales'!C12 -> 0 | E12: =G$1*C12 -> 0
B13: Harina Leudante | C13: 0 | D13: =C13*'Valores y Totales'!C13 -> 0 | E13: =G$1*C13 -> 0
B14: Limon | C14: 1 | D14: =C14*'Valores y Totales'!C14 -> 500 | E14: =G$1*C14 -> 1
B15: Bicarbonato | C15: 0 | D15: =C15*'Valores y Totales'!C15 -> 0 | E15: =G$1*C15 -> 0
B16: Polveo Hornear | C16: 10 | D16: =C16*'Valores y Totales'!C16 -> 40 | E16: =G$1*C16 -> 10
B17: Leche | C17: 0 | D17: =C17*'Valores y Totales'!C17 -> 0 | E17: =G$1*C17 -> 0
B18: Conac | C18: 20 | D18: =C18*'Valores y Totales'!C18 -> 266.66667 | E18: =G$1*C18 -> 20
... B26: Chocochips | C26: 0 | D26: =C26*'Valores y Totales'!C26 -> 0 | E26: =G$1*C26 -> 0
C28: Una Receta | D28: Por Cantidad de Recetas
B29: Cantidad de Masitas | C29: 80 | D29: =C29*G$1 -> 80 | E29: 3cm | F29: Masa Estirada Gruesa
B30: Costo Receta | C30: =SUM(D2:D21) -> 9486.6667 | D30: =C30*G$1 -> 9486.6667
B31: Costo Docena | C31: =C30/C29*12 -> 1423 | D31: =C31 -> 1423
B32: Costo Individual | C32: =C30/C29 -> 118.58333 | D32: =C32 -> 118.58333

Sheet Masitas de Manteca (choc)
B1: Ingrediente | C1: Gramos | D1: Precio | E1: Total Recetas | F1: Cantidad de Recetas: | G1: 1
B2: Manteca | C2: 115 | D2: =C2*'Valores y Totales'!C2 -> 1265 | E2: =G$1*C2 -> 115
B3: Harina 0000 | C3: 220 | D3: =C3*'Valores y Totales'!C3 -> 242 | E3: =G$1*C3 -> 220
B4: Azucar Impalpable | C4: 115 | D4: =C4*'Valores y Totales'!C4 -> 172.5 | E4: =G$1*C4 -> 115
B5: Cacao | C5: 25 | D5: =C5*'Valores y Totales'!C5 -> 625 | E5: =G$1*C5 -> 25
B6: Huevo (unidad) | C6: 1 | D6: =C6*'Valores y Totales'!C6 -> 210 | E6: =G$1*C6 -> 1
B7: Azucar Común | C7: 0 | D7: =C7*'Valores y Totales'!C7 -> 0 | E7: =G$1*C7 -> 0
B8: Maizena | C8: 0 | D8: =C8*'Valores y Totales'!C8 -> 0 | E8: =G$1*C8 -> 0
B9: Chocolate Taza | C9: 0 | D9: =C9*'Valores y Totales'!C9 -> 0 | E9: =G$1*C9 -> 0
B10: Nueces | C10: 0 | D10: =C10*'Valores y Totales'!C10 -> 0 | E10: =G$1*C10 -> 0
B11: Dulce de Leche | C11: 0 | D11: =C11*'Valores y Totales'!C11 -> 0 | E11: =G$1*C11 -> 0
B12: Crema | C12: 0 | D12: =C12*'Valores y Totales'!C12 -> 0 | E12: =G$1*C12 -> 0
B13: Harina Leudante | C13: 0 | D13: =C13*'Valores y Totales'!C13 -> 0 | E13: =G$1*C13 -> 0
... B26: Chocochips | C26: 0 | D26: =C26*'Valores y Totales'!C26 -> 0 | E26: =G$1*C26 -> 0
C28: Una Receta | D28: Por Cantidad de Recetas
B29: Cantidad de Masitas | C29: 50 | D29: =C29*G$1 -> 50
B30: Costo Receta | C30: =SUM(D2:D20) -> 2514.5 | D30: =C30*G$1 -> 2514.5
B31: Costo Docena | C31: =C30/C29*12 -> 603.48 | D31: =C31 -> 603.48
B32: Costo Individual | C32: =C30/C29 -> 50.29 | D32: =C32 -> 50.29

Sheet Alfajores de Mani
B1: Ingrediente | C1: Gramos | D1: Precio | E1: Total Recetas | F1: Cantidad de Recetas: | G1: 1
B2: Manteca | C2: 200 | D2: =C2*'Valores y Totales'!C2 -> 2200 | E2: =G$1*C2 -> 200
B3: Harina 0000 | C3: 250 | D3: =C3*'Valores y Totales'!C3 -> 275 | E3: =G$1*C3 -> 250
B4: Azucar Impalpable | C4: 0 | D4: =C4*'Valores y Totales'!C4 -> 0 | E4: =G$1*C4 -> 0
B5: Cacao | C5: 0 | D5: =C5*'Valores y Totales'!C5 -> 0 | E5: =G$1*C5 -> 0
B6: Huevo (unidad) | C6: 1 | D6: =C6*'Valores y Totales'!C6 -> 210 | E6: =G$1*C6 -> 1
B7: Azucar Común | C7: 0 | D7: =C7*'Valores y Totales'!C7 -> 0 | E7: =G$1*C7 -> 0
B8: Maizena | C8: 0 | D8: =C8*'Valores y Totales'!C8 -> 0 | E8: =G$1*C8 -> 0
B9: Chocolate Taza | C9: 150 | D9: =C9*'Valores y Totales'!C9 -> 3900 | E9: =G$1*C9 -> 150
B10: Mani | C10: 200 | D10: =C10*'Valores y Totales'!C53 -> 520 | E10: =G$1*C10 -> 200
B11: Dulce de Leche | C11: 500 | D11: =C11*'Valores y Totales'!C11 -> 2500 | E11: =G$1*C11 -> 500
B12: Pasta de Mani | C12: 200 | D12: =C12*'Valores y Totales'!C54 -> 1260 | E12: =G$1*C12 -> 200
B13: Harina Leudante | C13: 0 | D13: =C13*'Valores y Totales'!C13 -> 0 | E13: =G$1*C13 -> 0
B14: Limon | C14: 0 | D14: =C14*'Valores y Totales'!C14 -> 0 | E14: =G$1*C14 -> 0
B15: Azucar Negro | C15: 200 | D15: =C15*'Valores y Totales'!C20 -> 460 | E15: =G$1*C15 -> 200
B16: Chocolate Banio | C16: 150 | D16: =C16*'Valores y Totales'!C21 -> 1500 | E16: =G$1*C16 -> 150
B17: Biscochuelo | C17: 0 | D17: =C17*'Valores y Totales'!C22 -> 0 | E17: =G$1*C17 -> 0
B18: Ciruelas | C18: 0 | D18: =C18*'Valores y Totales'!C23 -> 0 | E18: =G$1*C18 -> 0
B19: Pasas | C19: 0 | D19: =C19*'Valores y Totales'!C24 -> 0 | E19: =G$1*C19 -> 0
B20: Yogur | C20: 0 | D20: =C20*'Valores y Totales'!C25 -> 0 | E20: =G$1*C20 -> 0
B21: Chocochips | C21: 0 | D21: =C21*'Valores y Totales'!C26 -> 0 | E21: =G$1*C21 -> 0
C23: Una Receta | D23: Por Cantidad de Recetas
B24: Cantidad de Masitas | C24: 60 | D24: =C24*G$1 -> 60
B25: Costo Receta | C25: =SUM(D2:D21) -> 12825 | D25: =C25*G$1 -> 12825
B26: Costo Docena | C26: =C25/C24*12 -> 2565 | D26: =C26 -> 2565
B27: Costo Individual | C27: =C25/C24 -> 213.75 | D27: =C27 -> 213.75

Sheet Alfajores de Nuez
B1: Ingrediente | C1: Gramos | D1: Precio | E1: Total Recetas | F1: Cantidad de Recetas: | G1: 1
B2: Manteca | C2: 200 | D2: =C2*'Valores y Totales'!C2 -> 2200 | E2: =G$1*C2 -> 200
B3: Harina 0000 | C3: 250 | D3: =C3*'Valores y Totales'!C3 -> 275 | E3: =G$1*C3 -> 250
B4: Azucar Impalpable | C4: 0 | D4: =C4*'Valores y Totales'!C4 -> 0 | E4: =G$1*C4 -> 0
B5: Cacao | C5: 0 | D5: =C5*'Valores y Totales'!C5 -> 0 | E5: =G$1*C5 -> 0
B6: Huevo (unidad) | C6: 1 | D6: =C6*'Valores y Totales'!C6 -> 210 | E6: =G$1*C6 -> 1
B7: Azucar Común | C7: 0 | D7: =C7*'Valores y Totales'!C7 -> 0 | E7: =G$1*C7 -> 0
B8: Maizena | C8: 0 | D8: =C8*'Valores y Totales'!C8 -> 0 | E8: =G$1*C8 -> 0
B9: Chocolate Taza | C9: 0 | D9: =C9*'Valores y Totales'!C9 -> 0 | E9: =G$1*C9 -> 0
B10: Nueces | C10: 200 | D10: =C10*'Valores y Totales'!C10 -> 4400 | E10: =G$1*C10 -> 200
B11: Dulce de Leche | C11: 1000 | D11: =C11*'Valores y Totales'!C11 -> 5000 | E11: =G$1*C11 -> 1000
B12: Crema | C12: 0 | D12: =C12*'Valores y Totales'!C12 -> 0 | E12: =G$1*C12 -> 0
B13: Harina Leudante | C13: 0 | D13: =C13*'Valores y Totales'!C13 -> 0 | E13: =G$1*C13 -> 0
... B26: Chocochips | C26: 0 | D26: =C26*'Valores y Totales'!C26 -> 0 | E26: =G$1*C26 -> 0
C28: Una Receta | D28: Por Cantidad de Recetas
B29: Cantidad de Masitas | C29: 60 | D29: =C29*G$1 -> 60
B30: Costo Receta | C30: =SUM(D2:D26) -> 12545 | D30: =C30*G$1 -> 12545
B31: Costo Docena | C31: =C30/C29*12 -> 2509 | D31: =C31 -> 2509
B32: Costo Individual | C32: =C30/C29 -> 209.08333 | D32: =C32 -> 209.08333

Sheet Torta Vainilla
B1: Ingrediente | C1: Gramos | D1: Precio | E1: Total Recetas | F1: Cantidad de Recetas: | G1: 1
B2: Manteca | C2: 200 | D2: =C2*'Valores y Totales'!C2 -> 2200 | E2: =G$1*C2 -> 200
B3: Harina 0000 | C3: 200 | D3: =C3*'Valores y Totales'!C3 -> 220 | E3: =G$1*C3 -> 200
B4: Azucar Impalpable | C4: 0 | D4: =C4*'Valores y Totales'!C4 -> 0 | E4: =G$1*C4 -> 0
B5: Cacao | C5: 0 | D5: =C5*'Valores y Totales'!C5 -> 0 | E5: =G$1*C5 -> 0
B6: Huevo (unidad) | C6: 3 | D6: =C6*'Valores y Totales'!B6 -> 630 | E6: =G$1*C6 -> 3
B7: Azucar Común | C7: 200 | D7: =C7*'Valores y Totales'!C7 -> 280 | E7: =G$1*C7 -> 200
B8: Maizena | C8: 0 | D8: =C8*'Valores y Totales'!C8 -> 0 | E8: =G$1*C8 -> 0
B9: Chocolate Taza | C9: 0 | D9: =C9*'Valores y Totales'!C9 -> 0 | E9: =G$1*C9 -> 0
B10: Nueces | C10: 0 | D10: =C10*'Valores y Totales'!C10 -> 0 | E10: =G$1*C10 -> 0
B11: Dulce de Leche | C11: 0 | D11: =C11*'Valores y Totales'!C11 -> 0 | E11: =G$1*C11 -> 0
B12: Crema | C12: 0 | D12: =C12*'Valores y Totales'!C12 -> 0 | E12: =G$1*C12 -> 0
B13: Harina Leudante | C13: 0 | D13: =C13*'Valores y Totales'!C13 -> 0 | E13: =G$1*C13 -> 0
B14: Limon | C14: 0 | D14: =C14*'Valores y Totales'!C14 -> 0 | E14: =G$1*C14 -> 0
B15: Bicarbonato | C15: 0 | D15: =C15*'Valores y Totales'!C15 -> 0 | E15: =G$1*C15 -> 0
B16: Polveo Hornear | C16: 5 | D16: =C16*'Valores y Totales'!C16 -> 20 | E16: =G$1*C16 -> 5
B17: Leche | C17: 0 | D17: =C17*'Valores y Totales'!C17 -> 0 | E17: =G$1*C17 -> 0
B18: Conac | C18: 0 | D18: =C18*'Valores y Totales'!C18 -> 0 | E18: =G$1*C18 -> 0
... B26: Chocochips | C26: 0 | D26: =C26*'Valores y Totales'!C26 -> 0 | E26: =G$1*C26 -> 0
C28: Una Receta | D28: Por Cantidad de Recetas
B29: Cantidad de Porciones | C29: 1 | D29: =C29*G$1 -> 1
B30: Costo Receta | C30: =SUM(D2:D20) -> 3350 | D30: =C30*G$1 -> 3350
B31: Costo Docena | C31: 0 | D31: =C31 -> 0
B32: Costo Individual | C32: =C30/C29 -> 3350 | D32: =C32 -> 3350

Sheet Torta Chocolate Mauricio Asta
B1: Ingrediente | C1: Gramos | D1: Precio | E1: Total Recetas | F1: Cantidad de Recetas: | G1: 1
B2: Manteca | C2: 115 | D2: =C2*'Valores y Totales'!C2 -> 1265 | E2: =G$1*C2 -> 115
B3: Harina 0000 | C3: 125 | D3: =C3*'Valores y Totales'!C3 -> 137.5 | E3: =G$1*C3 -> 125
B4: Azucar Impalpable | C4: 0 | D4: =C4*'Valores y Totales'!C4 -> 0 | E4: =G$1*C4 -> 0
B5: Cacao | C5: 60 | D5: =C5*'Valores y Totales'!C5 -> 1500 | E5: =G$1*C5 -> 60
B6: Huevo (unidad) | C6: 3 | D6: =C6*'Valores y Totales'!B6 -> 630 | E6: =G$1*C6 -> 3
B7: Azucar Común | C7: 0 | D7: =C7*'Valores y Totales'!C7 -> 0 | E7: =G$1*C7 -> 0
B8: Maizena | C8: 30 | D8: =C8*'Valores y Totales'!C8 -> 63 | E8: =G$1*C8 -> 30
B9: Chocolate Taza | C9: 0 | D9: =C9*'Valores y Totales'!C9 -> 0 | E9: =G$1*C9 -> 0
B10: Nueces | C10: 0 | D10: =C10*'Valores y Totales'!C10 -> 0 | E10: =G$1*C10 -> 0
B11: Dulce de Leche | C11: 0 | D11: =C11*'Valores y Totales'!C11 -> 0 | E11: =G$1*C11 -> 0
B12: Crema | C12: 0 | D12: =C12*'Valores y Totales'!C12 -> 0 | E12: =G$1*C12 -> 0
B13: Harina Leudante | C13: 0 | D13: =C13*'Valores y Totales'!C13 -> 0 | E13: =G$1*C13 -> 0
B14: Limon | C14: 0 | D14: =C14*'Valores y Totales'!C14 -> 0 | E14: =G$1*C14 -> 0
B15: Bicarbonato | C15: 0 | D15: =C15*'Valores y Totales'!C15 -> 0 | E15: =G$1*C15 -> 0
B16: Polveo Hornear | C16: 6 | D16: =C16*'Valores y Totales'!C16 -> 24 | E16: =G$1*C16 -> 6
B17: Leche | C17: 160 | D17: =C17*'Valores y Totales'!C17 -> 400 | E17: =G$1*C17 -> 160
B18: Conac | C18: 0 | D18: =C18*'Valores y Totales'!C18 -> 0 | E18: =G$1*C18 -> 0
... B26: Chocochips | C26: 0 | D26: =C26*'Valores y Totales'!C26 -> 0 | E26: =G$1*C26 -> 0
C28: Una Receta | D28: Por Cantidad de Recetas
B29: Cantidad de Porciones | C29: 1 | D29: =C29*G$1 -> 1
B30: Costo Receta | C30: =SUM(D2:D20) -> 4640.5 | D30: =C30*G$1 -> 4640.5
B32: Costo Individual | C32: =C30/C29 -> 4640.5 | D32: =C32 -> 4640.5

Sheet Torta Chocolate
B1: Ingrediente | C1: Gramos | D1: Precio | E1: Total Recetas | F1: Cantidad de Recetas: | G1: 1
B2: Manteca | C2: 250 | D2: =C2*'Valores y Totales'!C2 -> 2750 | E2: =G$1*C2 -> 250
B3: Harina 0000 | C3: 200 | D3: =C3*'Valores y Totales'!C3 -> 220 | E3: =G$1*C3 -> 200
B4: Azucar Impalpable | C4: 0 | D4: =C4*'Valores y Totales'!C4 -> 0 | E4: =G$1*C4 -> 0
B5: Cacao | C5: 50 | D5: =C5*'Valores y Totales'!C5 -> 1250 | E5: =G$1*C5 -> 50
B6: Huevo (unidad) | C6: 5 | D6: =C6*'Valores y Totales'!B6 -> 1050 | E6: =G$1*C6 -> 5
B7: Azucar Común | C7: 0 | D7: =C7*'Valores y Totales'!C7 -> 0 | E7: =G$1*C7 -> 0
B8: Maizena | C8: 0 | D8: =C8*'Valores y Totales'!C8 -> 0 | E8: =G$1*C8 -> 0
B9: Chocolate Taza | C9: 0 | D9: =C9*'Valores y Totales'!C9 -> 0 | E9: =G$1*C9 -> 0
B10: Nueces | C10: 0 | D10: =C10*'Valores y Totales'!C10 -> 0 | E10: =G$1*C10 -> 0
B11: Dulce de Leche | C11: 0 | D11: =C11*'Valores y Totales'!C11 -> 0 | E11: =G$1*C11 -> 0
B12: Crema | C12: 0 | D12: =C12*'Valores y Totales'!C12 -> 0 | E12: =G$1*C12 -> 0
B13: Harina Leudante | C13: 0 | D13: =C13*'Valores y Totales'!C13 -> 0 | E13: =G$1*C13 -> 0
B14: Limon | C14: 0 | D14: =C14*'Valores y Totales'!C14 -> 0 | E14: =G$1*C14 -> 0
B15: Bicarbonato | C15: 0 | D15: =C15*'Valores y Totales'!C15 -> 0 | E15: =G$1*C15 -> 0
B16: Polveo Hornear | C16: 10 | D16: =C16*'Valores y Totales'!C16 -> 40 | E16: =G$1*C16 -> 10
B17: Leche | C17: 0 | D17: =C17*'Valores y Totales'!C17 -> 0 | E17: =G$1*C17 -> 0
B18: Conac | C18: 0 | D18: =C18*'Valores y Totales'!C18 -> 0 | E18: =G$1*C18 -> 0
... B26: Chocochips | C26: 0 | D26: =C26*'Valores y Totales'!C26 -> 0 | E26: =G$1*C26 -> 0
C28: Una Receta | D28: Por Cantidad de Recetas
B29: Cantidad de Porciones | C29: 1 | D29: =C29*G$1 -> 1
B30: Costo Receta | C30: =SUM(D2:D20) -> 5885 | D30: =C30*G$1 -> 5885
B32: Costo Individual | C32: =C30/C29 -> 5885 | D32: =C32 -> 5885

Sheet Cupcakes Limón
B1: Ingrediente | C1: Gramos | D1: Precio | E1: Total Recetas | F1: Cantidad de Recetas: | G1: 1
B2: Manteca | C2: =110+25 -> 135 | D2: =C2*'Valores y Totales'!C2 -> 1485 | E2: =G$1*C2 -> 135
B3: Harina 0000 | C3: 300 | D3: =C3*'Valores y Totales'!C3 -> 330 | E3: =G$1*C3 -> 300
B4: Azucar Impalpable | C4: 0 | D4: =C4*'Valores y Totales'!C4 -> 0 | E4: =G$1*C4 -> 0
B5: Cacao | C5: 0 | D5: =C5*'Valores y Totales'!C5 -> 0 | E5: =G$1*C5 -> 0
B6: Huevo (unidad) | C6: =2+3 -> 5 | D6: =C6*'Valores y Totales'!B6 -> 1050 | E6: =G$1*C6 -> 5
B7: Azucar Común | C7: =160+100+200 -> 460 | D7: =C7*'Valores y Totales'!C7 -> 644 | E7: =G$1*C7 -> 460
B8: Maizena | C8: 30 | D8: =C8*'Valores y Totales'!C8 -> 63 | E8: =G$1*C8 -> 30
B9: Chocolate Taza | C9: 0 | D9: =C9*'Valores y Totales'!C9 -> 0 | E9: =G$1*C9 -> 0
B10: Nueces | C10: 0 | D10: =C10*'Valores y Totales'!C10 -> 0 | E10: =G$1*C10 -> 0
B11: Dulce de Leche | C11: 0 | D11: =C11*'Valores y Totales'!C11 -> 0 | E11: =G$1*C11 -> 0
B12: Crema | C12: 0 | D12: =C12*'Valores y Totales'!C12 -> 0 | E12: =G$1*C12 -> 0
B13: Harina Leudante | C13: 0 | D13: =C13*'Valores y Totales'!C13 -> 0 | E13: =G$1*C13 -> 0
B14: Limon | C14: =1+1 -> 2 | D14: =C14*'Valores y Totales'!C14 -> 1000 | E14: =G$1*C14 -> 2
B15: Bicarbonato | C15: 0 | D15: =C15*'Valores y Totales'!C15 -> 0 | E15: =G$1*C15 -> 0
B16: Polveo Hornear | C16: 14 | D16: =C16*'Valores y Totales'!C16 -> 56 | E16: =G$1*C16 -> 14
B17: Leche | C17: =160+250 -> 410 | D17: =C17*'Valores y Totales'!C17 -> 1025 | E17: =G$1*C17 -> 410
B18: Conac | C18: 0 | D18: =C18*'Valores y Totales'!C18 -> 0 | E18: =G$1*C18 -> 0
B19: Naranja | C19: 0 | D19: =C19*'Valores y Totales'!C19 -> 0 | E19: =G$1*C19 -> 0
B20: Azucar Negro | C20: 0 | D20: =C20*'Valores y Totales'!C20 -> 0 | E20: =G$1*C20 -> 0
B21: Chocolate Banio | C21: 0 | D21: =C21*'Valores y Totales'!C21 -> 0 | E21: =G$1*C21 -> 0
B22: Biscochuelo | C22: 0 | D22: =C22*'Valores y Totales'!C22 -> 0 | E22: =G$1*C22 -> 0
B23: Ciruelas | C23: 0 | D23: =C23*'Valores y Totales'!C23 -> 0 | E23: =G$1*C23 -> 0
B24: Pasas | C24: 0 | D24: =C24*'Valores y Totales'!C24 -> 0 | E24: =G$1*C24 -> 0
B25: Yogur | C25: 0 | D25: =C25*'Valores y Totales'!C25 -> 0 | E25: =G$1*C25 -> 0
B26: Chocochips | C26: 0 | D26: =C26*'Valores y Totales'!C26 -> 0 | E26: =G$1*C26 -> 0
B27: Leche Condensada (Unidad) | C27: 0 | D27: =C27*'Valores y Totales'!C27 -> 0 | E27: =G$1*C27 -> 0
B28: Gelatina SS (Unidad) | C28: 0 | D28: =C28*'Valores y Totales'!C28 -> 0 | E28: =G$1*C28 -> 0
B29: Frutos Rojos | C29: 0 | D29: =C29*'Valores y Totales'!C29 -> 0 | E29: =G$1*C29 -> 0
... B31: Pasta de Forrar | C31: 0 | D31: =C31*'Valores y Totales'!C31 -> 0 | E31: =G$1*C31 -> 0
B32: PIROTINES | C32: 12 | D32: 15
C36: Una Receta | D36: Por Cantidad de Recetas
B37: Cantidad de Porciones | C37: 12 | D37: =C37*G$1 -> 12
B38: Costo Receta | C38: =SUM(D2:D32) -> 5668 | D38: =C38*G$1 -> 5668

Sheet TORTA 3KG 20CM NO GANACHE
B1: Ingrediente | C1: Gramos | D1: Precio | E1: Total Recetas | F1: Cantidad de Recetas: | G1: 1
B2: Manteca | C2: 315 | D2: =C2*'Valores y Totales'!C2 -> 3465 | E2: =G$1*C2 -> 315
B3: Harina 0000 | C3: 575 | D3: =C3*'Valores y Totales'!C3 -> 632.5 | E3: =G$1*C3 -> 575
B4: Azucar Impalpable | C4: 0 | D4: =C4*'Valores y Totales'!C4 -> 0 | E4: =G$1*C4 -> 0
B5: Cacao | C5: 60 | D5: =C5*'Valores y Totales'!C5 -> 1500 | E5: =G$1*C5 -> 60
B6: Huevo (unidad) | C6: 5 | D6: =C6*'Valores y Totales'!B6 -> 1050 | E6: =G$1*C6 -> 5
B7: Azucar Común | C7: 400 | D7: =C7*'Valores y Totales'!C7 -> 560 | E7: =G$1*C7 -> 400
B8: Maizena | C8: 30 | D8: =C8*'Valores y Totales'!C8 -> 63 | E8: =G$1*C8 -> 30
B9: Chocolate Taza | C9: 0 | D9: =C9*'Valores y Totales'!C9 -> 0 | E9: =G$1*C9 -> 0
B10: Nueces | C10: 0 | D10: =C10*'Valores y Totales'!C10 -> 0 | E10: =G$1*C10 -> 0
B11: Dulce de Leche | C11: 1000 | D11: =C11*'Valores y Totales'!C11 -> 5000 | E11: =G$1*C11 -> 1000
B12: Crema | C12: 0 | D12: =C12*'Valores y Totales'!C12 -> 0 | E12: =G$1*C12 -> 0
B13: Harina Leudante | C13: 0 | D13: =C13*'Valores y Totales'!C13 -> 0 | E13: =G$1*C13 -> 0
B14: Limon | C14: 0 | D14: =C14*'Valores y Totales'!C14 -> 0 | E14: =G$1*C14 -> 0
B15: Bicarbonato | C15: 0 | D15: =C15*'Valores y Totales'!C15 -> 0 | E15: =G$1*C15 -> 0
B16: Polveo Hornear | C16: 18 | D16: =C16*'Valores y Totales'!C16 -> 72 | E16: =G$1*C16 -> 18
B17: Leche | C17: 160 | D17: =C17*'Valores y Totales'!C17 -> 400 | E17: =G$1*C17 -> 160
B18: Conac | C18: 0 | D18: =C18*'Valores y Totales'!C18 -> 0 | E18: =G$1*C18 -> 0
... B31: Pasta de Forrar | C31: 1000 | D31: =C31*'Valores y Totales'!C31 -> 6000 | E31: =G$1*C31 -> 1000
C36: Una Receta | D36: Por Cantidad de Recetas
B37: Cantidad de Porciones | C37: 1 | D37: =C37*G$1 -> 1
B38: Costo Receta | C38: =SUM(D2:D31) -> 20963.5 | D38: =C38*G$1 -> 20963.5

Sheet TORTA 3KG 20CM DIAM.
B1: Ingrediente | C1: Gramos | D1: Precio | E1: Total Recetas | F1: Cantidad de Recetas: | G1: 1
B2: Manteca | C2: 315 | D2: =C2*'Valores y Totales'!C2 -> 3465 | E2: =G$1*C2 -> 315
B3: Harina 0000 | C3: 575 | D3: =C3*'Valores y Totales'!C3 -> 632.5 | E3: =G$1*C3 -> 575
B4: Azucar Impalpable | C4: 0 | D4: =C4*'Valores y Totales'!C4 -> 0 | E4: =G$1*C4 -> 0
B5: Cacao | C5: 60 | D5: =C5*'Valores y Totales'!C5 -> 1500 | E5: =G$1*C5 -> 60
B6: Huevo (unidad) | C6: 5 | D6: =C6*'Valores y Totales'!B6 -> 1050 | E6: =G$1*C6 -> 5
B7: Azucar Común | C7: 400 | D7: =C7*'Valores y Totales'!C7 -> 560 | E7: =G$1*C7 -> 400
B8: Maizena | C8: 30 | D8: =C8*'Valores y Totales'!C8 -> 63 | E8: =G$1*C8 -> 30
B9: Chocolate Taza | C9: 0 | D9: =C9*'Valores y Totales'!C9 -> 0 | E9: =G$1*C9 -> 0
B10: Nueces | C10: 0 | D10: =C10*'Valores y Totales'!C10 -> 0 | E10: =G$1*C10 -> 0
B11: Dulce de Leche | C11: 1000 | D11: =C11*'Valores y Totales'!C11 -> 5000 | E11: =G$1*C11 -> 1000
B12: Crema | C12: 350 | D12: =C12*'Valores y Totales'!C12 -> 3500 | E12: =G$1*C12 -> 350
B13: Harina Leudante | C13: 0 | D13: =C13*'Valores y Totales'!C13 -> 0 | E13: =G$1*C13 -> 0
B14: Limon | C14: 0 | D14: =C14*'Valores y Totales'!C14 -> 0 | E14: =G$1*C14 -> 0
B15: Bicarbonato | C15: 0 | D15: =C15*'Valores y Totales'!C15 -> 0 | E15: =G$1*C15 -> 0
B16: Polveo Hornear | C16: 18 | D16: =C16*'Valores y Totales'!C16 -> 72 | E16: =G$1*C16 -> 18
B17: Leche | C17: 160 | D17: =C17*'Valores y Totales'!C17 -> 400 | E17: =G$1*C17 -> 160
B18: Conac | C18: 0 | D18: =C18*'Valores y Totales'!C18 -> 0 | E18: =G$1*C18 -> 0
... B31: Pasta de Forrar | C31: 1000 | D31: =C31*'Valores y Totales'!C31 -> 6000 | E31: =G$1*C31 -> 1000
C36: Una Receta | D36: Por Cantidad de Recetas
B37: Cantidad de Porciones | C37: 1 | D37: =C37*G$1 -> 1
B38: Costo Receta | C38: =SUM(D2:D31) -> 34463.5 | D38: =C38*G$1 -> 34463.5

Sheet Frosting Bariloche
B1: Ingrediente | C1: Gramos | D1: Precio | E1: Total Recetas | F1: Cantidad de Recetas: | G1: 1
B2: Manteca | C2: 0 | D2: =C2*'Valores y Totales'!C2 -> 0 | E2: =G$1*C2 -> 0
B3: Harina 0000 | C3: 0 | D3: =C3*'Valores y Totales'!C3 -> 0 | E3: =G$1*C3 -> 0
B4: Azucar Impalpable | C4: 0 | D4: =C4*'Valores y Totales'!C4 -> 0 | E4: =G$1*C4 -> 0
B5: Cacao | C5: 0 | D5: =C5*'Valores y Totales'!C5 -> 0 | E5: =G$1*C5 -> 0
B6: Huevo (unidad) | C6: 0 | D6: =C6*'Valores y Totales'!B6 -> 0 | E6: =G$1*C6 -> 0
B7: Azucar Común | C7: 0 | D7: =C7*'Valores y Totales'!C7 -> 0 | E7: =G$1*C7 -> 0
B8: Maizena | C8: 0 | D8: =C8*'Valores y Totales'!C8 -> 0 | E8: =G$1*C8 -> 0
B9: Chocolate Taza | C9: 150 | D9: =C9*'Valores y Totales'!C9 -> 3900 | E9: =G$1*C9 -> 150
B10: Nueces | C10: 0 | D10: =C10*'Valores y Totales'!C10 -> 0 | E10: =G$1*C10 -> 0
B11: Dulce de Leche | C11: 400 | D11: =C11*'Valores y Totales'!C11 -> 2000 | E11: =G$1*C11 -> 400
B12: Crema | C12: 120 | D12: =C12*'Valores y Totales'!C12 -> 1200 | E12: =G$1*C12 -> 120
B13: Harina Leudante | C13: 0 | D13: =C13*'Valores y Totales'!C13 -> 0 | E13: =G$1*C13 -> 0
B14: Limon | C14: 0 | D14: =C14*'Valores y Totales'!C14 -> 0 | E14: =G$1*C14 -> 0
B15: Bicarbonato | C15: 0 | D15: =C15*'Valores y Totales'!C15 -> 0 | E15: =G$1*C15 -> 0
B16: Polveo Hornear | C16: 0 | D16: =C16*'Valores y Totales'!C16 -> 0 | E16: =G$1*C16 -> 0
B17: Leche | C17: 0 | D17: =C17*'Valores y Totales'!C17 -> 0 | E17: =G$1*C17 -> 0
B18: Conac | C18: 30 | D18: =C18*'Valores y Totales'!C18 -> 400 | E18: =G$1*C18 -> 30
... B26: Chocochips | C26: 0 | D26: =C26*'Valores y Totales'!C26 -> 0 | E26: =G$1*C26 -> 0
C28: Una Receta | D28: Por Cantidad de Recetas
B29: Cantidad de Porciones | C29: 1 | D29: 1
B30: Costo Receta | C30: =SUM(D2:D26) -> 7500 | D30: =C30*G$1 -> 7500
B31: Costo Docena | C31: 0 | D31: 0
B32: Costo Individual | C32: =C30/C29 -> 7500 | D32: =C32 -> 7500

Sheet Cookies Pasas y Nueces
B1: Ingrediente | C1: Gramos | D1: Precio | E1: Total Recetas | F1: Cantidad de Recetas: | G1: 1
B2: Manteca | C2: 200 | D2: =C2*'Valores y Totales'!C2 -> 2200 | E2: =G$1*C2 -> 200
B3: Harina 0000 | C3: 450 | D3: =C3*'Valores y Totales'!C3 -> 495 | E3: =G$1*C3 -> 450
B4: Azucar Impalpable | C4: 0 | D4: =C4*'Valores y Totales'!C4 -> 0 | E4: =G$1*C4 -> 0
B5: Cacao | C5: 0 | D5: =C5*'Valores y Totales'!C5 -> 0 | E5: =G$1*C5 -> 0
B6: Huevo (unidad) | C6: 2 | D6: =C6*'Valores y Totales'!B6 -> 420 | E6: =G$1*C6 -> 2
B7: Azucar Común | C7: 400 | D7: =C7*'Valores y Totales'!C7 -> 560 | E7: =G$1*C7 -> 400
B8: Maizena | C8: 0 | D8: =C8*'Valores y Totales'!C8 -> 0 | E8: =G$1*C8 -> 0
B9: Chocolate Taza | C9: 0 | D9: =C9*'Valores y Totales'!C9 -> 0 | E9: =G$1*C9 -> 0
B10: Nueces | C10: 150 | D10: =C10*'Valores y Totales'!C10 -> 3300 | E10: =G$1*C10 -> 150
B11: Dulce de Leche | C11: 0 | D11: =C11*'Valores y Totales'!C11 -> 0 | E11: =G$1*C11 -> 0
B12: Crema | C12: 0 | D12: =C12*'Valores y Totales'!C12 -> 0 | E12: =G$1*C12 -> 0
B13: Harina Leudante | C13: 0 | D13: =C13*'Valores y Totales'!C13 -> 0 | E13: =G$1*C13 -> 0
B14: Limon | C14: 0 | D14: =C14*'Valores y Totales'!C14 -> 0 | E14: =G$1*C14 -> 0
B15: Bicarbonato | C15: 0 | D15: =C15*'Valores y Totales'!C15 -> 0 | E15: =G$1*C15 -> 0
B16: Polveo Hornear | C16: 15 | D16: =C16*'Valores y Totales'!C16 -> 60 | E16: =G$1*C16 -> 15
B17: Leche | C17: 0 | D17: =C17*'Valores y Totales'!C17 -> 0 | E17: =G$1*C17 -> 0
B18: Conac | C18: 0 | D18: =C18*'Valores y Totales'!C18 -> 0 | E18: =G$1*C18 -> 0
... B26: Chocochips | C26: 0 | D26: =C26*'Valores y Totales'!C26 -> 0 | E26: =G$1*C26 -> 0
C28: Una Receta | D28: Por Cantidad de Recetas
B29: Cantidad de Porciones | C29: 100 | D29: =C29*G$1 -> 100
B30: Costo Receta | C30: =SUM(D2:D26) -> 7758.15 | D30: =C30*G$1 -> 7758.15
B31: Costo Docena | C31: =C30/C29*12 -> 930.978 | D31: =C31 -> 930.978
B32: Costo Individual | C32: =C30/C29 -> 77.5815 | D32: =C32 -> 77.5815
B33: Las masitas son de 5 cm de diámetro

Sheet Masitas de Manteca
B1: Ingrediente | C1: Gramos | D1: Precio | E1: Total Recetas | F1: Cantidad de Recetas: | G1: 1
B2: Manteca | C2: 250 | D2: =C2*'Valores y Totales'!C2 -> 2750 | E2: =G$1*C2 -> 250
B3: Harina 0000 | C3: 500 | D3: =C3*'Valores y Totales'!C3 -> 550 | E3: =G$1*C3 -> 500
B4: Azucar Impalpable | C4: 0 | D4: =C4*'Valores y Totales'!C4 -> 0 | E4: =G$1*C4 -> 0
B5: Cacao | C5: 0 | D5: =C5*'Valores y Totales'!C5 -> 0 | E5: =G$1*C5 -> 0
B6: Huevo (unidad) | C6: 1 | D6: =C6*'Valores y Totales'!C6 -> 210 | E6: =G$1*C6 -> 1
B7: Azucar Común | C7: 220 | D7: =C7*'Valores y Totales'!C7 -> 308 | E7: =G$1*C7 -> 220
B8: Maizena | C8: 0 | D8: =C8*'Valores y Totales'!C8 -> 0 | E8: =G$1*C8 -> 0
B9: Chocolate Taza | C9: 0 | D9: =C9*'Valores y Totales'!C9 -> 0 | E9: =G$1*C9 -> 0
B10: Nueces | C10: 0 | D10: =C10*'Valores y Totales'!C10 -> 0 | E10: =G$1*C10 -> 0
B11: Dulce de Leche | C11: 0 | D11: =C11*'Valores y Totales'!C11 -> 0 | E11: =G$1*C11 -> 0
B12: Crema | C12: 0 | D12: =C12*'Valores y Totales'!C12 -> 0 | E12: =G$1*C12 -> 0
B13: Harina Leudante | C13: 0 | D13: =C13*'Valores y Totales'!C13 -> 0 | E13: =G$1*C13 -> 0
... B26: Chocochips | C26: 0 | D26: =C26*'Valores y Totales'!C26 -> 0 | E26: =G$1*C26 -> 0
C28: Una Receta | D28: Por Cantidad de Recetas
B29: Cantidad de Masitas | C29: 40 | D29: =C29*G$1 -> 40
B30: Costo Receta | C30: =SUM(D2:D20) -> 3818 | D30: =C30*G$1 -> 3818
B31: Costo Docena | C31: =C30/C29*12 -> 1145.4 | D31: =C31 -> 1145.4
B32: Costo Individual | C32: =C30/C29 -> 95.45 | D32: =C32 -> 95.45

Sheet Caja dia del padre
F3: Caja | G3: 100 | H3: 1 | I3: =H3*G3 -> 100 | K3: Caja | L3: 600
F4: Champagne | G4: 250 | H4: 1 | I4: =H4*G4 -> 250 | K4: Caja Con Champu | L4: 750
F5: Alfajor de Maicena | G5: 19 | H5: 3 | I5: =H5*G5 -> 57
F6: Alfajor de Choco Nutella | G6: 52 | H6: 3 | I6: =H6*G6 -> 156
F7: Alfajor de Nuez | G7: 27 | H7: 3 | I7: =H7*G7 -> 81
F8: Meteorito | G8: 27 | H8: 3 | I8: =H8*G8 -> 81
F9: Galletitas+Imagen | G9: =(3.26)*3+10 -> 19.78 | H9: 1 | I9: 25
F10: Galletitas+Pasta | G10: =(3.26+2.5)*3 -> 17.28 | H10: 1 | I10: 25
F11: Tarjeta | H11: 1 | I11: 7
F12: Cookies Chocochips | H12: 6 | I12: 36
I14: =SUM(I3:I13) -> 818

Sheet Cookies Chocochips
B1: Ingrediente | C1: Gramos | D1: Precio | E1: Total Recetas | F1: Cantidad de Recetas: | G1: 1
B2: Manteca | C2: 200 | D2: =C2*'Valores y Totales'!C2 -> 2200 | E2: =G$1*C2 -> 200
B3: Harina 0000 | C3: 400 | D3: =C3*'Valores y Totales'!C3 -> 440 | E3: =G$1*C3 -> 400
B4: Azucar Impalpable | C4: 0 | D4: =C4*'Valores y Totales'!C4 -> 0 | E4: =G$1*C4 -> 0
B5: Cacao | C5: 50 | D5: =C5*'Valores y Totales'!C5 -> 1250 | E5: =G$1*C5 -> 50
B6: Huevo (unidad) | C6: 2 | D6: =C6*'Valores y Totales'!B6 -> 420 | E6: =G$1*C6 -> 2
B7: Azucar Común | C7: 0 | D7: =C7*'Valores y Totales'!C7 -> 0 | E7: =G$1*C7 -> 0
B8: Maizena | C8: 0 | D8: =C8*'Valores y Totales'!C8 -> 0 | E8: =G$1*C8 -> 0
B9: Chocolate Taza | C9: 0 | D9: =C9*'Valores y Totales'!C9 -> 0 | E9: =G$1*C9 -> 0
B10: Nueces | C10: 0 | D10: =C10*'Valores y Totales'!C10 -> 0 | E10: =G$1*C10 -> 0
B11: Dulce de Leche | C11: 0 | D11: =C11*'Valores y Totales'!C11 -> 0 | E11: =G$1*C11 -> 0
B12: Crema | C12: 0 | D12: =C12*'Valores y Totales'!C12 -> 0 | E12: =G$1*C12 -> 0
B13: Harina Leudante | C13: 0 | D13: =C13*'Valores y Totales'!C13 -> 0 | E13: =G$1*C13 -> 0
B14: Limon | C14: 0 | D14: =C14*'Valores y Totales'!C14 -> 0 | E14: =G$1*C14 -> 0
B15: Bicarbonato | C15: 0 | D15: =C15*'Valores y Totales'!C15 -> 0 | E15: =G$1*C15 -> 0
B16: Polveo Hornear | C16: 15 | D16: =C16*'Valores y Totales'!C16 -> 60 | E16: =G$1*C16 -> 15
B17: Leche | C17: 0 | D17: =C17*'Valores y Totales'!C17 -> 0 | E17: =G$1*C17 -> 0
B18: Conac | C18: 0 | D18: =C18*'Valores y Totales'!C18 -> 0 | E18: =G$1*C18 -> 0
... B26: Chocochips | C26: 150 | D26: =C26*'Valores y Totales'!C26 -> 1200 | E26: =G$1*C26 -> 150
C27: Una Receta | D27: Por Cantidad de Recetas
B28: Cantidad de Porciones | C28: 66 | D28: =C28*G$1 -> 66
B29: Costo Receta | C29: =SUM(D2:D26) -> 6490 | D29: =C29*G$1 -> 6490
B30: Costo Docena | C30: =C29/C28*12 -> 1180 | D30: =C30 -> 1180
B31: Costo Individual | C31: =C29/C28 -> 98.333333 | D31: =C31 -> 98.333333
B32: Las masitas son de 5 cm de diámetro

Sheet Brownies
B1: Ingrediente | C1: Gramos | D1: Precio | E1: Total Recetas | F1: Cantidad de Recetas: | G1: 1
B2: Manteca | C2: 300 | D2: =C2*'Valores y Totales'!C2 -> 3300 | E2: =G$1*C2 -> 300
B3: Harina 0000 | C3: 200 | D3: =C3*'Valores y Totales'!C3 -> 220 | E3: =G$1*C3 -> 200
B4: Azucar Impalpable | C4: 0 | D4: =C4*'Valores y Totales'!C4 -> 0 | E4: =G$1*C4 -> 0
B5: Cacao | C5: 0 | D5: =C5*'Valores y Totales'!C5 -> 0 | E5: =G$1*C5 -> 0
B6: Huevo (unidad) | C6: 6 | D6: =C6*'Valores y Totales'!B6 -> 1260 | E6: =G$1*C6 -> 6
B7: Azucar Común | C7: 300 | D7: =C7*'Valores y Totales'!C7 -> 420 | E7: =G$1*C7 -> 300
B8: Maizena | C8: 0 | D8: =C8*'Valores y Totales'!C8 -> 0 | E8: =G$1*C8 -> 0
B9: Chocolate Taza | C9: 360 | D9: =C9*'Valores y Totales'!C9 -> 9360 | E9: =G$1*C9 -> 360
B10: Nueces | C10: 0 | D10: =C10*'Valores y Totales'!C10 -> 0 | E10: =G$1*C10 -> 0
B11: Dulce de Leche | C11: 0 | D11: =C11*'Valores y Totales'!C11 -> 0 | E11: =G$1*C11 -> 0
B12: Crema | C12: 0 | D12: =C12*'Valores y Totales'!C12 -> 0 | E12: =G$1*C12 -> 0
B13: Harina Leudante | C13: 0 | D13: =C13*'Valores y Totales'!C13 -> 0 | E13: =G$1*C13 -> 0
B14: Limon | C14: 0 | D14: =C14*'Valores y Totales'!C14 -> 0 | E14: =G$1*C14 -> 0
B15: Bicarbonato | C15: 0 | D15: =C15*'Valores y Totales'!C15 -> 0 | E15: =G$1*C15 -> 0
B16: Polveo Hornear | C16: 0 | D16: =C16*'Valores y Totales'!C16 -> 0 | E16: =G$1*C16 -> 0
B17: Leche | C17: 0 | D17: =C17*'Valores y Totales'!C17 -> 0 | E17: =G$1*C17 -> 0
B18: Conac | C18: 0 | D18: =C18*'Valores y Totales'!C18 -> 0 | E18: =G$1*C18 -> 0
... B26: Chocochips | C26: 0 | D26: =C26*'Valores y Totales'!C26 -> 0 | E26: =G$1*C26 -> 0
C28: Una Receta | D28: Por Cantidad de Recetas
B29: Cantidad de Porciones | C29: 60 | D29: =C29*G$1 -> 60
B30: Costo Receta | C30: =SUM(D2:D26) -> 15388 | D30: =C30*G$1 -> 15388
B31: Costo Docena | D31: =C31 -> 0
B32: Costo Individual | C32: =C30/C29 -> 256.46667 | D32: =C32 -> 256.46667

Sheet Crema de Naranja
B1: Ingrediente | C1: Gramos | D1: Precio | E1: Total Recetas | F1: Cantidad de Recetas: | G1: 1
B2: Manteca | C2: 0 | D2: =C2*'Valores y Totales'!C2 -> 0 | E2: =G$1*C2 -> 0
B3: Harina 0000 | C3: 0 | D3: =C3*'Valores y Totales'!C3 -> 0 | E3: =G$1*C3 -> 0
B4: Azucar Impalpable | C4: 200 | D4: =C4*'Valores y Totales'!C4 -> 300 | E4: =G$1*C4 -> 200
B5: Cacao | C5: 0 | D5: =C5*'Valores y Totales'!C5 -> 0 | E5: =G$1*C5 -> 0
B6: Huevo (unidad) | C6: 0 | D6: =C6*'Valores y Totales'!B6 -> 0 | E6: =G$1*C6 -> 0
B7: Azucar Común | C7: 0 | D7: =C7*'Valores y Totales'!C7 -> 0 | E7: =G$1*C7 -> 0
B8: Maizena | C8: 0 | D8: =C8*'Valores y Totales'!C8 -> 0 | E8: =G$1*C8 -> 0
B9: Chocolate Taza | C9: 0 | D9: =C9*'Valores y Totales'!C9 -> 0 | E9: =G$1*C9 -> 0
B10: Nueces | C10: 0 | D10: =C10*'Valores y Totales'!C10 -> 0 | E10: =G$1*C10 -> 0
B11: Dulce de Leche | C11: 0 | D11: =C11*'Valores y Totales'!C11 -> 0 | E11: =G$1*C11 -> 0
B12: Crema | C12: 0 | D12: =C12*'Valores y Totales'!C12 -> 0 | E12: =G$1*C12 -> 0
B13: Harina Leudante | C13: 0 | D13: =C13*'Valores y Totales'!C13 -> 0 | E13: =G$1*C13 -> 0
B14: Limon | C14: 1 | D14: =C14*'Valores y Totales'!C14 -> 500 | E14: =G$1*C14 -> 1
B15: Bicarbonato | C15: 0 | D15: =C15*'Valores y Totales'!C15 -> 0 | E15: =G$1*C15 -> 0
B16: Polveo Hornear | C16: 0 | D16: =C16*'Valores y Totales'!C16 -> 0 | E16: =G$1*C16 -> 0
B17: Leche | C17: 0 | D17: =C17*'Valores y Totales'!C17 -> 0 | E17: =G$1*C17 -> 0
B18: Conac | C18: 0 | D18: =C18*'Valores y Totales'!C18 -> 0 | E18: =G$1*C18 -> 0
B19: Naranja | C19: 0 | D19: =C19*'Valores y Totales'!C19 -> 0 | E19: =G$1*C19 -> 0
B20: Azucar Negro | C20: 0 | D20: =C20*'Valores y Totales'!C20 -> 0 | E20: =G$1*C20 -> 0 | I20: 76.2
B21: Chocolate Banio | C21: 0 | D21: =C21*'Valores y Totales'!C21 -> 0 | E21: =G$1*C21 -> 0 | I21: 20
B22: Biscochuelo | C22: 0 | D22: =C22*'Valores y Totales'!C22 -> 0 | E22: =G$1*C22 -> 0 | I22: =C33/4 -> 920
B23: Ciruelas | C23: 0 | D23: =C23*'Valores y Totales'!C23 -> 0 | E23: =G$1*C23 -> 0
B24: Pasas | C24: 0 | D24: =C24*'Valores y Totales'!C24 -> 0 | E24: =G$1*C24 -> 0 | I24: =SUM(I20:I22)*3 -> 3048.6
B25: Yogur | C25: 0 | D25: =C25*'Valores y Totales'!C25 -> 0 | E25: =G$1*C25 -> 0
B26: Chocochips | C26: 0 | D26: =C26*'Valores y Totales'!C26 -> 0 | E26: =G$1*C26 -> 0
B27: Queso Crema | C27: 320 | D27: =C27*'Valores y Totales'!C38 -> 2880 | E27: =G$1*C27 -> 320
C29: Una Receta | D29: Por Cantidad de Recetas
B30: Cantidad de Porciones | C30: 1 | D30: =C30*G$1 -> 1
B31: Costo Receta | C31: =SUM(D2:D28) -> 3680 | D31: =C31*G$1 -> 3680
B32: Costo Docena
B33: Costo Individual | C33: =C31/C30 -> 3680 | D33: =C33 -> 3680

Sheet Torta Manteca ODRA
B1: Ingrediente | C1: Gramos | D1: Precio | E1: Total Recetas | F1: Cantidad de Recetas: | G1: 1
B2: Manteca | C2: 250 | D2: =C2*'Valores y Totales'!C2 -> 2750 | E2: =G$1*C2 -> 250
B3: Harina 0000 | C3: 250 | D3: =C3*'Valores y Totales'!C3 -> 275 | E3: =G$1*C3 -> 250
B4: Azucar Impalpable | C4: 0 | D4: =C4*'Valores y Totales'!C4 -> 0 | E4: =G$1*C4 -> 0
B5: Cacao | C5: 30 | D5: =C5*'Valores y Totales'!C5 -> 750 | E5: =G$1*C5 -> 30 | H5: Pnemos cacao para estandarizar
B6: Huevo (unidad) | C6: 5 | D6: =C6*'Valores y Totales'!B6 -> 1050 | E6: =G$1*C6 -> 5
B7: Azucar Común | C7: 250 | D7: =C7*'Valores y Totales'!C7 -> 350 | E7: =G$1*C7 -> 250
B8: Maizena | C8: 0 | D8: =C8*'Valores y Totales'!C8 -> 0 | E8: =G$1*C8 -> 0
B9: Chocolate Taza | C9: 60 | D9: =C9*'Valores y Totales'!C9 -> 1560 | E9: =G$1*C9 -> 60
B10: Nueces | C10: 0 | D10: =C10*'Valores y Totales'!C10 -> 0 | E10: =G$1*C10 -> 0
B11: Dulce de Leche | C11: 0 | D11: =C11*'Valores y Totales'!C11 -> 0 | E11: =G$1*C11 -> 0
B12: Crema | C12: 0 | D12: =C12*'Valores y Totales'!C12 -> 0 | E12: =G$1*C12 -> 0
B13: Harina Leudante | C13: 0 | D13: =C13*'Valores y Totales'!C13 -> 0 | E13: =G$1*C13 -> 0
B14: Limon | C14: 0 | D14: =C14*'Valores y Totales'!C14 -> 0 | E14: =G$1*C14 -> 0
B15: Bicarbonato | C15: 0 | D15: =C15*'Valores y Totales'!C15 -> 0 | E15: =G$1*C15 -> 0
B16: Polveo Hornear | C16: 10 | D16: =C16*'Valores y Totales'!C16 -> 40 | E16: =G$1*C16 -> 10
B17: Leche | C17: 0 | D17: =C17*'Valores y Totales'!C17 -> 0 | E17: =G$1*C17 -> 0
B18: Conac | C18: 0 | D18: =C18*'Valores y Totales'!C18 -> 0 | E18: =G$1*C18 -> 0
... B26: Chocochips | C26: 0 | D26: =C26*'Valores y Totales'!C26 -> 0 | E26: =G$1*C26 -> 0
C28: Una Receta | D28: Por Cantidad de Recetas
B29: Cantidad de Porciones | C29: 1 | D29: =C29*G$1 -> 1
B30: Costo Receta | C30: =SUM(D2:D20) -> 6775 | D30: =C30*G$1 -> 6775
B32: Costo Individual | C32: =C30/C29 -> 6775 | D32: =C32 -> 6775
